Workbook

Sheet MASTER_TERM_REGISTRY
A1: This is the only part I don't like. I love that it leans back, but I wish I could stop it from leaning back. Oh. I pushed it. I know I would never stop it. Well, I guess not. Let's see, hold on. I like these, these. I've watched this one video and they're like this is the the backs that you need to get. But it's not this one. Hello. OK, then OK. Try now and then tell me when you wanna stop weather. Oh yeah, yeah. It's like a. Oh yeah, yeah. OK. Now I get it. I've been really debating to get this type. I watch this one guy that. Apparently he knows a lot about chairs and. He said that these are the best. Yeah, he said. Yeah, yeah, I didn't either. But yeah, it was to him. Do you want to try for a bit? Yeah. OK. It worked out OK. Perch on the edge of that one. I mean, it's just a bad habit. This one. Well, another thing I like about this one is my arms are above the table. On that, on the chair that you're taking. My arms are here, so it's always like that. Like my arms 3. Yeah, it is. Works. | B1: category | C1: fruit_mapping | D1: tier | E1: weight | F1: dialect | G1: active | H1: subcategory | I1: source_sheets | J1: semantic_register | K1: belief_deriv_level | L1: six_needs_served | M1: polarity_stability | N1: ai_detection | O1: danger_level | P1: shibboleth_cluster
A2: wisdom | B2: WISDOM | F2: Standard_English | G2: Y | I2: WISDOM_TERMS | J2: Diluted_2025 | K2: Meaning | L2: Growth | M2: Stable | N2: N | O2: Low | P2: Pastoral
A3: discernment | B3: WISDOM | F3: Standard_English | G3: Y | I3: WISDOM_TERMS | J3: Diluted_2025 | K3: Meaning | L3: Growth | M3: Stable | N3: N | O3: Low | P3: Pastoral
A4: eternal | B4: WISDOM | F4: Standard_English | G4: Y | I4: WISDOM_TERMS | J4: Diluted_2025 | K4: Meaning | L4: Growth | M4: Stable | N4: N | O4: Low | P4: Pastoral
A5: transcend | B5: WISDOM | F5: Standard_English | G5: Y | I5: WISDOM_TERMS | J5: Diluted_2025 | K5: Meaning | L5: Growth | M5: Stable | N5: N | O5: Low | P5: Pastoral
A6: revelation | B6: WISDOM | F6: Standard_English | G6: Y | I6: WISDOM_TERMS | J6: Diluted_2025 | K6: Meaning | L6: Growth | M6: Stable | N6: N | O6: Low | P6: Pastoral
A7: mystery | B7: WISDOM | F7: Standard_English | G7: Y | I7: WISDOM_TERMS | J7: Diluted_2025 | K7: Meaning | L7: Growth | M7: Stable | N7: N | O7: Low | P7: Pastoral
A8: grace | B8: WISDOM | F8: Standard_English | G8: Y | I8: WISDOM_TERMS | J8: Diluted_2025 | K8: Meaning | L8: Growth | M8: Stable | N8: N | O8: Low | P8: Pastoral
A9: covenant | B9: WISDOM | F9: Standard_English | G9: Y | I9: WISDOM_TERMS | J9: Diluted_2025 | K9: Meaning | L9: Growth | M9: Stable | N9: N | O9: Low | P9: Pastoral
A10: truth | B10: WISDOM | F10: Standard_English | G10: Y | I10: WISDOM_TERMS | J10: Diluted_2025 | K10: Meaning | L10: Growth | M10: Stable | N10: N | O10: Low | P10: Pastoral
A11: logos | B11: WISDOM | F11: Standard_English | G11: Y | I11: WISDOM_TERMS | J11: Diluted_2025 | K11: Meaning | L11: Growth | M11: Stable | N11: N | O11: Low | P11: Pastoral
A12: spirit | B12: WISDOM | F12: Standard_English | G12: Y | I12: WISDOM_TERMS | J12: Diluted_2025 | K12: Meaning | L12: Growth | M12: Stable | N12: N | O12: Low | P12: Pastoral
A13: divine | B13: WISDOM | F13: Standard_English | G13: Y | I13: WISDOM_TERMS | J13: Diluted_2025 | K13: Meaning | L13: Growth | M13: Stable | N13: N | O13: Low | P13: Pastoral
... A128: however | B128: BRIDGE | F128: Standard_English | G128: Y | I128: BRIDGE_TERMS | J128: Standard | K128: Interpretation | L128: None | M128: Stable | N128: N | O128: Low | P128: None
A129: FALSE | B129: NEGATION | F129: Standard_English | G129: Y | I129: NEGATION_TERMS | J129: Standard | K129: Interpretation | L129: Multiple | M129: Stable | N129: N | O129: Low | P129: None
A130: can't | B130: NEGATION | F130: Standard_English | G130: Y | I130: NEGATION_TERMS | J130: Standard | K130: Interpretation | L130: Multiple | M130: Stable | N130: N | O130: Low | P130: None
A131: never | B131: NEGATION | F131: Standard_English | G131: Y | I131: NEGATION_TERMS | J131: Standard | K131: Interpretation | L131: Multiple | M131: Stable | N131: N | O131: High | P131: None
A132: fails | B132: NEGATION | F132: Standard_English | G132: Y | I132: NEGATION_TERMS | J132: Standard | K132: Interpretation | L132: Multiple | M132: Stable | N132: N | O132: Low | P132: None
A133: cannot | B133: NEGATION | F133: Standard_English | G133: Y | I133: NEGATION_TERMS | J133: Standard | K133: Interpretation | L133: Multiple | M133: Stable | N133: N | O133: Low | P133: None
A134: no | B134: NEGATION | F134: Standard_English | G134: Y | I134: NEGATION_TERMS | J134: Standard | K134: Interpretation | L134: Multiple | M134: Stable | N134: N | O134: Low | P134: None
A135: not | B135: NEGATION | F135: Standard_English | G135: Y | I135: NEGATION_TERMS | J135: Standard | K135: Interpretation | L135: Multiple | M135: Stable | N135: N | O135: Low | P135: None
A136: 3 | B136: COHERENCE_TERMS | C136: coherence | F136: Standard_English | G136: Y | I136: COHERENCE_TERMS | J136: Standard | K136: Interpretation | L136: Multiple | M136: Stable | N136: N | O136: Low | P136: Academic
A137: 3 | B137: COHERENCE_TERMS | C137: coherent | F137: Standard_English | G137: Y | I137: COHERENCE_TERMS | J137: Standard | K137: Interpretation | L137: Multiple | M137: Stable | N137: N | O137: Low | P137: Academic
A138: 3 | B138: COHERENCE_TERMS | C138: logos | F138: Standard_English | G138: Y | I138: COHERENCE_TERMS | J138: Standard | K138: Interpretation | L138: Multiple | M138: Stable | N138: N | O138: Low | P138: Academic
A139: 3 | B139: COHERENCE_TERMS | C139: quantum | F139: Standard_English | G139: Y | I139: COHERENCE_TERMS | J139: Standard | K139: Interpretation | L139: Multiple | M139: Stable | N139: N | O139: Low | P139: Academic
A140: 3 | B140: COHERENCE_TERMS | C140: decoherence | F140: Standard_English | G140: Y | I140: COHERENCE_TERMS | J140: Standard | K140: Interpretation | L140: Multiple | M140: Stable | N140: N | O140: Low | P140: Academic
A141: 3 | B141: COHERENCE_TERMS | C141: wavefunction | F141: Standard_English | G141: Y | I141: COHERENCE_TERMS | J141: Standard | K141: Interpretation | L141: Multiple | M141: Stable | N141: N | O141: Low | P141: Academic
A142: 2 | B142: COHERENCE_TERMS | C142: entropy | F142: Standard_English | G142: Y | I142: COHERENCE_TERMS | J142: Standard | K142: Interpretation | L142: Multiple | M142: Stable | N142: N | O142: Low | P142: Academic
A143: 2 | B143: COHERENCE_TERMS | C143: conservation | F143: Standard_English | G143: Y | I143: COHERENCE_TERMS | J143: Standard | K143: Interpretation | L143: Multiple | M143: Stable | N143: N | O143: Low | P143: Academic
A144: 2 | B144: COHERENCE_TERMS | C144: order | F144: Standard_English | G144: Y | I144: COHERENCE_TERMS | J144: Standard | K144: Interpretation | L144: Multiple | M144: Stable | N144: N | O144: Low | P144: Academic
A145: 2 | B145: COHERENCE_TERMS | C145: structure | F145: Standard_English | G145: Y | I145: COHERENCE_TERMS | J145: Standard | K145: Interpretation | L145: Multiple | M145: Stable | N145: N | O145: Low | P145: Academic
A146: 2 | B146: COHERENCE_TERMS | C146: framework | F146: Standard_English | G146: Y | I146: COHERENCE_TERMS | J146: Standard | K146: Interpretation | L146: Multiple | M146: Stable | N146: N | O146: Low | P146: Academic
A147: 2 | B147: COHERENCE_TERMS | C147: principle | F147: Standard_English | G147: Y | I147: COHERENCE_TERMS | J147: Standard | K147: Interpretation | L147: Multiple | M147: Stable | N147: N | O147: Low | P147: Academic
... A165: 2 | B165: COHERENCE_TERMS | C165: fundamental | F165: Standard_English | G165: Y | I165: COHERENCE_TERMS | J165: Standard | K165: Interpretation | L165: Multiple | M165: Stable | N165: N | O165: Low | P165: Academic
A166: gravity | B166: ME_VARS | C166: G_gravity_belonging | F166: Standard_English | G166: Y | I166: ME_VARS | J166: Standard | K166: Interpretation | L166: Multiple | M166: Stable | N166: N | O166: Low | P166: Academic
A167: belonging | B167: ME_VARS | C167: G_gravity_belonging | F167: Standard_English | G167: Y | I167: ME_VARS | J167: Standard | K167: Interpretation | L167: Multiple | M167: Stable | N167: N | O167: Low | P167: Academic
A168: community | B168: ME_VARS | C168: G_gravity_belonging | F168: Standard_English | G168: Y | I168: ME_VARS | J168: Standard | K168: Interpretation | L168: Multiple | M168: Stable | N168: N | O168: Low | P168: Academic
A169: gather | B169: ME_VARS | C169: G_gravity_belonging | F169: Standard_English | G169: Y | I169: ME_VARS | J169: Standard | K169: Interpretation | L169: Multiple | M169: Stable | N169: N | O169: Low | P169: Academic
A170: love | B170: ME_VARS | C170: G_gravity_belonging | F170: Standard_English | G170: Y | I170: ME_VARS | J170: Diluted_2025 | K170: Interpretation | L170: Multiple | M170: Stable | N170: N | O170: Low | P170: Pastoral
A171: binding | B171: ME_VARS | C171: G_gravity_belonging | F171: Standard_English | G171: Y | I171: ME_VARS | J171: Standard | K171: Interpretation | L171: Multiple | M171: Stable | N171: N | O171: Low | P171: Academic
A172: together | B172: ME_VARS | C172: G_gravity_belonging | F172: Standard_English | G172: Y | I172: ME_VARS | J172: Standard | K172: Interpretation | L172: Multiple | M172: Stable | N172: N | O172: Low | P172: Academic
A173: meaning | B173: ME_VARS | C173: M_mass_meaning | F173: Standard_English | G173: Y | I173: ME_VARS | J173: Standard | K173: Interpretation | L173: Multiple | M173: Stable | N173: N | O173: Low | P173: Academic
A174: purpose | B174: ME_VARS | C174: M_mass_meaning | F174: Standard_English | G174: Y | I174: ME_VARS | J174: Standard | K174: Interpretation | L174: Multiple | M174: Stable | N174: N | O174: Low | P174: Academic
A175: mass | B175: ME_VARS | C175: M_mass_meaning | F175: Standard_English | G175: Y | I175: ME_VARS | J175: Standard | K175: Interpretation | L175: Multiple | M175: Stable | N175: N | O175: Low | P175: Academic
A176: nuclear | B176: ME_VARS | C176: M_mass_meaning | F176: Standard_English | G176: Y | I176: ME_VARS | J176: Standard | K176: Interpretation | L176: Multiple | M176: Stable | N176: N | O176: Low | P176: Academic
A177: commit | B177: ME_VARS | C177: M_mass_meaning | F177: Standard_English | G177: Y | I177: ME_VARS | J177: Standard | K177: Interpretation | L177: Multiple | M177: Stable | N177: N | O177: Low | P177: Academic
... A362: unrestrained | B362: ANTI_FRUITS | C362: self_control | F362: Standard_English | G362: Y | I362: ANTI_FRUITS | J362: Standard | K362: Perception | L362: Significance | M362: Stable | N362: N | O362: Medium | P362: None
A363: protective | B363: CHAR_ATTR_PATTERNS | C363: spiritual_coherence | F363: Standard_English | G363: Y | H363: kind | I363: CHAR_ATTR_PATTERNS | J363: Standard | K363: Interpretation | L363: Multiple | M363: Stable | N363: N | O363: Low | P363: None
A364: transparent faith | B364: CHAR_ATTR_PATTERNS | C364: spiritual_coherence | F364: Standard_English | G364: Y | H364: positive | I364: CHAR_ATTR_PATTERNS | J364: Diluted_2025 | K364: Interpretation | L364: Multiple | M364: Stable | N364: N | O364: Low | P364: Pastoral
A365: sacrificial love | B365: CHAR_ATTR_PATTERNS | C365: spiritual_coherence | F365: Standard_English | G365: Y | H365: positive | I365: CHAR_ATTR_PATTERNS | J365: Diluted_2025 | K365: Interpretation | L365: Multiple | M365: Stable | N365: N | O365: Low | P365: Pastoral
A366: walks the talk | B366: CHAR_ATTR_PATTERNS | C366: spiritual_coherence | F366: Standard_English | G366: Y | H366: positive | I366: CHAR_ATTR_PATTERNS | J366: Standard | K366: Interpretation | L366: Multiple | M366: Stable | N366: N | O366: Low | P366: None
A367: servant heart | B367: CHAR_ATTR_PATTERNS | C367: spiritual_coherence | F367: Standard_English | G367: Y | H367: positive | I367: CHAR_ATTR_PATTERNS | J367: Standard | K367: Interpretation | L367: Multiple | M367: Stable | N367: N | O367: Low | P367: None
A368: glorifies god | B368: CHAR_ATTR_PATTERNS | C368: spiritual_coherence | F368: Standard_English | G368: Y | H368: positive | I368: CHAR_ATTR_PATTERNS | J368: Standard | K368: Interpretation | L368: Multiple | M368: Stable | N368: N | O368: Low | P368: None
A369: genuine worship | B369: CHAR_ATTR_PATTERNS | C369: spiritual_coherence | F369: Standard_English | G369: Y | H369: positive | I369: CHAR_ATTR_PATTERNS | J369: Standard | K369: Interpretation | L369: Multiple | M369: Stable | N369: N | O369: Low | P369: None
A370: coherent theology | B370: CHAR_ATTR_PATTERNS | C370: spiritual_coherence | F370: Standard_English | G370: Y | H370: positive | I370: CHAR_ATTR_PATTERNS | J370: Standard | K370: Interpretation | L370: Multiple | M370: Stable | N370: N | O370: Low | P370: None
A371: consistent worldview | B371: CHAR_ATTR_PATTERNS | C371: spiritual_coherence | F371: Standard_English | G371: Y | H371: positive | I371: CHAR_ATTR_PATTERNS | J371: Standard | K371: Interpretation | L371: Multiple | M371: Stable | N371: N | O371: Low | P371: None
A372: contradictory statements | B372: CHAR_ATTR_PATTERNS | C372: spiritual_coherence | F372: Standard_English | G372: Y | H372: negative | I372: CHAR_ATTR_PATTERNS | J372: Standard | K372: Interpretation | L372: Multiple | M372: Stable | N372: N | O372: Low | P372: None
A373: self-serving theology | B373: CHAR_ATTR_PATTERNS | C373: spiritual_coherence | F373: Standard_English | G373: Y | H373: negative | I373: CHAR_ATTR_PATTERNS | J373: Standard | K373: Interpretation | L373: Multiple | M373: Stable | N373: N | O373: Low | P373: None
A374: manipulates faith | B374: CHAR_ATTR_PATTERNS | C374: spiritual_coherence | F374: Standard_English | G374: Y | H374: negative | I374: CHAR_ATTR_PATTERNS | J374: Diluted_2025 | K374: Interpretation | L374: Multiple | M374: Stable | N374: N | O374: Low | P374: Pastoral
... A546: excitement | B546: FRUIT_BLEND | C546: self_control | F546: Standard_English | G546: Y | H546: negative | I546: FRUIT_BLEND | J546: Standard | K546: Meaning | L546: Contribution | M546: Stable | N546: N | O546: Low | P546: None
A547: anger | B547: ANTI_FRUIT_MAP | C547: hatred | F547: Standard_English | G547: Y | I547: ANTI_FRUIT_MAP | J547: Standard | K547: Perception | L547: Significance | M547: Stable | N547: N | O547: Medium | P547: None
A548: disgust | B548: ANTI_FRUIT_MAP | C548: hatred | F548: Standard_English | G548: Y | I548: ANTI_FRUIT_MAP | J548: Standard | K548: Perception | L548: Significance | M548: Stable | N548: N | O548: Medium | P548: None
A549: disapproval | B549: ANTI_FRUIT_MAP | C549: hatred | F549: Standard_English | G549: Y | I549: ANTI_FRUIT_MAP | J549: Standard | K549: Perception | L549: Significance | M549: Stable | N549: N | O549: Medium | P549: None
A550: sadness | B550: ANTI_FRUIT_MAP | C550: despair | F550: Standard_English | G550: Y | I550: ANTI_FRUIT_MAP | J550: Standard | K550: Perception | L550: Significance | M550: Stable | N550: N | O550: Medium | P550: None
A551: grief | B551: ANTI_FRUIT_MAP | C551: despair | F551: Standard_English | G551: Y | I551: ANTI_FRUIT_MAP | J551: Standard | K551: Perception | L551: Significance | M551: Stable | N551: N | O551: Medium | P551: None
A552: disappointment | B552: ANTI_FRUIT_MAP | C552: despair | F552: Standard_English | G552: Y | I552: ANTI_FRUIT_MAP | J552: Standard | K552: Perception | L552: Significance | M552: Stable | N552: N | O552: Medium | P552: None
A553: anger | B553: ANTI_FRUIT_MAP | C553: conflict | F553: Standard_English | G553: Y | I553: ANTI_FRUIT_MAP | J553: Standard | K553: Perception | L553: Significance | M553: Stable | N553: N | O553: Medium | P553: None
A554: annoyance | B554: ANTI_FRUIT_MAP | C554: conflict | F554: Standard_English | G554: Y | I554: ANTI_FRUIT_MAP | J554: Standard | K554: Perception | L554: Significance | M554: Stable | N554: N | O554: Medium | P554: None
A555: fear | B555: ANTI_FRUIT_MAP | C555: conflict | F555: Standard_English | G555: Y | I555: ANTI_FRUIT_MAP | J555: Standard | K555: Perception | L555: Significance | M555: Stable | N555: N | O555: Medium | P555: None
A556: nervousness | B556: ANTI_FRUIT_MAP | C556: conflict | F556: Standard_English | G556: Y | I556: ANTI_FRUIT_MAP | J556: Standard | K556: Perception | L556: Significance | M556: Stable | N556: N | O556: Medium | P556: None
A557: anger | B557: ANTI_FRUIT_MAP | C557: impatience | F557: Standard_English | G557: Y | I557: ANTI_FRUIT_MAP | J557: Standard | K557: Perception | L557: Significance | M557: Stable | N557: N | O557: Medium | P557: None
A558: annoyance | B558: ANTI_FRUIT_MAP | C558: impatience | F558: Standard_English | G558: Y | I558: ANTI_FRUIT_MAP | J558: Standard | K558: Perception | L558: Significance | M558: Stable | N558: N | O558: Medium | P558: None
... A703: const | B703: DOC_TYPE_PATTERNS | C703: code | F703: Standard_English | G703: Y | I703: DOC_TYPE_PATTERNS | J703: Standard | K703: Interpretation | L703: Multiple | M703: Stable | N703: N | O703: Low | P703: Academic
A704: on God | B704: Fruit | D704: Tier 1 | E704: 2x weight (oath-level truth) | F704: AAVE | G704: Y | H704: direct_truth [RECOVERED] | I704: AAVE-Ebonics | J704: Standard | K704: Meaning | L704: Contribution | M704: Dialect-dependent | N704: N | O704: Low | P704: Street
A705: on everything | B705: Fruit | D705: Tier 1 | E705: 2x weight (oath-level truth) | F705: AAVE | G705: Y | H705: direct_truth [RECOVERED] | I705: AAVE-Ebonics | J705: Standard | K705: Meaning | L705: Contribution | M705: Dialect-dependent | N705: N | O705: Low | P705: Street
A706: on my mama | B706: Fruit | D706: Tier 1 | E706: 2x weight (oath-level truth) | F706: AAVE | G706: Y | H706: direct_truth [RECOVERED] | I706: AAVE-Ebonics | J706: Standard | K706: Meaning | L706: Contribution | M706: Dialect-dependent | N706: N | O706: Low | P706: Street
A707: on my kids | B707: Fruit | D707: Tier 1 | E707: 2x weight (oath-level truth) | F707: AAVE | G707: Y | H707: direct_truth [RECOVERED] | I707: AAVE-Ebonics | J707: Standard | K707: Meaning | L707: Contribution | M707: Dialect-dependent | N707: N | O707: Low | P707: Street
A708: on the set | B708: Fruit | D708: Tier 1 | E708: 2x weight (oath-level truth) | F708: AAVE | G708: Y | H708: direct_truth [RECOVERED] | I708: AAVE-Ebonics | J708: Standard | K708: Meaning | L708: Contribution | M708: Dialect-dependent | N708: N | O708: Low | P708: Street
A709: on the gang | B709: Fruit | D709: Tier 1 | E709: 2x weight (oath-level truth) | F709: AAVE | G709: Y | H709: direct_truth [RECOVERED] | I709: AAVE-Ebonics | J709: Standard | K709: Meaning | L709: Contribution | M709: Dialect-dependent | N709: N | O709: Low | P709: Street
A710: no cap | B710: Fruit | D710: Tier 1 | E710: 2x weight (oath-level truth) | F710: AAVE | G710: Y | H710: direct_truth [RECOVERED] | I710: AAVE-Ebonics | J710: Standard | K710: Meaning | L710: Contribution | M710: Dialect-dependent | N710: N | O710: Low | P710: Street
A711: fr fr | B711: Fruit | D711: Tier 1 | E711: 2x weight (oath-level truth) | F711: AAVE | G711: Y | H711: direct_truth [RECOVERED] | I711: AAVE-Ebonics | J711: Standard | K711: Meaning | L711: Contribution | M711: Dialect-dependent | N711: N | O711: Low | P711: Street
A712: for real | B712: Fruit | D712: Tier 1 | E712: 2x weight (oath-level truth) | F712: AAVE | G712: Y | H712: direct_truth [RECOVERED] | I712: AAVE-Ebonics | J712: Standard | K712: Meaning | L712: Contribution | M712: Dialect-dependent | N712: N | O712: Low | P712: Street
A713: for real for real | B713: Fruit | D713: Tier 1 | E713: 2x weight (oath-level truth) | F713: AAVE | G713: Y | H713: direct_truth [RECOVERED] | I713: AAVE-Ebonics | J713: Standard | K713: Meaning | L713: Contribution | M713: Dialect-dependent | N713: N | O713: Low | P713: Street
A714: deadass | B714: Fruit | D714: Tier 1 | E714: 2x weight (oath-level truth) | F714: AAVE | G714: Y | H714: direct_truth [RECOVERED] | I714: AAVE-Ebonics | J714: Standard | K714: Meaning | L714: Contribution | M714: Dialect-dependent | N714: N | O714: Low | P714: Street
A715: dead ass | B715: Fruit | D715: Tier 1 | E715: 2x weight (oath-level truth) | F715: AAVE | G715: Y | H715: direct_truth [RECOVERED] | I715: AAVE-Ebonics | J715: Standard | K715: Meaning | L715: Contribution | M715: Dialect-dependent | N715: N | O715: Low | P715: Street
... A765: that part | B765: Fruit | D765: Tier 1 | E765: 2x weight (oath-level truth) | F765: AAVE | G765: Y | H765: direct_truth | I765: AAVE-Ebonics | J765: Standard | K765: Meaning | L765: Contribution | M765: Dialect-dependent | N765: N | O765: Low | P765: Street
A766: solid | B766: Fruit | D766: Tier 2 | F766: AAVE | G766: Y | H766: authenticity | I766: AAVE-Ebonics | J766: Standard | K766: Meaning | L766: Contribution | M766: Dialect-dependent | N766: N | O766: Low | P766: Street
A767: he solid | B767: Fruit | D767: Tier 2 | F767: AAVE | G767: Y | H767: authenticity | I767: AAVE-Ebonics | J767: Standard | K767: Meaning | L767: Contribution | M767: Dialect-dependent | N767: N | O767: Low | P767: Street
A768: she solid | B768: Fruit | D768: Tier 2 | F768: AAVE | G768: Y | H768: authenticity | I768: AAVE-Ebonics | J768: Standard | K768: Meaning | L768: Contribution | M768: Dialect-dependent | N768: N | O768: Low | P768: Street
A769: stand on business | B769: Fruit | D769: Tier 2 | F769: AAVE | G769: Y | H769: authenticity | I769: AAVE-Ebonics | J769: Standard | K769: Meaning | L769: Contribution | M769: Dialect-dependent | N769: N | O769: Low | P769: Street
A770: stand on it | B770: Fruit | D770: Tier 2 | F770: AAVE | G770: Y | H770: authenticity | I770: AAVE-Ebonics | J770: Standard | K770: Meaning | L770: Contribution | M770: Dialect-dependent | N770: N | O770: Low | P770: Street
A771: a real one | B771: Fruit | D771: Tier 2 | F771: AAVE | G771: Y | H771: authenticity | I771: AAVE-Ebonics | J771: Standard | K771: Meaning | L771: Contribution | M771: Dialect-dependent | N771: N | O771: Low | P771: Street
A772: real one right there | B772: Fruit | D772: Tier 2 | F772: AAVE | G772: Y | H772: authenticity | I772: AAVE-Ebonics | J772: Standard | K772: Meaning | L772: Contribution | M772: Dialect-dependent | N772: N | O772: Low | P772: Street
A773: down | B773: Fruit | D773: Tier 2 | F773: AAVE | G773: Y | H773: authenticity | I773: AAVE-Ebonics | J773: Standard | K773: Meaning | L773: Contribution | M773: Dialect-dependent | N773: N | O773: Low | P773: Street
A774: I'm down | B774: Fruit | D774: Tier 2 | F774: AAVE | G774: Y | H774: authenticity | I774: AAVE-Ebonics | J774: Standard | K774: Meaning | L774: Contribution | M774: Dialect-dependent | N774: N | O774: Low | P774: Street
A775: he down | B775: Fruit | D775: Tier 2 | F775: AAVE | G775: Y | H775: authenticity | I775: AAVE-Ebonics | J775: Standard | K775: Meaning | L775: Contribution | M775: Dialect-dependent | N775: N | O775: Low | P775: Street
A776: official | B776: Fruit | D776: Tier 2 | F776: AAVE | G776: Y | H776: authenticity | I776: AAVE-Ebonics | J776: Standard | K776: Meaning | L776: Contribution | M776: Dialect-dependent | N776: N | O776: Low | P776: Street
A777: he official | B777: Fruit | D777: Tier 2 | F777: AAVE | G777: Y | H777: authenticity | I777: AAVE-Ebonics | J777: Standard | K777: Meaning | L777: Contribution | M777: Dialect-dependent | N777: N | O777: Low | P777: Street
... A855: build each other up | B855: Fruit | D855: Tier 4 | F855: AAVE | G855: Y | H855: relational | I855: AAVE-Ebonics | J855: Standard | K855: Meaning | L855: Connection | M855: Dialect-dependent | N855: N | O855: Low | P855: Street
A856: cap | B856: Anti-Fruit | D856: Tier 1 | E856: 1.5x weight (culturally specific) | F856: AAVE | G856: Y | H856: deception | I856: AAVE-Ebonics | J856: Standard | K856: Perception | L856: Significance | M856: Dialect-dependent | N856: N | O856: Medium | P856: Street
...

Sheet AAVE-Ebonics
A1: I need you to fill in the blank columns for every row in the MASTER_TERM_REGISTRY sheet. Each row is a term in a semantic classification lexicon. The filled columns are: term, category, fruit_mapping, tier, weight, dialect, active, subcategory, source_sheets. The blank columns that need filling are:
A3: COLUMN F — semantic_register: Choose one of: Full_1828 / Standard / Diluted_2025 / Inverted
A4: {=- Full_1828 = the term carries its full historical/theological/moral depth} -> #NAME? | B4: Category | C4: Tier | D4: Subcategory | E4: Active | F4: Weight Note
A5: {=- Standard = Standard modern meaning, intact but no theological overtone} -> #NAME? | B5: Fruit | C5: Tier 1 | D5: direct_truth | E5: Y | F5: 2x weight (oath-level truth)
A6: - Diluted_2025 = meaning has been weakened or bleached in contemporary usage | B6: Fruit | C6: Tier 1 | D6: direct_truth | E6: Y | F6: 2x weight (oath-level truth)
A7: - Inverted = meaning has flipped or been co-opted to serve the opposite function | B7: Fruit | C7: Tier 1 | D7: direct_truth | E7: Y | F7: 2x weight (oath-level truth)
A8: - Default: if the term is in the AAVE dialect, default to Standard. If it's a theological term (love, grace, faith, patience, faithfulness), lean toward Diluted_2025 unless the subcategory is direct_truth or oath-level. | B8: Fruit | C8: Tier 1 | D8: direct_truth | E8: Y | F8: 2x weight (oath-level truth)
B9: Fruit | C9: Tier 1 | D9: direct_truth | E9: Y | F9: 2x weight (oath-level truth)
A10: COLUMN H — belief_deriv_level: Choose one of: Reality / Distinction / Signal / Perception / Interpretation / Meaning / Belief / Identity / Action / World | B10: Fruit | C10: Tier 1 | D10: direct_truth | E10: Y | F10: 2x weight (oath-level truth)
A11: {=- Reality = ground facts. Signal = data/evidence. Perception = how things appear. Interpretation = meaning-making. meaning = _xleta.VALUE-placed. Belief = held proposition. Identity = who I am. Action = behavior. World = institution-building.} -> #NAME? | B11: Fruit | C11: Tier 1 | D11: direct_truth | E11: Y | F11: 2x weight (oath-level truth)
A12: - Default: Grounding terms → Signal or Reality. Fruit terms → Meaning or Belief. Anti-Fruit terms → Perception or Interpretation. Propaganda terms → Meaning or Identity. Claim terms → Belief. Evidence terms → Signal. Hedge terms → Interpretation. | B12: Fruit | C12: Tier 1 | D12: direct_truth | E12: Y | F12: 2x weight (oath-level truth)
B13: Fruit | C13: Tier 1 | D13: direct_truth | E13: Y | F13: 2x weight (oath-level truth)
A14: COLUMN I — six_needs_served: Choose one of: Certainty / Variety / Significance / Connection / Growth / Contribution / Multiple / None | B14: Fruit | C14: Tier 1 | D14: direct_truth | E14: Y | F14: 2x weight (oath-level truth)
A15: - Certainty = safety, stability. Variety = change, stimulation. Significance = importance, recognition. Connection = bonds, belonging. Growth = learning, expansion. Contribution = giving, service. | B15: Fruit | C15: Tier 1 | D15: direct_truth | E15: Y | F15: 2x weight (oath-level truth)
A16: - Default: Most Fruit terms → Connection or Contribution. Most Anti-Fruit terms → Significance or Certainty. Grounding terms → Certainty. Propaganda terms → Significance. Bridge terms → None. | B16: Fruit | C16: Tier 1 | D16: direct_truth | E16: Y | F16: 2x weight (oath-level truth)
B17: Fruit | C17: Tier 1 | D17: direct_truth | E17: Y | F17: 2x weight (oath-level truth)
A18: COLUMN K — polarity_stability: Choose one of: Stable / Context-flip / Sarcasm-risk / Dialect-dependent | B18: Fruit | C18: Tier 1 | D18: direct_truth | E18: Y | F18: 2x weight (oath-level truth)
A19: {=- Stable = always the same polarity. Context-flip = Context can reverse meaning. Sarcasm-risk = frequently sarcastic. Dialect-dependent = meaning changes by community.} -> #NAME? | B19: Fruit | C19: Tier 1 | D19: direct_truth | E19: Y | F19: 2x weight (oath-level truth)
A20: - Default: Tier 1 terms → Stable. AAVE terms → check for dialect-dependency. Terms like "interesting," "fine," "sure," "nice" → Sarcasm-risk or Context-flip. | B20: Fruit | C20: Tier 1 | D20: direct_truth | E20: Y | F20: 2x weight (oath-level truth)
B21: Fruit | C21: Tier 1 | D21: direct_truth | E21: Y | F21: 2x weight (oath-level truth)
A22: COLUMN L — ai_detection: Y or N | B22: Fruit | C22: Tier 1 | D22: direct_truth | E22: Y | F22: 2x weight (oath-level truth)
A23: - Y = this term is characteristic of AI-generated text (e.g., delve, tapestry, nuanced, multifaceted, it's important to note, I'd be happy to, certainly, absolutely, in conclusion, comprehensive, robust, leverage, facilitate, utilize, albeit, furthermore, moreover, notable, noteworthy, underscores, underpin) | B23: Fruit | C23: Tier 1 | D23: direct_truth | E23: Y | F23: 2x weight (oath-level truth)
A24: - Default: N for most terms. Y only for known AI-speak markers. | B24: Fruit | C24: Tier 1 | D24: direct_truth | E24: Y | F24: 2x weight (oath-level truth)
B25: Fruit | C25: Tier 1 | D25: direct_truth | E25: Y | F25: 2x weight (oath-level truth)
A26: COLUMN M — danger_level: Choose one of: Low / Medium / High / Critical | B26: Fruit | C26: Tier 1 | D26: direct_truth | E26: Y | F26: 2x weight (oath-level truth)
A27: - Low = safe in most contexts. Medium = context-dependent. High = frequently overclaims. Critical = almost always overclaims or signals manipulation. | B27: Fruit | C27: Tier 1 | D27: direct_truth | E27: Y | F27: 2x weight (oath-level truth)
A28: - Default: Tier 1 Fruit → Low. Tier 4 peripheral → Low. Propaganda terms → High or Critical. Absolute terms (proves, always, never) → High. Hedge terms → Low. Claim-strength terms → Medium to High depending on subcategory. | B28: Fruit | C28: Tier 1 | D28: direct_truth | E28: Y | F28: 2x weight (oath-level truth)
B29: Fruit | C29: Tier 1 | D29: direct_truth | E29: Y | F29: 2x weight (oath-level truth)
A30: COLUMN N — shibboleth_cluster: Choose one of: Pastoral / Therapeutic / Academic / Legal / Medical / Military / Street / Tech / Trades / Finance / Political / AI / None | B30: Fruit | C30: Tier 1 | D30: direct_truth | E30: Y | F30: 2x weight (oath-level truth)
A31: - This is the profession/community fingerprint. Which community would immediately recognize this term as "one of theirs"? | B31: Fruit | C31: Tier 1 | D31: direct_truth | E31: Y | F31: 2x weight (oath-level truth)
A32: - Default: AAVE terms → Street. Terms from theophysics_scorer.py → Academic. Terms with theological subcategory → Pastoral. Terms like "boundaries," "hold space," "validate" → Therapeutic. Terms like "leverage," "utilize" → could be Tech, Finance, or AI. | B32: Fruit | C32: Tier 1 | D32: direct_truth | E32: Y | F32: 2x weight (oath-level truth)
B33: Fruit | C33: Tier 1 | D33: direct_truth | E33: Y | F33: 2x weight (oath-level truth)
A34: Work through every row. Where you're unsure, use the defaults above. Speed matters more than perfection here — this is a first pass that will be audited by a specialized classification model afterward. | B34: Fruit | C34: Tier 1 | D34: direct_truth | E34: Y | F34: 2x weight (oath-level truth)
A35: I swear | B35: Fruit | C35: Tier 1 | D35: direct_truth | E35: Y | F35: 2x weight (oath-level truth)
A36: keep it 100 | B36: Fruit | C36: Tier 1 | D36: direct_truth | E36: Y | F36: 2x weight (oath-level truth)
A37: keep it a buck | B37: Fruit | C37: Tier 1 | D37: direct_truth | E37: Y | F37: 2x weight (oath-level truth)
A38: keep it a stack | B38: Fruit | C38: Tier 1 | D38: direct_truth | E38: Y | F38: 2x weight (oath-level truth)
A39: keep it real | B39: Fruit | C39: Tier 1 | D39: direct_truth | E39: Y | F39: 2x weight (oath-level truth)
A40: keep it G | B40: Fruit | C40: Tier 1 | D40: direct_truth | E40: Y | F40: 2x weight (oath-level truth)
A41: periodt | B41: Fruit | C41: Tier 1 | D41: direct_truth | E41: Y | F41: 2x weight (oath-level truth)
A42: say that | B42: Fruit | C42: Tier 1 | D42: direct_truth | E42: Y | F42: 2x weight (oath-level truth)
A43: say it louder | B43: Fruit | C43: Tier 1 | D43: direct_truth | E43: Y | F43: 2x weight (oath-level truth)
A44: preach | B44: Fruit | C44: Tier 1 | D44: direct_truth | E44: Y | F44: 2x weight (oath-level truth)
A45: that's what I'm talkin' about | B45: Fruit | C45: Tier 1 | D45: direct_truth | E45: Y | F45: 2x weight (oath-level truth)
... A66: that part | B66: Fruit | C66: Tier 1 | D66: direct_truth | E66: Y | F66: 2x weight (oath-level truth)
A67: solid | B67: Fruit | C67: Tier 2 | D67: authenticity | E67: Y
A68: he solid | B68: Fruit | C68: Tier 2 | D68: authenticity | E68: Y
A69: she solid | B69: Fruit | C69: Tier 2 | D69: authenticity | E69: Y
A70: stand on business | B70: Fruit | C70: Tier 2 | D70: authenticity | E70: Y
A71: stand on it | B71: Fruit | C71: Tier 2 | D71: authenticity | E71: Y
A72: a real one | B72: Fruit | C72: Tier 2 | D72: authenticity | E72: Y
A73: real one right there | B73: Fruit | C73: Tier 2 | D73: authenticity | E73: Y
A74: down | B74: Fruit | C74: Tier 2 | D74: authenticity | E74: Y
A75: I'm down | B75: Fruit | C75: Tier 2 | D75: authenticity | E75: Y
A76: he down | B76: Fruit | C76: Tier 2 | D76: authenticity | E76: Y
A77: official | B77: Fruit | C77: Tier 2 | D77: authenticity | E77: Y
A78: he official | B78: Fruit | C78: Tier 2 | D78: authenticity | E78: Y
... A156: build each other up | B156: Fruit | C156: Tier 4 | D156: relational | E156: Y
A157: cap | B157: Anti-Fruit | C157: Tier 1 | D157: deception | E157: Y | F157: 1.5x weight (culturally specific)
A158: cappin' | B158: Anti-Fruit | C158: Tier 1 | D158: deception | E158: Y | F158: 1.5x weight (culturally specific)
A159: you cappin' | B159: Anti-Fruit | C159: Tier 1 | D159: deception | E159: Y | F159: 1.5x weight (culturally specific)
A160: straight cappin' | B160: Anti-Fruit | C160: Tier 1 | D160: deception | E160: Y | F160: 1.5x weight (culturally specific)
A161: all cap | B161: Anti-Fruit | C161: Tier 1 | D161: deception | E161: Y | F161: 1.5x weight (culturally specific)
A162: lyin' | B162: Anti-Fruit | C162: Tier 1 | D162: deception | E162: Y | F162: 1.5x weight (culturally specific)
A163: he lyin' | B163: Anti-Fruit | C163: Tier 1 | D163: deception | E163: Y | F163: 1.5x weight (culturally specific)
A164: she lyin' | B164: Anti-Fruit | C164: Tier 1 | D164: deception | E164: Y | F164: 1.5x weight (culturally specific)
A165: straight lyin' | B165: Anti-Fruit | C165: Tier 1 | D165: deception | E165: Y | F165: 1.5x weight (culturally specific)
A166: fake | B166: Anti-Fruit | C166: Tier 1 | D166: deception | E166: Y | F166: 1.5x weight (culturally specific)
A167: fake as hell | B167: Anti-Fruit | C167: Tier 1 | D167: deception | E167: Y | F167: 1.5x weight (culturally specific)
A168: fake AF | B168: Anti-Fruit | C168: Tier 1 | D168: deception | E168: Y | F168: 1.5x weight (culturally specific)
... A212: shady as hell | B212: Anti-Fruit | C212: Tier 1 | D212: deception | E212: Y | F212: 1.5x weight (culturally specific)
A213: gas you up | B213: Anti-Fruit | C213: Tier 2 | D213: manipulation | E213: Y
A214: gassed up | B214: Anti-Fruit | C214: Tier 2 | D214: manipulation | E214: Y
A215: playin' you | B215: Anti-Fruit | C215: Tier 2 | D215: manipulation | E215: Y
A216: gettin' played | B216: Anti-Fruit | C216: Tier 2 | D216: manipulation | E216: Y
A217: played out | B217: Anti-Fruit | C217: Tier 2 | D217: manipulation | E217: Y
A218: finesse | B218: Anti-Fruit | C218: Tier 2 | D218: manipulation | E218: Y
A219: finessin' | B219: Anti-Fruit | C219: Tier 2 | D219: manipulation | E219: Y
A220: scam | B220: Anti-Fruit | C220: Tier 2 | D220: manipulation | E220: Y
A221: scammin' | B221: Anti-Fruit | C221: Tier 2 | D221: manipulation | E221: Y
A222: scammer | B222: Anti-Fruit | C222: Tier 2 | D222: manipulation | E222: Y
A223: got scammed | B223: Anti-Fruit | C223: Tier 2 | D223: manipulation | E223: Y
A224: hustle | B224: Anti-Fruit | C224: Tier 2 | D224: manipulation | E224: Y
... A308: workin' for the man | B308: Anti-Fruit | C308: Tier 4 | D308: systemic | E308: Y
A309: 12 | B309: Anti-Fruit | C309: Tier 4 | D309: systemic | E309: Y
A310: one time | B310: Anti-Fruit | C310: Tier 4 | D310: systemic | E310: Y
A311: the boys | B311: Anti-Fruit | C311: Tier 4 | D311: systemic | E311: Y
A312: the feds | B312: Anti-Fruit | C312: Tier 4 | D312: systemic | E312: Y
A313: the police | B313: Anti-Fruit | C313: Tier 4 | D313: systemic | E313: Y
A314: Uncle Tom | B314: Anti-Fruit | C314: Tier 4 | D314: systemic | E314: Y
A315: coon | B315: Anti-Fruit | C315: Tier 4 | D315: systemic | E315: Y
A316: house negro | B316: Anti-Fruit | C316: Tier 4 | D316: systemic | E316: Y
A317: field negro | B317: Anti-Fruit | C317: Tier 4 | D317: systemic | E317: Y
A318: token | B318: Anti-Fruit | C318: Tier 4 | D318: systemic | E318: Y
A319: tokenism | B319: Anti-Fruit | C319: Tier 4 | D319: systemic | E319: Y
A320: token Black person | B320: Anti-Fruit | C320: Tier 4 | D320: systemic | E320: Y
A321: white-washed | B321: Anti-Fruit | C321: Tier 4 | D321: systemic | E321: Y
... A324: respectability politics | B324: Anti-Fruit | C324: Tier 4 | D324: systemic | E324: Y
A325: the receipts | B325: Grounding | C325: Tier 1 | D325: evidence | E325: Y | F325: 1.5x weight (concrete evidence)
A326: check the receipts | B326: Grounding | C326: Tier 1 | D326: evidence | E326: Y | F326: 1.5x weight (concrete evidence)
...

Sheet MASTER_README
A1: Is it working Goodbye more when I go on there The last one I I don't know what I'm gonna do today | B1: role | C1: notes
A2: MASTER_README | B2: orientation | C2: Canonical single workbook. Subjective sheets are indexed separately below.
A3: Fruit Semantic Architecture | B3: general
A4: README | B4: general
A5: WISDOM_TERMS | B5: subjective
A6: KNOWLEDGE_TERMS | B6: subjective
A7: COHERENCE_TERMS | B7: subjective
A8: FRUITS | B8: subjective
A9: ME_VARS | B9: general
A10: CLAIM_TERMS | B10: subjective
A11: EVIDENCE_TERMS | B11: subjective
A12: FALSIFY_TERMS | B12: subjective
A13: DEPENDENCY_TERMS | B13: subjective
A14: HEDGE_TERMS | B14: subjective
... A24: DOC_TYPE_PATTERNS | B24: subjective

Sheet TEXT_GRADER
A1: TEXT GRADER — Import & Grade Sentence-by-Sentence
A2: Paste text into B10 (one block). Sentences auto-split below and are scored word-by-word against the chosen lexicon.
A4: CONFIG | E4: RESULTS
A5: Lexicon sheet | B5: SEMANTIC_BUCKETS | C5: <- name of the term table to grade against | E5: Sentences | F5: =COUNT(A14:A213) -> 0
A6: Lexicon range (term col) | B6: SEMANTIC_BUCKETS!$A$2:$A$348 | C6: <- terms (edit formulas in row 14 if you change the lexicon) | E6: Total score | F6: =SUM(E14:E213) -> 0
A7: Weight col | B7: SEMANTIC_BUCKETS!$E$2:$E$348 | C7: <- weights (must align row-for-row with terms) | E7: Avg score/sentence | F7: =IFERROR(F6/F5,0) -> 0
A8: Bucket col | B8: SEMANTIC_BUCKETS!$B$2:$B$348 | C8: <- buckets (must align row-for-row with terms) | E8: PASS / WARN / FAIL | F8: =COUNTIF(G14:G213,"PASS")&" / "&COUNTIF(G14:G213,"WARN")&" / "&COUNTIF(G14:G213,"FAIL") -> 0 / 0 / 0
A9: Warn threshold (score ≥) | B9: 3 | C9: <- sentence flagged WARN at/above this matched-weight | E9: Fail threshold (score ≥) | F9: 6
A10: PASTE TEXT HERE →
A12: GRADED SENTENCES
A13: # | B13: Sentence | C13: Words | D13: Matched terms | E13: Score | F13: Top bucket | G13: Grade | H13: Matched list
A14: =IF(B14="","",ROW()-13) | B14: {=IFERROR(_xlfn.LET(_xlpm.s,$B$10,_xlpm.norm,SUBSTITUTE(SUBSTITUTE(_xlpm.s,"!","."),"?","."),_xlpm.parts,_xlfn.TEXTSPLIT(_xlpm.norm,,".",TRUE),TRIM(INDEX(_xlpm.parts,ROW()-13))),"")} | C14: =IF(B14="","",IF(TRIM(B14)="",0,LEN(TRIM(B14))-LEN(SUBSTITUTE(TRIM(B14)," ",""))+1)) | D14: {=IF(B14="","",SUMPRODUCT(--ISNUMBER(SEARCH(" "&SEMANTIC_BUCKETS!$A$2:$A$348&" "," "&B14&" "))))} | E14: {=IF(B14="","",SUMPRODUCT(--ISNUMBER(SEARCH(" "&SEMANTIC_BUCKETS!$A$2:$A$348&" "," "&B14&" ")),SEMANTIC_BUCKETS!$E$2:$E$348))} | F14: {=IF(OR(B14="",D14=0),"",INDEX(SEMANTIC_BUCKETS!$B$2:$B$348,MATCH(TRUE,ISNUMBER(SEARCH(" "&SEMANTIC_BUCKETS!$A$2:$A$348&" "," "&B14&" ")),0)))} | G14: =IF(B14="","",IF(E14>=$F$9,"FAIL",IF(E14>=$B$9,"WARN","PASS"))) | H14: {=IF(OR(B14="",D14=0),"",_xlfn.TEXTJOIN(", ",TRUE,IF(ISNUMBER(SEARCH(" "&SEMANTIC_BUCKETS!$A$2:$A$348&" "," "&B14&" ")),SEMANTIC_BUCKETS!$A$2:$A$348,"")))}
A15: =IF(B15="","",ROW()-13) | B15: {=IFERROR(_xlfn.LET(_xlpm.s,$B$10,_xlpm.norm,SUBSTITUTE(SUBSTITUTE(_xlpm.s,"!","."),"?","."),_xlpm.parts,_xlfn.TEXTSPLIT(_xlpm.norm,,".",TRUE),TRIM(INDEX(_xlpm.parts,ROW()-13))),"")} | C15: =IF(B15="","",IF(TRIM(B15)="",0,LEN(TRIM(B15))-LEN(SUBSTITUTE(TRIM(B15)," ",""))+1)) | D15: {=IF(B15="","",SUMPRODUCT(--ISNUMBER(SEARCH(" "&SEMANTIC_BUCKETS!$A$2:$A$348&" "," "&B15&" "))))} | E15: {=IF(B15="","",SUMPRODUCT(--ISNUMBER(SEARCH(" "&SEMANTIC_BUCKETS!$A$2:$A$348&" "," "&B15&" ")),SEMANTIC_BUCKETS!$E$2:$E$348))} | F15: {=IF(OR(B15="",D15=0),"",INDEX(SEMANTIC_BUCKETS!$B$2:$B$348,MATCH(TRUE,ISNUMBER(SEARCH(" "&SEMANTIC_BUCKETS!$A$2:$A$348&" "," "&B15&" ")),0)))} | G15: =IF(B15="","",IF(E15>=$F$9,"FAIL",IF(E15>=$B$9,"WARN","PASS"))) | H15: {=IF(OR(B15="",D15=0),"",_xlfn.TEXTJOIN(", ",TRUE,IF(ISNUMBER(SEARCH(" "&SEMANTIC_BUCKETS!$A$2:$A$348&" "," "&B15&" ")),SEMANTIC_BUCKETS!$A$2:$A$348,"")))}
A16: =IF(B16="","",ROW()-13) | B16: {=IFERROR(_xlfn.LET(_xlpm.s,$B$10,_xlpm.norm,SUBSTITUTE(SUBSTITUTE(_xlpm.s,"!","."),"?","."),_xlpm.parts,_xlfn.TEXTSPLIT(_xlpm.norm,,".",TRUE),TRIM(INDEX(_xlpm.parts,ROW()-13))),"")} | C16: =IF(B16="","",IF(TRIM(B16)="",0,LEN(TRIM(B16))-LEN(SUBSTITUTE(TRIM(B16)," ",""))+1)) | D16: {=IF(B16="","",SUMPRODUCT(--ISNUMBER(SEARCH(" "&SEMANTIC_BUCKETS!$A$2:$A$348&" "," "&B16&" "))))} | E16: {=IF(B16="","",SUMPRODUCT(--ISNUMBER(SEARCH(" "&SEMANTIC_BUCKETS!$A$2:$A$348&" "," "&B16&" ")),SEMANTIC_BUCKETS!$E$2:$E$348))} | F16: {=IF(OR(B16="",D16=0),"",INDEX(SEMANTIC_BUCKETS!$B$2:$B$348,MATCH(TRUE,ISNUMBER(SEARCH(" "&SEMANTIC_BUCKETS!$A$2:$A$348&" "," "&B16&" ")),0)))} | G16: =IF(B16="","",IF(E16>=$F$9,"FAIL",IF(E16>=$B$9,"WARN","PASS"))) | H16: {=IF(OR(B16="",D16=0),"",_xlfn.TEXTJOIN(", ",TRUE,IF(ISNUMBER(SEARCH(" "&SEMANTIC_BUCKETS!$A$2:$A$348&" "," "&B16&" ")),SEMANTIC_BUCKETS!$A$2:$A$348,"")))}
A17: =IF(B17="","",ROW()-13) | B17: {=IFERROR(_xlfn.LET(_xlpm.s,$B$10,_xlpm.norm,SUBSTITUTE(SUBSTITUTE(_xlpm.s,"!","."),"?","."),_xlpm.parts,_xlfn.TEXTSPLIT(_xlpm.norm,,".",TRUE),TRIM(INDEX(_xlpm.parts,ROW()-13))),"")} | C17: =IF(B17="","",IF(TRIM(B17)="",0,LEN(TRIM(B17))-LEN(SUBSTITUTE(TRIM(B17)," ",""))+1)) | D17: {=IF(B17="","",SUMPRODUCT(--ISNUMBER(SEARCH(" "&SEMANTIC_BUCKETS!$A$2:$A$348&" "," "&B17&" "))))} | E17: {=IF(B17="","",SUMPRODUCT(--ISNUMBER(SEARCH(" "&SEMANTIC_BUCKETS!$A$2:$A$348&" "," "&B17&" ")),SEMANTIC_BUCKETS!$E$2:$E$348))} | F17: {=IF(OR(B17="",D17=0),"",INDEX(SEMANTIC_BUCKETS!$B$2:$B$348,MATCH(TRUE,ISNUMBER(SEARCH(" "&SEMANTIC_BUCKETS!$A$2:$A$348&" "," "&B17&" ")),0)))} | G17: =IF(B17="","",IF(E17>=$F$9,"FAIL",IF(E17>=$B$9,"WARN","PASS"))) | H17: {=IF(OR(B17="",D17=0),"",_xlfn.TEXTJOIN(", ",TRUE,IF(ISNUMBER(SEARCH(" "&SEMANTIC_BUCKETS!$A$2:$A$348&" "," "&B17&" ")),SEMANTIC_BUCKETS!$A$2:$A$348,"")))}
A18: =IF(B18="","",ROW()-13) | B18: {=IFERROR(_xlfn.LET(_xlpm.s,$B$10,_xlpm.norm,SUBSTITUTE(SUBSTITUTE(_xlpm.s,"!","."),"?","."),_xlpm.parts,_xlfn.TEXTSPLIT(_xlpm.norm,,".",TRUE),TRIM(INDEX(_xlpm.parts,ROW()-13))),"")} | C18: =IF(B18="","",IF(TRIM(B18)="",0,LEN(TRIM(B18))-LEN(SUBSTITUTE(TRIM(B18)," ",""))+1)) | D18: {=IF(B18="","",SUMPRODUCT(--ISNUMBER(SEARCH(" "&SEMANTIC_BUCKETS!$A$2:$A$348&" "," "&B18&" "))))} | E18: {=IF(B18="","",SUMPRODUCT(--ISNUMBER(SEARCH(" "&SEMANTIC_BUCKETS!$A$2:$A$348&" "," "&B18&" ")),SEMANTIC_BUCKETS!$E$2:$E$348))} | F18: {=IF(OR(B18="",D18=0),"",INDEX(SEMANTIC_BUCKETS!$B$2:$B$348,MATCH(TRUE,ISNUMBER(SEARCH(" "&SEMANTIC_BUCKETS!$A$2:$A$348&" "," "&B18&" ")),0)))} | G18: =IF(B18="","",IF(E18>=$F$9,"FAIL",IF(E18>=$B$9,"WARN","PASS"))) | H18: {=IF(OR(B18="",D18=0),"",_xlfn.TEXTJOIN(", ",TRUE,IF(ISNUMBER(SEARCH(" "&SEMANTIC_BUCKETS!$A$2:$A$348&" "," "&B18&" ")),SEMANTIC_BUCKETS!$A$2:$A$348,"")))}
A19: =IF(B19="","",ROW()-13) | B19: {=IFERROR(_xlfn.LET(_xlpm.s,$B$10,_xlpm.norm,SUBSTITUTE(SUBSTITUTE(_xlpm.s,"!","."),"?","."),_xlpm.parts,_xlfn.TEXTSPLIT(_xlpm.norm,,".",TRUE),TRIM(INDEX(_xlpm.parts,ROW()-13))),"")} | C19: =IF(B19="","",IF(TRIM(B19)="",0,LEN(TRIM(B19))-LEN(SUBSTITUTE(TRIM(B19)," ",""))+1)) | D19: {=IF(B19="","",SUMPRODUCT(--ISNUMBER(SEARCH(" "&SEMANTIC_BUCKETS!$A$2:$A$348&" "," "&B19&" "))))} | E19: {=IF(B19="","",SUMPRODUCT(--ISNUMBER(SEARCH(" "&SEMANTIC_BUCKETS!$A$2:$A$348&" "," "&B19&" ")),SEMANTIC_BUCKETS!$E$2:$E$348))} | F19: {=IF(OR(B19="",D19=0),"",INDEX(SEMANTIC_BUCKETS!$B$2:$B$348,MATCH(TRUE,ISNUMBER(SEARCH(" "&SEMANTIC_BUCKETS!$A$2:$A$348&" "," "&B19&" ")),0)))} | G19: =IF(B19="","",IF(E19>=$F$9,"FAIL",IF(E19>=$B$9,"WARN","PASS"))) | H19: {=IF(OR(B19="",D19=0),"",_xlfn.TEXTJOIN(", ",TRUE,IF(ISNUMBER(SEARCH(" "&SEMANTIC_BUCKETS!$A$2:$A$348&" "," "&B19&" ")),SEMANTIC_BUCKETS!$A$2:$A$348,"")))}
A20: =IF(B20="","",ROW()-13) | B20: {=IFERROR(_xlfn.LET(_xlpm.s,$B$10,_xlpm.norm,SUBSTITUTE(SUBSTITUTE(_xlpm.s,"!","."),"?","."),_xlpm.parts,_xlfn.TEXTSPLIT(_xlpm.norm,,".",TRUE),TRIM(INDEX(_xlpm.parts,ROW()-13))),"")} | C20: =IF(B20="","",IF(TRIM(B20)="",0,LEN(TRIM(B20))-LEN(SUBSTITUTE(TRIM(B20)," ",""))+1)) | D20: {=IF(B20="","",SUMPRODUCT(--ISNUMBER(SEARCH(" "&SEMANTIC_BUCKETS!$A$2:$A$348&" "," "&B20&" "))))} | E20: {=IF(B20="","",SUMPRODUCT(--ISNUMBER(SEARCH(" "&SEMANTIC_BUCKETS!$A$2:$A$348&" "," "&B20&" ")),SEMANTIC_BUCKETS!$E$2:$E$348))} | F20: {=IF(OR(B20="",D20=0),"",INDEX(SEMANTIC_BUCKETS!$B$2:$B$348,MATCH(TRUE,ISNUMBER(SEARCH(" "&SEMANTIC_BUCKETS!$A$2:$A$348&" "," "&B20&" ")),0)))} | G20: =IF(B20="","",IF(E20>=$F$9,"FAIL",IF(E20>=$B$9,"WARN","PASS"))) | H20: {=IF(OR(B20="",D20=0),"",_xlfn.TEXTJOIN(", ",TRUE,IF(ISNUMBER(SEARCH(" "&SEMANTIC_BUCKETS!$A$2:$A$348&" "," "&B20&" ")),SEMANTIC_BUCKETS!$A$2:$A$348,"")))}
A21: =IF(B21="","",ROW()-13) | B21: {=IFERROR(_xlfn.LET(_xlpm.s,$B$10,_xlpm.norm,SUBSTITUTE(SUBSTITUTE(_xlpm.s,"!","."),"?","."),_xlpm.parts,_xlfn.TEXTSPLIT(_xlpm.norm,,".",TRUE),TRIM(INDEX(_xlpm.parts,ROW()-13))),"")} | C21: =IF(B21="","",IF(TRIM(B21)="",0,LEN(TRIM(B21))-LEN(SUBSTITUTE(TRIM(B21)," ",""))+1)) | D21: {=IF(B21="","",SUMPRODUCT(--ISNUMBER(SEARCH(" "&SEMANTIC_BUCKETS!$A$2:$A$348&" "," "&B21&" "))))} | E21: {=IF(B21="","",SUMPRODUCT(--ISNUMBER(SEARCH(" "&SEMANTIC_BUCKETS!$A$2:$A$348&" "," "&B21&" ")),SEMANTIC_BUCKETS!$E$2:$E$348))} | F21: {=IF(OR(B21="",D21=0),"",INDEX(SEMANTIC_BUCKETS!$B$2:$B$348,MATCH(TRUE,ISNUMBER(SEARCH(" "&SEMANTIC_BUCKETS!$A$2:$A$348&" "," "&B21&" ")),0)))} | G21: =IF(B21="","",IF(E21>=$F$9,"FAIL",IF(E21>=$B$9,"WARN","PASS"))) | H21: {=IF(OR(B21="",D21=0),"",_xlfn.TEXTJOIN(", ",TRUE,IF(ISNUMBER(SEARCH(" "&SEMANTIC_BUCKETS!$A$2:$A$348&" "," "&B21&" ")),SEMANTIC_BUCKETS!$A$2:$A$348,"")))}
A22: =IF(B22="","",ROW()-13) | B22: {=IFERROR(_xlfn.LET(_xlpm.s,$B$10,_xlpm.norm,SUBSTITUTE(SUBSTITUTE(_xlpm.s,"!","."),"?","."),_xlpm.parts,_xlfn.TEXTSPLIT(_xlpm.norm,,".",TRUE),TRIM(INDEX(_xlpm.parts,ROW()-13))),"")} | C22: =IF(B22="","",IF(TRIM(B22)="",0,LEN(TRIM(B22))-LEN(SUBSTITUTE(TRIM(B22)," ",""))+1)) | D22: {=IF(B22="","",SUMPRODUCT(--ISNUMBER(SEARCH(" "&SEMANTIC_BUCKETS!$A$2:$A$348&" "," "&B22&" "))))} | E22: {=IF(B22="","",SUMPRODUCT(--ISNUMBER(SEARCH(" "&SEMANTIC_BUCKETS!$A$2:$A$348&" "," "&B22&" ")),SEMANTIC_BUCKETS!$E$2:$E$348))} | F22: {=IF(OR(B22="",D22=0),"",INDEX(SEMANTIC_BUCKETS!$B$2:$B$348,MATCH(TRUE,ISNUMBER(SEARCH(" "&SEMANTIC_BUCKETS!$A$2:$A$348&" "," "&B22&" ")),0)))} | G22: =IF(B22="","",IF(E22>=$F$9,"FAIL",IF(E22>=$B$9,"WARN","PASS"))) | H22: {=IF(OR(B22="",D22=0),"",_xlfn.TEXTJOIN(", ",TRUE,IF(ISNUMBER(SEARCH(" "&SEMANTIC_BUCKETS!$A$2:$A$348&" "," "&B22&" ")),SEMANTIC_BUCKETS!$A$2:$A$348,"")))}
A23: =IF(B23="","",ROW()-13) | B23: {=IFERROR(_xlfn.LET(_xlpm.s,$B$10,_xlpm.norm,SUBSTITUTE(SUBSTITUTE(_xlpm.s,"!","."),"?","."),_xlpm.parts,_xlfn.TEXTSPLIT(_xlpm.norm,,".",TRUE),TRIM(INDEX(_xlpm.parts,ROW()-13))),"")} | C23: =IF(B23="","",IF(TRIM(B23)="",0,LEN(TRIM(B23))-LEN(SUBSTITUTE(TRIM(B23)," ",""))+1)) | D23: {=IF(B23="","",SUMPRODUCT(--ISNUMBER(SEARCH(" "&SEMANTIC_BUCKETS!$A$2:$A$348&" "," "&B23&" "))))} | E23: {=IF(B23="","",SUMPRODUCT(--ISNUMBER(SEARCH(" "&SEMANTIC_BUCKETS!$A$2:$A$348&" "," "&B23&" ")),SEMANTIC_BUCKETS!$E$2:$E$348))} | F23: {=IF(OR(B23="",D23=0),"",INDEX(SEMANTIC_BUCKETS!$B$2:$B$348,MATCH(TRUE,ISNUMBER(SEARCH(" "&SEMANTIC_BUCKETS!$A$2:$A$348&" "," "&B23&" ")),0)))} | G23: =IF(B23="","",IF(E23>=$F$9,"FAIL",IF(E23>=$B$9,"WARN","PASS"))) | H23: {=IF(OR(B23="",D23=0),"",_xlfn.TEXTJOIN(", ",TRUE,IF(ISNUMBER(SEARCH(" "&SEMANTIC_BUCKETS!$A$2:$A$348&" "," "&B23&" ")),SEMANTIC_BUCKETS!$A$2:$A$348,"")))}
A24: =IF(B24="","",ROW()-13) | B24: {=IFERROR(_xlfn.LET(_xlpm.s,$B$10,_xlpm.norm,SUBSTITUTE(SUBSTITUTE(_xlpm.s,"!","."),"?","."),_xlpm.parts,_xlfn.TEXTSPLIT(_xlpm.norm,,".",TRUE),TRIM(INDEX(_xlpm.parts,ROW()-13))),"")} | C24: =IF(B24="","",IF(TRIM(B24)="",0,LEN(TRIM(B24))-LEN(SUBSTITUTE(TRIM(B24)," ",""))+1)) | D24: {=IF(B24="","",SUMPRODUCT(--ISNUMBER(SEARCH(" "&SEMANTIC_BUCKETS!$A$2:$A$348&" "," "&B24&" "))))} | E24: {=IF(B24="","",SUMPRODUCT(--ISNUMBER(SEARCH(" "&SEMANTIC_BUCKETS!$A$2:$A$348&" "," "&B24&" ")),SEMANTIC_BUCKETS!$E$2:$E$348))} | F24: {=IF(OR(B24="",D24=0),"",INDEX(SEMANTIC_BUCKETS!$B$2:$B$348,MATCH(TRUE,ISNUMBER(SEARCH(" "&SEMANTIC_BUCKETS!$A$2:$A$348&" "," "&B24&" ")),0)))} | G24: =IF(B24="","",IF(E24>=$F$9,"FAIL",IF(E24>=$B$9,"WARN","PASS"))) | H24: {=IF(OR(B24="",D24=0),"",_xlfn.TEXTJOIN(", ",TRUE,IF(ISNUMBER(SEARCH(" "&SEMANTIC_BUCKETS!$A$2:$A$348&" "," "&B24&" ")),SEMANTIC_BUCKETS!$A$2:$A$348,"")))}
A25: =IF(B25="","",ROW()-13) | B25: {=IFERROR(_xlfn.LET(_xlpm.s,$B$10,_xlpm.norm,SUBSTITUTE(SUBSTITUTE(_xlpm.s,"!","."),"?","."),_xlpm.parts,_xlfn.TEXTSPLIT(_xlpm.norm,,".",TRUE),TRIM(INDEX(_xlpm.parts,ROW()-13))),"")} | C25: =IF(B25="","",IF(TRIM(B25)="",0,LEN(TRIM(B25))-LEN(SUBSTITUTE(TRIM(B25)," ",""))+1)) | D25: {=IF(B25="","",SUMPRODUCT(--ISNUMBER(SEARCH(" "&SEMANTIC_BUCKETS!$A$2:$A$348&" "," "&B25&" "))))} | E25: {=IF(B25="","",SUMPRODUCT(--ISNUMBER(SEARCH(" "&SEMANTIC_BUCKETS!$A$2:$A$348&" "," "&B25&" ")),SEMANTIC_BUCKETS!$E$2:$E$348))} | F25: {=IF(OR(B25="",D25=0),"",INDEX(SEMANTIC_BUCKETS!$B$2:$B$348,MATCH(TRUE,ISNUMBER(SEARCH(" "&SEMANTIC_BUCKETS!$A$2:$A$348&" "," "&B25&" ")),0)))} | G25: =IF(B25="","",IF(E25>=$F$9,"FAIL",IF(E25>=$B$9,"WARN","PASS"))) | H25: {=IF(OR(B25="",D25=0),"",_xlfn.TEXTJOIN(", ",TRUE,IF(ISNUMBER(SEARCH(" "&SEMANTIC_BUCKETS!$A$2:$A$348&" "," "&B25&" ")),SEMANTIC_BUCKETS!$A$2:$A$348,"")))}
... A213: =IF(B213="","",ROW()-13) | B213: {=IFERROR(_xlfn.LET(_xlpm.s,$B$10,_xlpm.norm,SUBSTITUTE(SUBSTITUTE(_xlpm.s,"!","."),"?","."),_xlpm.parts,_xlfn.TEXTSPLIT(_xlpm.norm,,".",TRUE),TRIM(INDEX(_xlpm.parts,ROW()-13))),"")} | C213: =IF(B213="","",IF(TRIM(B213)="",0,LEN(TRIM(B213))-LEN(SUBSTITUTE(TRIM(B213)," ",""))+1)) | D213: {=IF(B213="","",SUMPRODUCT(--ISNUMBER(SEARCH(" "&SEMANTIC_BUCKETS!$A$2:$A$348&" "," "&B213&" "))))} | E213: {=IF(B213="","",SUMPRODUCT(--ISNUMBER(SEARCH(" "&SEMANTIC_BUCKETS!$A$2:$A$348&" "," "&B213&" ")),SEMANTIC_BUCKETS!$E$2:$E$348))} | F213: {=IF(OR(B213="",D213=0),"",INDEX(SEMANTIC_BUCKETS!$B$2:$B$348,MATCH(TRUE,ISNUMBER(SEARCH(" "&SEMANTIC_BUCKETS!$A$2:$A$348&" "," "&B213&" ")),0)))} | G213: =IF(B213="","",IF(E213>=$F$9,"FAIL",IF(E213>=$B$9,"WARN","PASS"))) | H213: {=IF(OR(B213="",D213=0),"",_xlfn.TEXTJOIN(", ",TRUE,IF(ISNUMBER(SEARCH(" "&SEMANTIC_BUCKETS!$A$2:$A$348&" "," "&B213&" ")),SEMANTIC_BUCKETS!$A$2:$A$348,"")))}
A215: BUCKET BREAKDOWN
A216: Bucket | B216: Sentences hit
A217: ANTI_FRUIT_BEHAVIOR_EXPANSION | B217: =COUNTIF($F$14:$F$213,A217) -> 0
A218: CLAIM_STRENGTH | B218: =COUNTIF($F$14:$F$213,A218) -> 0
A219: DANGER_LANGUAGE | B219: =COUNTIF($F$14:$F$213,A219) -> 0
A220: DRIFT_WARNING | B220: =COUNTIF($F$14:$F$213,A220) -> 0
A221: EVIDENCE_MATURITY | B221: =COUNTIF($F$14:$F$213,A221) -> 0
A222: FALSIFICATION | B222: =COUNTIF($F$14:$F$213,A222) -> 0
A223: FORMAL_PROOF | B223: =COUNTIF($F$14:$F$213,A223) -> 0
A224: FRUIT_BEHAVIOR_EXPANSION | B224: =COUNTIF($F$14:$F$213,A224) -> 0
A225: METHODS_PROVENANCE | B225: =COUNTIF($F$14:$F$213,A225) -> 0
A226: PREFERRED_REPLACEMENT | B226: =COUNTIF($F$14:$F$213,A226) -> 0
A227: REDUCTION_QUALITY | B227: =COUNTIF($F$14:$F$213,A227) -> 0
A228: RELATION_TYPE | B228: =COUNTIF($F$14:$F$213,A228) -> 0
... A230: THEOLOGICAL_STATUS | B230: =COUNTIF($F$14:$F$213,A230) -> 0

Sheet SUPRA_INFRAQUE
A1: SUPRA INFRAQUE — Radical Epistemic Storage Schema v1
A2: Ontology-first, question-driven epistemic graph for the full Theophysics corpus — without collapsing theology into physics, treating mathematics as empirical proof, or hiding assumptions inside classifications.
A4: THE REDESIGN IN ONE SENTENCE
A5: The file is no longer the unit of knowledge: the system stores independently identifiable questions, statements, axioms, constitutive disclosures, definitions, derivations, bridges, evidence units, countermodels, predictions, protocols, tests, results, and interpretations — while files remain immutable provenance containers that may hold any number of those objects.
A7: GOVERNING COMMITMENTS
A8: 2.1 Ontology before classification | B8: First ask what kind of thing a record is and what it asserts. Do not begin by forcing it into a scientific, theological, mathematical, or philosophical verdict.
A9: 2.2 Questions before inferred answers | B9: Neutral questions define the information slots. A question may specify a contrast, test, or required distinction; it may not presuppose the preferred conclusion.
A10: 2.3 Classification is multidimensional | B10: No single label represents both what a statement does and what it is about. Logical role and ontological domain are independent axes, plus warrant, status, relation to A0, mode, testability.
A11: 2.4 Unpacking is not addition | B11: A0 is one content-rich Triune axiom. Trinity, Being, Truth, Goodness, Love, relational distinction, positive fruits are constitutive disclosures/semantic unpackings — not independent axioms unless an argument explicitly posits another primitive.
A12: 2.5 A bridge is a claim | B12: No cross-domain transition is automatic. Each must be stored as a bridge dossier with mapping, preserved structure, assumptions, loss, direction, and tests.
A13: 2.6 Evidence is not interpretation | B13: Observations, measurements, quotations, datasets, and formal results are stored separately from what an author believes they mean. Competing interpretations may cite the same evidence unit.
A14: 2.7 Good and privation are not forced into symmetry | B14: The schema can represent truth as prior to falsehood, life to death, good to corruption. Negative states may be privative/parasitic/corruptive/derivative rather than co-original positive substances. A representational capability, not a DB-imposed conclusion.
A15: 2.8 Append, assess, supersede — do not silently overwrite | B15: Historical classifications and assessments remain visible. Corrections create new versions or superseding records so the development of the theory can be audited.
A17: THE SIX INTERLOCKING PLANES | B17: Stores | C17: Governing question
A18: Provenance | B18: artifacts, versions, spans, authors, dates, hashes | C18: Where exactly did this come from?
A19: Inquiry | B19: neutral questions, runs, responses, leakage checks | C19: What was asked, under what framing, and what appeared?
A20: Semantic | B20: statements and other epistemic objects | C20: What exactly is being said or represented?
A21: Inferential | B21: typed relationships and warrants | C21: How does one object depend on or affect another?
A22: Evaluation | B22: evidence, formalization, bridges, tests, objections | C22: What licenses, limits, tests, or defeats it?
A23: Governance | B23: versions, statuses, conflicts, decisions, audit trail | C23: Who changed what, why, and with what authority?
A24: Logical planes, not necessarily separate databases. PostgreSQL = authoritative store; a graph projection supports traversal; vector indexes assist retrieval but must never become the source of truth.
A26: THREE INQUIRY LEVELS — Methodus Veritatis Supra Infraque
A27: Supra-systemic | B27: Asks what must be true for the system, distinction, inquiry, or meaning to be possible.
A28: Intra-systemic | B28: Asks what the proposed system claims and how its parts relate.
A29: Infra-systemic | B29: Asks what observable, formal, experiential, or behavioral consequences occur within implementations.

Sheet FRUIT_RETRIEVAL_LEXICON_V2
A1: FRUIT RETRIEVAL LEXICON V2 — retrieval hierarchy with semantic controls
A2: Retrieval class | B2: Meaning / scanner handling
A3: CANONICAL | B3: Exact named fruit — high-confidence hit
A4: DIRECT | B4: Near-synonym or grammatical form — high-confidence hit
A5: FUNCTIONAL | B5: Describes the fruit in action — medium-confidence; inspect context
A6: RELATIONAL | B6: Often co-occurs but can mean something else — low-confidence; context required
A7: AMBIGUOUS | B7: May indicate several fruits or none — do not assign automatically
A8: ANTI | B8: Counter-orientation or corruption — separate negative signal
A9: GOVERNING | B9: Truth terms — track globally; do not score as a ninth fruit
A11: fruit_key | B11: fruit_display | C11: greek_term | D11: term | E11: normalized_term | F11: retrieval_class | G11: core_semantic_center | H11: boundary_note
A12: love | B12: Love | C12: agapē | D12: love | E12: love | F12: CANONICAL | G12: Willing, seeking, protecting, and participating in another's true good without reducing them to use, exchange, tribe, sentiment, or possession. | H12: Love is not identical to approval, permissiveness, emotional intensity, sexual desire, tribal loyalty, or nonjudgment. It must remain ordered to true good.
A13: love | B13: Love | C13: agapē | D13: agape | E13: agape | F13: CANONICAL | G13: Willing, seeking, protecting, and participating in another's true good without reducing them to use, exchange, tribe, sentiment, or possession. | H13: Love is not identical to approval, permissiveness, emotional intensity, sexual desire, tribal loyalty, or nonjudgment. It must remain ordered to true good.
A14: love | B14: Love | C14: agapē | D14: charity | E14: charity | F14: CANONICAL | G14: Willing, seeking, protecting, and participating in another's true good without reducing them to use, exchange, tribe, sentiment, or possession. | H14: Love is not identical to approval, permissiveness, emotional intensity, sexual desire, tribal loyalty, or nonjudgment. It must remain ordered to true good.
A15: love | B15: Love | C15: agapē | D15: affection | E15: affection | F15: DIRECT | G15: Willing, seeking, protecting, and participating in another's true good without reducing them to use, exchange, tribe, sentiment, or possession. | H15: Love is not identical to approval, permissiveness, emotional intensity, sexual desire, tribal loyalty, or nonjudgment. It must remain ordered to true good.
A16: love | B16: Love | C16: agapē | D16: benevolence | E16: benevolence | F16: DIRECT | G16: Willing, seeking, protecting, and participating in another's true good without reducing them to use, exchange, tribe, sentiment, or possession. | H16: Love is not identical to approval, permissiveness, emotional intensity, sexual desire, tribal loyalty, or nonjudgment. It must remain ordered to true good.
A17: love | B17: Love | C17: agapē | D17: compassion | E17: compassion | F17: DIRECT | G17: Willing, seeking, protecting, and participating in another's true good without reducing them to use, exchange, tribe, sentiment, or possession. | H17: Love is not identical to approval, permissiveness, emotional intensity, sexual desire, tribal loyalty, or nonjudgment. It must remain ordered to true good.
A18: love | B18: Love | C18: agapē | D18: mercy | E18: mercy | F18: DIRECT | G18: Willing, seeking, protecting, and participating in another's true good without reducing them to use, exchange, tribe, sentiment, or possession. | H18: Love is not identical to approval, permissiveness, emotional intensity, sexual desire, tribal loyalty, or nonjudgment. It must remain ordered to true good.
A19: love | B19: Love | C19: agapē | D19: care | E19: care | F19: DIRECT | G19: Willing, seeking, protecting, and participating in another's true good without reducing them to use, exchange, tribe, sentiment, or possession. | H19: Love is not identical to approval, permissiveness, emotional intensity, sexual desire, tribal loyalty, or nonjudgment. It must remain ordered to true good.
A20: love | B20: Love | C20: agapē | D20: devotion | E20: devotion | F20: DIRECT | G20: Willing, seeking, protecting, and participating in another's true good without reducing them to use, exchange, tribe, sentiment, or possession. | H20: Love is not identical to approval, permissiveness, emotional intensity, sexual desire, tribal loyalty, or nonjudgment. It must remain ordered to true good.
A21: love | B21: Love | C21: agapē | D21: goodwill | E21: goodwill | F21: DIRECT | G21: Willing, seeking, protecting, and participating in another's true good without reducing them to use, exchange, tribe, sentiment, or possession. | H21: Love is not identical to approval, permissiveness, emotional intensity, sexual desire, tribal loyalty, or nonjudgment. It must remain ordered to true good.
A22: love | B22: Love | C22: agapē | D22: loving-kindness | E22: loving-kindness | F22: DIRECT | G22: Willing, seeking, protecting, and participating in another's true good without reducing them to use, exchange, tribe, sentiment, or possession. | H22: Love is not identical to approval, permissiveness, emotional intensity, sexual desire, tribal loyalty, or nonjudgment. It must remain ordered to true good.
... A546: truth | B546: Truth (governing) | C546: alētheia | D546: truth | E546: truth | F546: CANONICAL | G546: Governing condition: names and applies what is real. Truth governs the recognition and application of the nine fruits; it is not itself a ninth fruit. | H546: Truth is necessary but not sufficient. A statement can be factually accurate and still be delivered cruelly, manipulatively, prematurely, or dominantly. An act styled as 'loving' that conceals or distorts reality fails the governing condition.
A547: truth | B547: Truth (governing) | C547: alētheia | D547: TRUE | E547: TRUE | F547: CANONICAL | G547: Governing condition: names and applies what is real. Truth governs the recognition and application of the nine fruits; it is not itself a ninth fruit. | H547: Truth is necessary but not sufficient. A statement can be factually accurate and still be delivered cruelly, manipulatively, prematurely, or dominantly. An act styled as 'loving' that conceals or distorts reality fails the governing condition.
A548: truth | B548: Truth (governing) | C548: alētheia | D548: truthfulness | E548: truthfulness | F548: CANONICAL | G548: Governing condition: names and applies what is real. Truth governs the recognition and application of the nine fruits; it is not itself a ninth fruit. | H548: Truth is necessary but not sufficient. A statement can be factually accurate and still be delivered cruelly, manipulatively, prematurely, or dominantly. An act styled as 'loving' that conceals or distorts reality fails the governing condition.
A549: truth | B549: Truth (governing) | C549: alētheia | D549: honesty | E549: honesty | F549: DIRECT | G549: Governing condition: names and applies what is real. Truth governs the recognition and application of the nine fruits; it is not itself a ninth fruit. | H549: Truth is necessary but not sufficient. A statement can be factually accurate and still be delivered cruelly, manipulatively, prematurely, or dominantly. An act styled as 'loving' that conceals or distorts reality fails the governing condition.
A550: truth | B550: Truth (governing) | C550: alētheia | D550: candor | E550: candor | F550: DIRECT | G550: Governing condition: names and applies what is real. Truth governs the recognition and application of the nine fruits; it is not itself a ninth fruit. | H550: Truth is necessary but not sufficient. A statement can be factually accurate and still be delivered cruelly, manipulatively, prematurely, or dominantly. An act styled as 'loving' that conceals or distorts reality fails the governing condition.
A551: truth | B551: Truth (governing) | C551: alētheia | D551: sincerity | E551: sincerity | F551: DIRECT | G551: Governing condition: names and applies what is real. Truth governs the recognition and application of the nine fruits; it is not itself a ninth fruit. | H551: Truth is necessary but not sufficient. A statement can be factually accurate and still be delivered cruelly, manipulatively, prematurely, or dominantly. An act styled as 'loving' that conceals or distorts reality fails the governing condition.
A552: truth | B552: Truth (governing) | C552: alētheia | D552: accuracy | E552: accuracy | F552: DIRECT | G552: Governing condition: names and applies what is real. Truth governs the recognition and application of the nine fruits; it is not itself a ninth fruit. | H552: Truth is necessary but not sufficient. A statement can be factually accurate and still be delivered cruelly, manipulatively, prematurely, or dominantly. An act styled as 'loving' that conceals or distorts reality fails the governing condition.
A553: truth | B553: Truth (governing) | C553: alētheia | D553: veracity | E553: veracity | F553: DIRECT | G553: Governing condition: names and applies what is real. Truth governs the recognition and application of the nine fruits; it is not itself a ninth fruit. | H553: Truth is necessary but not sufficient. A statement can be factually accurate and still be delivered cruelly, manipulatively, prematurely, or dominantly. An act styled as 'loving' that conceals or distorts reality fails the governing condition.
A554: truth | B554: Truth (governing) | C554: alētheia | D554: integrity | E554: integrity | F554: DIRECT | G554: Governing condition: names and applies what is real. Truth governs the recognition and application of the nine fruits; it is not itself a ninth fruit. | H554: Truth is necessary but not sufficient. A statement can be factually accurate and still be delivered cruelly, manipulatively, prematurely, or dominantly. An act styled as 'loving' that conceals or distorts reality fails the governing condition.
A555: truth | B555: Truth (governing) | C555: alētheia | D555: transparency | E555: transparency | F555: DIRECT | G555: Governing condition: names and applies what is real. Truth governs the recognition and application of the nine fruits; it is not itself a ninth fruit. | H555: Truth is necessary but not sufficient. A statement can be factually accurate and still be delivered cruelly, manipulatively, prematurely, or dominantly. An act styled as 'loving' that conceals or distorts reality fails the governing condition.
A556: truth | B556: Truth (governing) | C556: alētheia | D556: fidelity to reality | E556: fidelity to reality | F556: DIRECT | G556: Governing condition: names and applies what is real. Truth governs the recognition and application of the nine fruits; it is not itself a ninth fruit. | H556: Truth is necessary but not sufficient. A statement can be factually accurate and still be delivered cruelly, manipulatively, prematurely, or dominantly. An act styled as 'loving' that conceals or distorts reality fails the governing condition.
A557: truth | B557: Truth (governing) | C557: alētheia | D557: factuality | E557: factuality | F557: DIRECT | G557: Governing condition: names and applies what is real. Truth governs the recognition and application of the nine fruits; it is not itself a ninth fruit. | H557: Truth is necessary but not sufficient. A statement can be factually accurate and still be delivered cruelly, manipulatively, prematurely, or dominantly. An act styled as 'loving' that conceals or distorts reality fails the governing condition.
A558: truth | B558: Truth (governing) | C558: alētheia | D558: correctness | E558: correctness | F558: DIRECT | G558: Governing condition: names and applies what is real. Truth governs the recognition and application of the nine fruits; it is not itself a ninth fruit. | H558: Truth is necessary but not sufficient. A statement can be factually accurate and still be delivered cruelly, manipulatively, prematurely, or dominantly. An act styled as 'loving' that conceals or distorts reality fails the governing condition.
A559: truth | B559: Truth (governing) | C559: alētheia | D559: names what is real | E559: names what is real | F559: FUNCTIONAL | G559: Governing condition: names and applies what is real. Truth governs the recognition and application of the nine fruits; it is not itself a ninth fruit. | H559: Truth is necessary but not sufficient. A statement can be factually accurate and still be delivered cruelly, manipulatively, prematurely, or dominantly. An act styled as 'loving' that conceals or distorts reality fails the governing condition.
... A595: truth | B595: Truth (governing) | C595: alētheia | D595: gaslighting | E595: gaslighting | F595: ANTI | G595: Governing condition: names and applies what is real. Truth governs the recognition and application of the nine fruits; it is not itself a ninth fruit. | H595: Truth is necessary but not sufficient. A statement can be factually accurate and still be delivered cruelly, manipulatively, prematurely, or dominantly. An act styled as 'loving' that conceals or distorts reality fails the governing condition.
A598: ANTI-FRUIT TAXONOMY BY TYPE
A599: Not every fruit-like word is a fruit: a term may be a deficiency, an excess/counterfeit, or a direct contrary. A = {privation, distortion, excess, deficiency, counterfeit}.
A600: Fruit | B600: Deficiency | C600: Excess / counterfeit | D600: Direct contrary
A601: Love | B601: Indifference | C601: Possessiveness, enabling | D601: Hatred, exploitation
A602: Joy | B602: Despair | C602: Denial, mania, triumphalism | D602: Resentment, envy
A603: Peace | B603: Fragmentation | C603: Appeasement, false peace | D603: Hostility, violence
A604: Patience | B604: Impatience | C604: Passivity, enabling delay | D604: Rage, forced timing
A605: Kindness | B605: Coldness | C605: People-pleasing | D605: Cruelty, contempt
A606: Goodness | B606: Corruption | C606: Moralism, legalism | D606: Wickedness, injustice
A607: Faithfulness | B607: Fickleness | C607: Blind loyalty | D607: Betrayal, abandonment
A608: Gentleness | B608: Harshness | C608: Weakness, evasion | D608: Domination, brutality
A609: Self-control | B609: Compulsion | C609: Repression, rigidity | D609: Indulgence, recklessness

Sheet SI_OBJECT_TYPES
A1: EPISTEMIC OBJECT — REQUIRED CORE FIELDS
A2: Field | B2: Meaning
A3: object_id | B3: Immutable machine identity, preferably UUID/ULID
A4: human_code | B4: Stable readable code such as A0, Q-014, CLM-208, BR-031
A5: object_type | B5: Primary logical object type
A6: canonical_text | B6: Smallest complete statement or definition
A7: scope | B7: Universe, framework, model, population, time, or conditions covered
A8: modality | B8: Necessary, possible, actual, probable, conditional, normative, interrogative
A9: polarity | B9: Affirmed, denied, suspended, alternative
A10: owner_framework | B10: Framework in which the object is defined
A11: status | B11: Draft, proposed, active, contested, supported, defeated, superseded, retired
A12: created_by / created_at | B12: Authorship and time
A13: version | B13: Semantic version of this object
A14: OBJECT TYPES — CONTROLLED VOCABULARY
A15: Family | B15: Types
A16: Foundations | B16: AXIOM, CONSTITUTIVE_DISCLOSURE, PRIMITIVE, DEFINITION, DISTINCTION
A17: Inquiry | B17: QUESTION, QUESTION_FAMILY, RESPONSE, OBSERVATION
A18: Reasoning | B18: CLAIM, PREMISE, LEMMA, THEOREM, COROLLARY, DERIVATION, INFERENCE_RULE
A19: Representation | B19: MODEL, FORMAL_EXPRESSION, ANALOGY, METAPHOR, INTERPRETATION
A20: Connection | B20: BRIDGE, TRANSLATION, CORRESPONDENCE, IDENTITY_CLAIM
A21: Evaluation | B21: EVIDENCE_UNIT, PREDICTION, PROTOCOL, TEST, RESULT, FALSIFIER, DEFEATER
A22: Critique | B22: OBJECTION, COUNTEREXAMPLE, COUNTERMODEL, ALTERNATIVE_EXPLANATION, LIMITATION
A23: Synthesis | B23: LAW, PRINCIPLE, SYNTHESIS, APPLICATION
A24: The primary type answers 'what does this record do?' Secondary logical-role tags are allowed, but one primary type is mandatory in each argument context.

Sheet SI_CLASS_AXES
A1: MULTIAXIAL CLASSIFICATION — INDEPENDENT AXES
A2: Classification is stored as assignments, not hard-coded columns. One object carries multiple domains and can be reassessed without mutation. Each assignment records classifier, date, confidence, rationale, source. Conflicting assignments may coexist until adjudicated.
A3: Axis | B3: Example terms
A4: Logical role | B4: definition, axiom, theorem, model, bridge, prediction, interpretation
A5: Ontological domain | B5: mathematical, physical, informational, theological, consciousness, moral, cosmological, relational, ontological, epistemic
A6: Relation to A0 | B6: constitutive of, disclosed by, derived from, compatible with, independent of, opposed to, unassessed
A7: Ontological mode | B7: positive-prior, dependent-positive, relational, privative, corruptive, operational, representational, formal-only, empirical-candidate
A8: Warrant type | B8: axiomatic, deductive, abductive, inductive, testimonial, revelatory, phenomenological, empirical, pragmatic, analogical
A9: Formal status | B9: unformalized, notation-only, defined, derived, proven-relative-to-premises, simulated, dimensionally checked
A10: Empirical status | B10: non-empirical, operationalizable, predicted, protocol-ready, tested, replicated, disconfirmed, underdetermined
A11: Epistemic status | B11: stipulated, inferred, observed, interpreted, contested, provisionally accepted, rejected
A12: Bridge strength | B12: metaphorical, heuristic, structural analogy, homomorphism, isomorphism, causal proposal, identity claim
A13: PRIMARY + SECONDARY EXAMPLE (one object, many independent facts)
A14: primary logical role | B14: BRIDGE
A15: primary domain | B15: INFORMATIONAL
A16: secondary domains | B16: THEOLOGICAL, PHYSICAL
A17: warrant | B17: ABDUCTIVE
A18: empirical status | B18: OPERATIONALIZABLE
A19: bridge strength | B19: CAUSAL_PROPOSAL
A20: The system must never convert these independent facts into one opaque label.

Sheet SI_RELATIONS
A1: TYPED RELATIONS — THE INFERENCE GRAPH
A2: An edge is never 'just a link'; it states a relationship and requires its own provenance and warrant. The derivation subgraph must be acyclic — other relations may form cycles, but cycles cannot masquerade as proofs.
A3: Relation group | B3: Edge types
A4: Constitution | B4: CONSTITUTIVE_OF, DISCLOSES, DEFINES, HAS_PART, INSTANTIATES
A5: Inference | B5: DEPENDS_ON, DERIVED_FROM, ENTAILS, IMPLIES, COROLLARY_OF, USES_RULE
A6: Evidence | B6: SUPPORTS, WEAKENS, CONTRADICTS, UNDERDETERMINES, EXPLAINS, PREDICTS
A7: Testing | B7: TESTS, FALSIFIES_IF, CONFIRMS_IF, IMPLEMENTS_PROTOCOL, PRODUCES_RESULT
A8: Bridging | B8: MAPS_FROM, MAPS_TO, PRESERVES, LOSES, TRANSLATES, CORRESPONDS_TO
A9: Critique | B9: OBJECTS_TO, COUNTEREXAMPLE_TO, COUNTERMODEL_TO, DEFEATS, LIMITS
A10: Governance | B10: DUPLICATES, REFINES, SUPERSEDES, RETRACTS, CONFLICTS_WITH
A11: EVERY CONSEQUENTIAL EDGE RECORDS
A12: source and target object versions; direction; relation type; whether it claims necessity/sufficiency/probability/compatibility/analogy; stated warrant; supporting source spans; assumptions required; confidence and status; defeat conditions.
A13: A0 AND CONSTITUTIVE DISCLOSURE
A14: Object | B14: Type / Relation
A15: A0 | B15: AXIOM — root declaration of the Triune God
A16: Trinity | B16: CONSTITUTIVE_DISCLOSURE — CONSTITUTIVE_OF A0
A17: Being / 'I AM' | B17: CONSTITUTIVE_DISCLOSURE — CONSTITUTIVE_OF A0
A18: Truth | B18: CONSTITUTIVE_DISCLOSURE — CONSTITUTIVE_OF A0
A19: Goodness | B19: CONSTITUTIVE_DISCLOSURE — CONSTITUTIVE_OF A0
A20: Love | B20: CONSTITUTIVE_DISCLOSURE — CONSTITUTIVE_OF A0
A21: Relational distinction without division | B21: CONSTITUTIVE_DISCLOSURE — CONSTITUTIVE_OF A0
A22: Positive fruits / dispositional expressions | B22: CONSTITUTIVE_DISCLOSURE or DERIVED_EXPRESSION (as argued) — linked with explicit warrant
A23: A0 AUDIT — every proposed disclosure must answer
A24: 1 | B24: Is this constitutive, definitional, entailed, inferred, analogical, or merely associated?
A25: 2 | B25: Could A0 remain numerically the same axiom if this content were denied?
A26: 3 | B26: Is the disclosure textually declared, logically required, traditionally received, or introduced by the present model?
A27: 4 | B27: What later derivations depend on it?
A28: 5 | B28: Does moving it into or out of A0 change the theory's conclusions?

Sheet SI_SCHEMA_TABLES
A1: MINIMAL RELATIONAL IMPLEMENTATION
A2: Table | B2: Purpose | C2: Plane
A3: artifacts | B3: stable source identities | C3: Provenance
A4: artifact_versions | B4: immutable source versions and hashes | C4: Provenance
A5: source_spans | B5: precise source locators | C5: Provenance
A6: epistemic_objects | B6: universal typed object registry | C6: Semantic
A7: object_versions | B7: canonical text and scoped semantic versions | C7: Semantic
A8: object_occurrences | B8: object-to-source-span links | C8: Semantic
A9: relation_types | B9: controlled edge vocabulary | C9: Inferential
A10: relations | B10: versioned, warranted edges | C10: Inferential
A11: classification_axes | B11: independent dimensions | C11: Semantic
A12: classification_terms | B12: controlled values within axes | C12: Semantic
A13: classification_assignments | B13: multivalued, assessed classifications | C13: Semantic
... A28: change_events | B28: audit trail and supersession decisions | C28: Governance
A29: Use JSONB only for genuinely extensible secondary metadata. Identities, types, relations, statuses, provenance, and critical evaluation fields must remain queryable and constrained.

Sheet SI_VALIDATION
A1: VALIDATION RULES — reject or flag
A2: 1 | B2: a claim with no canonical text or scope
A3: 2 | B3: an evidence citation with no retrievable source locator
A4: 3 | B4: a derivation cycle
A5: 4 | B5: a cross-domain edge lacking a bridge dossier
A6: 5 | B6: a theorem lacking explicit premises
A7: 6 | B7: an empirical conclusion supported only by notation
A8: 7 | B8: a 'proven' status without a declared proof system or protocol
A9: 8 | B9: a question whose wording contains its expected answer
A10: 9 | B10: a result record that contains interpretation but no raw observation link
A11: 10 | B11: a constitutive disclosure treated as an independent axiom without adjudication
A12: 11 | B12: a new A0 disclosure with no semantic-addition audit
A13: 12 | B13: a classification that combines logical role and domain into one untraceable label
... A16: 15 | B16: a bridge based only on lexical similarity
A17: TEST CHAIN — each stage is a separate object
A18: CLAIM → PREDICTION → OPERATIONALIZATION → PROTOCOL → TEST RUN → RESULT → INTERPRETATION → ASSESSMENT
A19: DEFEAT CONDITIONS — every load-bearing object must declare relevant forms ('N/A' only with a reason)
A20: logical contradiction • countermodel • failed entailment • empirical falsifier • unsuccessful replication • superior alternative explanation • category error • bridge failure • source/provenance failure • scope violation • semantic equivocation
A22: MIGRATION FROM EXISTING CORPUS
A23: Phase 1 — Freeze & register sources | B23: Hash every artifact version. Preserve filenames and existing codes as aliases. Do not reorganize content during registration.
A24: Phase 2 — Extract without adjudicating | B24: Segment into candidate questions, declarations, definitions, claims, equations, bridges, evidence units, predictions, objections, limitations. Retain verbatim spans.
A25: Phase 3 — Normalize objects | B25: Merge true duplicates preserving occurrences. Split compound claims. Assign stable readable codes independent of file order.
A26: Phase 4 — Reconstruct A0 | B26: Register A0 once. Classify candidate content as constitutive disclosure, definition, entailment, inference, or later association. Record disagreements rather than resolving by import order.
A27: Phase 5 — Build dependency graph | B27: Add explicit edges, then identify unsupported transitions, circular derivations, hidden premises, load-bearing bridges.
A28: Phase 6 — Attach evaluation | B28: Connect evidence, formal expressions, tests, countermodels, limitations, defeat conditions.
A29: Phase 7 — Run neutral inquiry | B29: Only after slots and validation rules are frozen: finalize and execute the unbiased question canon. Prevents the desired answer from redesigning the questions after the fact.
A30: FIVE DECISIONS REQUIRED BEFORE V1 IS FROZEN (governance, not software defaults)
A31: 1. A0 disclosure boundary | B31: Which properties are strictly constitutive, and which are derived expressions?
A32: 2. Canonical codes | B32: Whether readable identifiers follow families such as AX, DSC, Q, CLM, BR, EVD, TST.
A33: 3. Bridge threshold | B33: Which cross-domain relations require a full dossier vs a lighter translation record?
A34: 4. Assessment vocabulary | B34: Whether 'supported', 'established', and 'proven' receive domain-specific definitions.
A35: 5. Question freeze procedure | B35: How blind, adversarial, and repeated runs are versioned before results are reviewed.
A36: ACCEPTANCE CRITERIA — represent all of these without contradiction or loss
A37: one Triune A0 with many inseparable disclosures but no accidental axiom multiplication
A38: a question asked before a claim exists, and the later claim it reveals
A39: the same statement serving different logical roles in different arguments
A40: dual or multiple ontological domains
A41: a theological claim evaluated as theological without being dismissed for not being physics
A42: a physical claim denied empirical status until operationalized and tested
A43: a mathematical result valid relative to premises without metaphysical overreach
A44: good as positive-prior and evil as a proposed privation, while retaining room for rival models
A45: several interpretations of one evidence unit
A46: a bridge that succeeds structurally but fails as an identity claim
A47: uncertainty, objection, defeat, correction, and supersession without erasing history
A48: exact reconstruction of why any conclusion was reached

Sheet BFP_DG_GRAMMAR
A1: BFP-DG GRAMMAR — THE ENGINE
A2: Bidirectional First-Principles Discovery Grammar. Run any raw expression through forward discovery (Q0–Q14), reverse reconstruction (B0–B8), convergence, and the Why-Closure Gate. Classifications emerge; they are not presupposed.
A3: Phase | B3: Step | C3: What it asks
A4: FORWARD | B4: Q0 | C4: Exact expression — preserve verbatim, not yet classified
A5: FORWARD | B5: Q1 | C5: What is being picked out? (referent; one/many; same/changing; real/possible/imagined)
A6: FORWARD | B6: Q2 | C6: What makes it this rather than not-this? (identity & distinguishing conditions)
A7: FORWARD | B7: Q3 | C7: What is required for the expression to have meaning? (dependency floor)
A8: FORWARD | B8: Q4 | C8: What can vary while it remains the same referent? (state space & invariants)
A9: FORWARD | B9: Q5 | C9: What can it do, undergo, or participate in? (operation signature)
A10: FORWARD | B10: Q6 | C10: What connects one valid state to another? (transition rule & mechanism)
A11: FORWARD | B11: Q7 | C11: What limits the possibilities? (admissible / forbidden states, domain of validity)
A12: FORWARD | B12: Q8 | C12: What necessarily follows if the expression is granted? (inference rules)
A13: FORWARD | B13: Q9 | C13: In what forms can the structure be represented? (representation ladder)
A14: FORWARD | B14: Q10 | C14: What does each representation preserve and lose?
... A33: GATE | B33: Gate outcome | C33: WHY_CLOSED (with closure level) or WHY_OPEN (with honest boundary flagged)

Sheet BFP_DG_PRIMITIVES
A1: BFP-DG APPLIED: THEOPHYSICS PRIMITIVE ANALYSIS
A2: Bidirectional First-Principles Discovery Grammar — Q0–Q14 forward, B0–B8 reverse, convergence, why-closure. Classifications emerge from analysis; not presupposed.
A4: RAW EXPRESSION → | B4: A separation can be made. | C4: number | D4: God | E4: scientific method
A5: GRAMMAR STEP | B5: THE MARK | C5: NUMBER | D5: GOD | E5: SCIENTIFIC METHOD
A6: Raw Expression | B6: RAW: A separation can be made. SPEAKER-INTENDED QUESTION: What is the most primitive act from which all structure follows? CONTEXT: Attempt to find a fixed point that cannot be denied without performing it. | C6: RAW: number SPEAKER-INTENDED QUESTION: What is number, and does it drop out of the primitive? CONTEXT: BFP-DG worked skeleton (section 9, document BFP-DG-0.1) | D6: RAW: God SPEAKER-INTENDED QUESTION: Does God drop out of the primitive, and if so, in what form? CONTEXT: BFP-DG worked skeleton; Theophysics framework. | E6: RAW: scientific method SPEAKER-INTENDED QUESTION: Does the scientific method drop out of the primitive? CONTEXT: BFP-DG worked skeleton (section 9, document BFP-DG-0.1)
A7: Forward Discovery (Q0–Q14)
A8: Q0 — Exact Expression | B8: "A separation can be made." Preserved verbatim. Not yet classified. | C8: "number" | D8: "God" | E8: "scientific method"
A9: Q1 — What is being picked out? | B9: REFERRED CONTENT: The act of making a distinction, not the things distinguished. ONE OR MANY: One act. SAME OR CHANGING: The act is repeatable; each performance is a new token of the same type. REAL/POSSIBLE/IMAGINED/UNDECIDED: The act is performable. Its possibility is demonstrated by any utterance, thought, or perception. Output candidate: Referent = the act of distinction (μ). | C9: REFERRED CONTENT: Something used to discriminate quantity, order, or position. ONE OR MANY: Many numbers, but the concept is one. SAME OR CHANGING: The concept is stable; individual numbers are immutable. REAL/POSSIBLE/IMAGINED/UNDECIDED: Numbers are used as if real. Ontological status disputed (Platonist, nominalist, structuralist, formalist, fictionalist). | D9: REFERRED CONTENT: Proposed ultimate ground of all existence, consciousness, value, and intelligibility. ONE OR MANY: One in essence; three in person (Trinitarian claim). SAME OR CHANGING: Eternal, unchanging in essence; internally dynamic in relation. REAL/POSSIBLE/IMAGINED/UNDECIDED: Claimed as real and necessary. Disputed by atheism, agnosticism, alternative theisms. | E9: REFERRED CONTENT: Proposed disciplined inquiry process for discovering patterns in nature. ONE OR MANY: One method with many variations. SAME OR CHANGING: Core structure stable; specific procedures evolve. REAL/POSSIBLE/IMAGINED/UNDECIDED: Real and practiced. Philosophical foundations disputed.
A10: Q2 — What makes it this rather than not-this? | B10: IDENTITY: The act is identifiable as the same type across performances. DISTINGUISHING: The act creates two sides where before there was one; result distinguishable from unmarked state. SAME: Any performance that creates a boundary between "this" and "that." DIFFERENT: The unmarked state; a different act (e.g., combination). Output: Identity kernel = the act creates a boundary. Boundary is the invariant. | C10: IDENTITY: Equality criteria (a=b iff same successor structure). DISTINGUISHING: Non-equality (a≠b iff different successor structure). SAME: Same position in the successor sequence. DIFFERENT: Different position in the successor sequence. | D10: IDENTITY: God is the necessary being, ground of all, one in essence, three in person. DISTINGUISHING: God distinguished from creation (Creator/creature); from impersonal ground (personal); from non-Trinitarian monotheism (Trinity). SAME: The same ground across all domains. DIFFERENT: A created being; an impersonal force; a non-Trinitarian deity. | E10: IDENTITY: Public testing, error exposure, revisability, empirical grounding. DISTINGUISHING: From pseudoscience (no testing), pure rationalism (no observation), revelation-only (no empirical check), radical skepticism (no knowledge). SAME: The same error-correcting structure across disciplines. DIFFERENT: Astrology, philosophy, theology (each missing a component).
A11: Q3 — What is required for the expression to have meaning? | B11: REQUIRES FOR FORMULATION: A speaker capable of performing the act (even silently, in thought). REQUIRES FOR COHERENCE: The possibility of two states (marked/unmarked). REQUIRES FOR EXISTENCE: The act does not claim existence of an object; it claims performability. The performance demonstrates the possibility. Output: Dependency floor = the possibility of two states; a performer capable of marking. | C11: REQUIRES FOR FORMULATION: Repeatable identity and distinction; a successor operation; a starting point (0 or 1). REQUIRES FOR COHERENCE: The successor must produce a new number, not loop back (unless modular). REQUIRES FOR EXISTENCE: Depends on ontological commitment (Platonist/formalist/structuralist). Critical dependency: Number requires repeatable distinction — the mark applied iteratively. | D11: REQUIRES FOR FORMULATION: Coherent use of being, unity, distinction, relation, knowledge, goodness, agency. REQUIRES FOR COHERENCE: The concept must not be self-contradictory (though it may exceed full comprehension). REQUIRES FOR EXISTENCE: The concept is not empty; the ground is not merely possible but necessary. | E11: REQUIRES FOR FORMULATION: Observation, distinction, logic, regularity, comparison. REQUIRES FOR COHERENCE: The world must be patterned; the mind must recognize pattern; communication must be possible. REQUIRES FOR EXISTENCE: The method exists as a practice. Its justification requires the primitives (mark, pattern, consciousness).
A12: Q4 — What can vary while it remains the same referent? | B12: MAY VARY: Medium (ink, sound, thought, physical boundary); content marked; scale. MUST REMAIN: The creation of a boundary; two sides. PRESERVES IDENTITY: Same act in a different medium. DESTROYS IDENTITY: The act fails to create a boundary. Output: State space = all possible boundaries; Invariant = two-sidedness. | C12: MAY VARY: Notation (1, I, uno, 一); base (binary, decimal); application. MUST REMAIN: Successor structure; order; cardinality. PRESERVES IDENTITY: Different notation for the same number. DESTROYS IDENTITY: Changing the successor (2's successor is 4 not 3). | D12: MAY VARY: Names (God, Allah, Yahweh, Trinity); cultural expressions; theological formulations. MUST REMAIN: Necessity; ultimacy; personhood (Trinitarian); love (Theophysics). PRESERVES IDENTITY: Different theological language for the same God. DESTROYS IDENTITY: Denial of necessity, personhood, or Trinity. | E12: MAY VARY: Instruments, procedures, statistical methods, specific hypotheses. MUST REMAIN: Observation, hypothesis, prediction, testing, comparison, revision, replication. PRESERVES IDENTITY: Different instruments testing the same hypothesis. DESTROYS IDENTITY: Removing testing (speculation), observation (rationalism), or revision (dogma).
A13: Q5 — What can it do, undergo, or participate in? | B13: ACCEPTS: A medium, location, context. PRODUCES: Two sides; a boundary; the possibility of counting. ACTS UPON: The unmarked state (→ marked). ACTED UPON BY: The performer; time (boundaries fade). COMBINES WITH: Other marks (nesting, parallel, intersection). FORBIDS: Being both marked and unmarked in the same respect. Output: Operation signature = μ: unmarked → {marked, unmarked}. | C13: ACCEPTS: Operations (successor, addition, multiplication). PRODUCES: New numbers; quantitative results. ACTS UPON: Collections (counting); magnitudes (measuring); positions (ordering). COMBINES WITH: Other numbers. PRESERVES: Structure under isomorphism. FORBIDS: Division by zero; contradiction. | D13: ACCEPTS: Nothing from outside (aseity). Receives love internally (Trinity). PRODUCES: Creation; revelation; sustenance; redemption; love. ACTS UPON: Creation (sustaining); history (providence); hearts (sanctification). ACTED UPON BY: Nothing external; internally the Persons love one another. PRESERVES: Being; truth; goodness; love. FORBIDS: Contradiction in essence; evil as divine attribute; non-existence. | E13: ACCEPTS: Observations, hypotheses, theories, data. PRODUCES: Confirmed/refuted hypotheses, refined theories, predictions, models. ACTS UPON: Nature (observation/experiment); theories (testing). ACTED UPON BY: Nature (unexpected results); logic; peer review. COMBINES WITH: Mathematics; technology; philosophy. FORBIDS: Data falsification; dogmatic adherence to falsified theories; untestable ad hoc hypotheses.
A14: Q6 — What connects one valid state to another? | B14: PRIOR: Unmarked (no boundary). TRANSITION: The act of marking. NEXT: Marked (boundary exists). NECESSARY INPUT: A performer, a medium, the possibility of two states. SUFFICIENT INPUT: The act itself. REVERSIBLE?: Physical mark may be erased, but the logical possibility remains; the act is irreversible in that it demonstrates possibility. Output: μ is a transition operator; Mechanism = performative demonstration. | C14: PRIOR: n TRANSITION: Successor S(n)=n+1 NEXT: n+1 NECESSARY INPUT: n; the successor operation. SUFFICIENT INPUT: n and S. REVERSIBLE?: Reversible (predecessor exists for n>0). | D14: PRIOR: God as pure act (actus purus); eternal self-knowledge and self-love. TRANSITION: Creation (asymmetric: God→world); Incarnation; Redemption. NEXT: Created order; Incarnate Christ; redeemed community. NECESSARY INPUT: God's free will (creation not necessary); God's love. REVERSIBLE?: Creation and redemption are irreversible. Critical boundary: Creation is not divine self-production; God does not create out of need. The transition is asymmetric. | E14: PRIOR: Observation or anomaly. TRANSITION: Hypothesis formation. NEXT: Predicted consequence. NECESSARY INPUT: Pattern recognition; logical inference; empirical access. SUFFICIENT INPUT: Hypothesis + prediction + test. REVERSIBLE?: Irreversible — once falsified, a theory cannot be un-falsified (may be revised/restricted).
A15: Q7 — What limits the possibilities? | B15: ADMISSIBLE: Unmarked; marked with boundary; multiply marked. FORBIDDEN: Marked and unmarked in same respect (contradiction); a one-sided boundary. INITIAL: The unmarked state must be possible. TERMINAL: None — marking iterates indefinitely. DOMAIN: Any context where distinction is possible. Output: Constraint = two-sidedness mandatory; contradiction excluded. | C15: ADMISSIBLE: Natural numbers; integers; rationals; reals; complex (per axioms). FORBIDDEN: Division by zero; contradiction; largest natural number. INITIAL: 0 (or 1). TERMINAL: None (infinite). DOMAIN: Depends on number system (ℕ, ℤ, ℚ, ℝ, ℂ). EXTERNAL: Physical reality may not instantiate all numbers (e.g., transfinite). | D15: ADMISSIBLE: God as necessary, personal, loving, triune. FORBIDDEN: God as contingent, impersonal (Theophysics frame), non-loving, self-contradictory. INITIAL/TERMINAL: None — God is eternal, uncaused. DOMAIN: All domains (God is the ground of all). IDENTITY LIMITS: God cannot deny Himself, be evil, or not exist. EXTERNAL: None. Internal: cannot do the logically impossible (not a thing to do). | E15: ADMISSIBLE: Hypothesis testing; model refinement; theory development. FORBIDDEN: Dogma without test; data fabrication; unfalsifiable claims (Popperian). INITIAL: An observable, patterned world. TERMINAL: None — science is open-ended. DOMAIN: The physical world (methodologically); does not access the unconditioned ground directly. EXTERNAL: Measurement precision; technology; ethical constraints.
A16: Q8 — What necessarily follows if the expression is granted? | B16: IMMEDIATE: Two sides exist; the bit is born (0/1); the possibility of counting (2>1). CONDITIONAL: Iteration → number; stability → logic; multiplicity → relation; consistency → pattern. ADDED REQUIREMENTS: None beyond the act. NON-CONSEQUENCE: The content of what is marked (act determines only that there are sides). | C16: IMMEDIATE: Arithmetic; order; comparison. CONDITIONAL: If extended — algebra, analysis, geometry, topology, all of mathematics. ADDED: Axioms (Peano, ZF) for full development. NON-CONSEQUENCE: Physical existence (numbers need no physical instantiation). | D16: IMMEDIATE: Creation possible and actual; consciousness, love, morality have a ground; the universe is intelligible. CONDITIONAL: If triune → love internal to God; if personal → relation internal; if creates freely → creation contingent. ADDED: Revelation (Trinity); faith (relationship). NON-CONSEQUENCE: 'Everything is God's will' (confuses permission/causation); 'God causes evil' (category error). | E16: IMMEDIATE: Knowledge of the physical world; technology; error correction. CONDITIONAL: If successful → unified theories; if limited → compartmentalized knowledge. ADDED: Peer review; replication; statistics. NON-CONSEQUENCE: Scientism (science is the only knowledge / answers all questions / disproves God — category error).
A17: Q9 — In what forms can the structure be represented? | B17: PLAIN: 'A line can be drawn.' LOGICAL: P → (A ∨ ¬A). SET: μ: ∅ → {0,1}. ALGEBRAIC: Boolean algebra on {0,1}, μ as generator. DYNAMICAL: Phase transition symmetric → broken symmetry. FORMALISM: Spencer-Brown, Laws of Form (1969). MACHINE: The bit; any Turing machine presupposes μ. LOSS: The experiential 'making' of the distinction (performative aspect). | C17: PLAIN: 'How many or how much.' LOGICAL: ∃x(Number(x) ∧ (Countable ∨ Orderable ∨ Measurable)). SET: Von Neumann ordinals 0=∅, 1={∅}, 2={∅,{∅}}... ALGEBRAIC: Peano axioms; group/ring/field. FORMALISM: Category theory (NNO); type theory. MACHINE: Coq, Lean formalize arithmetic. LOSS: The intuitive grasp of 'how many'. | D17: PLAIN: 'God is creator and sustainer, who loves us.' LOGICAL: □∃G; ∀x(x exists → G sustains x); L(G,G). SET/ALGEBRAIC/DYNAMICAL: Not applicable — God is not a set/structure/system. FORMALISM: Not applicable — full divine reality not exhausted mathematically. LOSS: Personal relationship; prayer; phenomenology of divine love. Critical finding: Logic is partial. This is a boundary of mathematical representation, not a failure of the concept. | E17: PLAIN: 'Watching, guessing, checking.' LOGICAL: If H predicts O and O observed → H supported (not proven). SET: Hypotheses as prediction-sets; testing as intersection. ALGEBRAIC: Bayesian P(H|O)=P(O|H)P(H)/P(O). DYNAMICAL: Confidence levels change with evidence. FORMALISM: Popper, Kuhn, Lakatos, Feyerabend. LOSS: Creativity of hypothesis formation; judgment; social dimension.
A18: Q10 — What does each representation preserve and lose? | B18: PLAIN: +accessibility / −precision. LOGICAL: +inferential structure / −the act itself. SET: +extensionality / −intensionality. ALGEBRAIC: +tractability / −ontological commitment. DYNAMICAL: +physical analogy / −logical necessity. MACHINE: +executability / −meaning entirely. Output: No exact formalization; all partial. The mark is the fixed point all representations circle. | C18: PLAIN: +intuition / −precision. GRAMMAR: +clarity / −rigor. LOGICAL: +inference / −computational content. SET: +foundation / −intuitive access. ALGEBRAIC: +operations / −ontological commitment. FORMALISM: +generality / −concreteness. MACHINE: +certainty / −meaning. | D18: PLAIN: +relational accessibility / −precision. GRAMMAR: +doctrinal content / −experiential depth. LOGICAL: +inferential structure / −personhood. SET/ALGEBRAIC/DYNAMICAL/FORMALISM/MACHINE: Not applicable. | E18: PLAIN: +accessibility / −rigor. GRAMMAR: +clarity / −formal precision. LOGICAL: +inference / −empirical content. SET: +structure / −dynamics. ALGEBRAIC: +quantification / −qualitative judgment. DYNAMICAL: +change / −static truth. MACHINE: +reproducibility / −discovery.
A19: Q11 — What would reality look like if it were true? | B19: LOGICAL: Two-valued logic; non-contradiction; excluded middle. MATH: Number, arithmetic, set theory, all mathematics. PHYSICAL: Symmetry breaking; phase transitions. BIOLOGICAL: Cellular differentiation; organism/environment boundary. CONSCIOUS: Perception (figure/ground); self-awareness (self/other). MORAL: Distinguishing good/evil; choice. THEOLOGICAL: God's self-differentiation (Father/Son); creation as distinction; the Logos. OBSERVABLE: Every perception, utterance, thought demonstrates the mark; any denial performs it. | C19: LOGICAL: Arithmetic consistent (if axioms are); induction works. MATH: All of mathematics. PHYSICAL: Quantities measurable; laws mathematical. BIOLOGICAL: Numerosity discrimination. CONSCIOUS: Humans count and calculate. MORAL: Justice requires proportion; fairness requires counting. THEOLOGICAL: God counts the stars (Ps 147:4); creates by number (Wis 11:20). OBSERVABLE: Counting ubiquitous; math effective in science. | D19: LOGICAL: Existence, reason, morality grounded. MATH: Mathematics discovered, not invented (God thinks structures eternally). PHYSICAL: Universe lawful, fine-tuned, intelligible. BIOLOGICAL: Life purposeful, not merely mechanistic. CONSCIOUS: Consciousness has a source; love real; meaning attainable. MORAL: Good and evil real; moral law binding; love highest. THEOLOGICAL: All Christian theology follows. OBSERVABLE: Fine-tuning; moral law on the heart; historical revelation; transformed lives. | E19: LOGICAL: Empirical conclusions follow defeasibly, not deductively. MATH: Statistics, probability, modeling. PHYSICAL: Laws discoverable; technology possible. BIOLOGICAL: Reducible to physics/chemistry or emergent. CONSCIOUS: World intelligible; minds can understand it. MORAL: Science informs but cannot determine ethics (Hume's guillotine). THEOLOGICAL: Science studies God's faithful speech (book of nature). OBSERVABLE: Technology, medicine, engineering, predictions.
... A30: Gate outcome | B30: WHY_CLOSED Closure level: STRUCTURAL (strongest applicable) Explanation type: LOGICAL NECESSITY + SHARED CONSTRAINT + COMMON GROUND | C30: WHY_CLOSED Closure level: STRUCTURAL Explanation type: LOGICAL NECESSITY + MATHEMATICAL NECESSITY + COMMON GROUND | D30: WHY_CLOSED at the structural level (personal ground capable of love). WHY_OPEN at the full Trinitarian level (specific number of persons and their identities require revelation). Closure: STRUCTURAL for personhood; EXPLANATORY for Trinity. Type: SHARED CONSTRAINT + COMMON SOURCE + PURPOSIVE + HISTORICAL DEVELOPMENT. Honest boundary: The step from 'personal ground' to 'Trinity' is the strongest inference in the chain — structurally compelling but not deductively closed. An adversary can accept the ground and deny the Trinity. This is the boundary between natural and revealed theology. | E30: WHY_CLOSED Closure level: STRUCTURAL Explanation type: LOGICAL NECESSITY + SHARED CONSTRAINT + COMMON GROUND + PURPOSIVE EXPLANATION
A32: KEY FINDINGS
A33: Mark → Number | B33: WHY_CLOSED at the structural level.
A34: Mark → Scientific Method | B34: WHY_CLOSED at the structural level.
A35: Mark → God | B35: Converges to a personal ground capable of love (WHY_CLOSED, structural). The specific Trinitarian structure requires a bridge that is WHY_OPEN at the full-closure level — the strongest inference in the chain and the most vulnerable to objection. Flagged, not hidden.
A36: PRESERVED CANON
A37: Prior rulings | B37: All rulings from Theophysics v5, Axiom Chain Defense Grid v1.1, and ZFC GOD MATH.md are preserved and integrated (see source Appendix D).
A38: Honest boundary | B38: The step from 'personal ground' to 'Trinity' is structurally compelling but not deductively closed: an adversary can accept the ground and deny the Trinity. This is the boundary between natural theology and revealed theology, not a failure of logic.

Sheet NAMING_TAXONOMY
A1: NAMING TAXONOMY
A3: DOMAIN CODES (2–3 letters)
A4: Code | B4: Meaning
A5: PHY | B5: Physics
A6: THE | B6: Theology
A7: TPH | B7: Theophysics (cross-domain)
A8: MEQ | B8: Master Equation
A9: LAW | B9: Ten Laws (individual law work)
A10: CON | B10: Consciousness
A11: GRC | B11: Grace
A12: INF | B12: Information Theory
A13: FRM | B13: Formal / Lean / Proofs
A14: AXM | B14: Axioms
A15: ETH | B15: Ethics / Moral
... A19: PUB | B19: Publication / Website
A21: TYPE TAGS (what the file IS)
A22: Tag | B22: Meaning
A23: ART | B23: Article (public-facing prose)
A24: PAP | B24: Paper (formal / academic)
A25: DRV | B25: Derivation (step-by-step chain)
A26: PRF | B26: Proof (Lean or formal)
A27: BRF | B27: Brief (precision correction)
A28: SPE | B28: Spec (build specification)
A29: AUD | B29: Audit (review / grading)
A30: SRC | B30: Source of Truth (canonical)
A31: DFT | B31: Draft (not final)
A32: NOD | B32: Node file (extracted claims)
A33: MAP | B33: Map / Index / Router
... A38: LOG | B38: Session log / transcript
A40: NAMING PATTERN
A41: {DOMAIN}_{TYPE}_{title-slug}_{date}.{ext}
A43: EXAMPLES
A44: MEQ_SRC_master-equation-derivation-chain_20260814.html
A45: GRC_DRV_grace-canonical-v1-1_20260720.md
A46: LAW_PAP_fruits-of-spirit-yukawa_20260801.md
A47: TPH_ART_dear-stephen-ch01_20260814.md
A48: FRM_PRF_quantitative-structure-lean_20260214.lean
A49: CON_PAP_consciousness-paper-v2_20260809.md
A50: TPH_BRF_brief-09-free-energy_20260715.md
A51: TPH_MAP_consolidated-backbone_20260814.md
A52: TPH_STY_what-the-machine-sees_20260814.md
... A60: RULES
A61: 1 | B61: Domain first — you can sort any folder by domain instantly
A62: 2 | B62: Type second — you know what it IS before you open it
A63: 3 | B63: Slug third — human-readable title
A64: 4 | B64: Date last — you know when, and same-name files sort chronologically
A65: 5 | B65: All lowercase except domain and type codes
A66: 6 | B66: Hyphens in slug, underscores between fields
A67: 7 | B67: No spaces ever
A69: Maps directly onto the .fisnote classification — the domain and type codes ARE the tags. The FIS can read the filename and know what it's dealing with before opening the file.

Sheet SUBJECTIVE_INDEX
A1: sheet | B1: priority | C1: reason
A2: WISDOM_TERMS | B2: high | C2: Judgment-heavy or interpretation-heavy scoring surface
A3: KNOWLEDGE_TERMS | B3: high | C3: Judgment-heavy or interpretation-heavy scoring surface
A4: COHERENCE_TERMS | B4: high | C4: Judgment-heavy or interpretation-heavy scoring surface
A5: FRUITS | B5: high | C5: Judgment-heavy or interpretation-heavy scoring surface
A6: CLAIM_TERMS | B6: high | C6: Judgment-heavy or interpretation-heavy scoring surface
A7: EVIDENCE_TERMS | B7: high | C7: Judgment-heavy or interpretation-heavy scoring surface
A8: FALSIFY_TERMS | B8: high | C8: Judgment-heavy or interpretation-heavy scoring surface
A9: DEPENDENCY_TERMS | B9: high | C9: Judgment-heavy or interpretation-heavy scoring surface
A10: HEDGE_TERMS | B10: high | C10: Judgment-heavy or interpretation-heavy scoring surface
A11: ABSOLUTE_TERMS | B11: high | C11: Judgment-heavy or interpretation-heavy scoring surface
A12: BRIDGE_TERMS | B12: high | C12: Judgment-heavy or interpretation-heavy scoring surface
... A20: DOC_TYPE_PATTERNS | B20: high | C20: Judgment-heavy or interpretation-heavy scoring surface

Sheet Fruit Semantic Architecture
A1: FRUIT OF THE SPIRIT — SEMANTIC ARCHITECTURE
A2: Galatians 5:22-23 | Deep Classification & Naming Convention Reference
A4: SECTION 1: CORE CLASSIFICATION
A5: # | B5: Canonical (English) | C5: Greek Term | D5: Cluster ID | E5: Adjacent Cluster Terms | F5: Primary Anti-Fruit Opposed | G5: Valence Profile (Moral / Social / Self-Reg / Relational)
A6: 1 | B6: Love | C6: Agape | D6: affection_benevolence | E6: compassion, mercy, grace, forgiveness, hospitality, solidarity, communion, covenant-faithfulness | F6: hatred, selfish ambition, envy | G6: 1.0 / 1.0 / 0.3 / 1.0
A7: 2 | B7: Joy | C7: Chara | D7: delight_exultation | E7: rejoicing, contentment, satisfaction, wonder, awe, gratitude, hope, triumph, festivity | F7: jealousy, envy, idolatry | G7: 0.7 / 0.5 / 0.3 / 0.7
A8: 3 | B8: Peace | C8: Eirene | D8: tranquility_harmony | E8: reconciliation, wholeness, integration, rest, silence, centeredness, balance, shalom, pax, truce | F8: discord, dissensions, factions, hatred | G8: 0.5 / 1.0 / 0.7 / 1.0
A9: 4 | B9: Patience | C9: Makrothymia | D9: endurance_composure | E9: perseverance, endurance, forbearance, constancy, steadfastness, slowness-to-anger, tolerance, delay-tolerance | F9: fits of rage, discord, jealousy | G9: 0.5 / 0.5 / 1.0 / 0.7
A10: 5 | B10: Kindness | C10: Chrestotes | D10: compassion_generosity | E10: compassion, mercy, grace, benevolence, generosity, helpfulness, courtesy, considerateness, thoughtfulness, tenderness, clemency, leniency | F10: selfish ambition, sorcery, hatred | G10: 0.7 / 1.0 / 0.3 / 1.0
A11: 6 | B11: Goodness | C11: Agathosyne | D11: virtue_integrity | E11: integrity, righteousness, uprightness, probity, rectitude, honor, decency, purity, excellence, beneficence, moral-courage, truthfulness, justice | F11: impurity, sorcery, selfish ambition | G11: 1.0 / 0.7 / 0.5 / 0.5
A12: 7 | B12: Faithfulness | C12: Pistis | D12: loyalty_reliability | E12: loyalty, fidelity, steadfastness, constancy, allegiance, devotion, reliability, trustworthiness, dependability, fealty, commitment, covenant-keeping | F12: idolatry, dissensions, factions | G12: 0.7 / 0.5 / 0.7 / 1.0
A13: 8 | B13: Gentleness | C13: Prautes | D13: mildness_meekness | E13: meekness, mildness, softness, tenderness, humility, approachability, clemency, leniency, forbearance, non-coercion, persuasion, diplomacy, tact | F13: fits of rage, debauchery, hatred | G13: 0.5 / 0.7 / 0.7 / 1.0
A14: 9 | B14: Self-Control | C14: Egkrateia | D14: restraint_mastery | E14: temperance, moderation, discipline, restraint, willpower, mastery, sobriety, continence, impulse-control, delayed-gratification, boundary-keeping | F14: debauchery, drunkenness, orgies, sexual immorality | G14: 0.7 / 0.3 / 1.0 / 0.5
A16: SECTION 2: DEEP SEMANTIC FACETS (4 Measurement Dimensions per Fruit)
A17: Fruit | B17: Facet | D17: Semantic Field Terms
A18: Love (Agape) | B18: Affective | D18: cherishing, tenderness, devotion, ardor, fondness, heart-connection, emotional investment
B19: Behavioral | D19: self-sacrifice, nurture, protection, advocacy, presence, service, loyalty-in-action
B20: Motivational | D20: other-regard, seeking-flourishing, non-transactional care, commitment-despite-cost
B21: Cognitive | D21: inherent-worth perception, image-of-God recognition, non-commodification
A22: Joy (Chara) | B22: Affective | D22: exultation, euphoria, mirth, jubilation, elation, bliss, radiance, lightness
B23: Behavioral | D23: celebration, praise, gratitude-expression, laughter, dance, song, generosity-sparked
B24: Motivational | D24: hope-anchored, future-oriented delight, defiance-of-circumstance
B25: Cognitive | D25: eschatological-awareness, gift-recognition, abundance-framing
A26: Peace (Eirene) | B26: Affective | D26: serenity, calm, stillness, quietude, rest, ease, unperturbedness
B27: Behavioral | D27: reconciliation, mediation, non-retaliation, bridge-building, silence-as-presence
B28: Motivational | D28: wholeness-seeking, conflict-transformation (not avoidance), integration-desire
B29: Cognitive | D29: systemic-harmony perception, shalom-framing (not just absence-of-war)
A30: Patience (Makrothymia) | B30: Affective | D30: composure, equanimity, unflappability, calm-under-pressure, grace-under-fire
B31: Behavioral | D31: waiting-without-demand, persevering-presence, delayed-gratification, bearing-with
B32: Motivational | D32: trust-in-timing, process-respect, redemptive-hope (things take time)
B33: Cognitive | D33: temporal-perspective, eschatological-patience, "not-yet" framing
A34: Kindness (Chrestotes) | B34: Affective | D34: warmth, tenderness, soft-heartedness, movedness, pity (non-condescending)
B35: Behavioral | D35: helpfulness, courtesy, generosity, practical-care, going-out-of-way, micro-kindnesses
B36: Motivational | D36: gratuitous-goodness, no-strings-attached, image-bearing recognition
B37: Cognitive | D37: situational-awareness, need-perception, "what would help here?"
A38: Goodness (Agathosyne) | B38: Affective | D38: uprightness-satisfaction, moral-clarity, clean-conscience, rectitude
B39: Behavioral | D39: integrity-in-action, honesty, justice-doing, moral-courage, truth-telling
B40: Motivational | D40: excellence-seeking, holiness-aim, rightness-for-its-own-sake
B41: Cognitive | D41: moral-discernment, truth-orientation, "this is right" conviction
A42: Faithfulness (Pistis) | B42: Affective | D42: loyalty-affection, steadfast-love, secure-attachment, trust-feeling
B43: Behavioral | D43: consistency, reliability, promise-keeping, showing-up, follow-through
B44: Motivational | D44: covenant-loyalty, commitment-despite-cost, through-thick-and-thin
B45: Cognitive | D45: trust-in-character, dependability-assessment, "I can count on this"
A46: Gentleness (Prautes) | B46: Affective | D46: softness, mildness, tenderness, non-threateningness, approachability
B47: Behavioral | D47: careful-handling, measured-response, non-coercion, persuasion-over-force
B48: Motivational | D48: power-under-control, strength-restrained, non-dominance-despite-ability
B49: Cognitive | D49: situational-proportion, "how much force is needed?" discernment
A50: Self-Control (Egkrateia) | B50: Affective | D50: calm-desire, ordered-passion, non-compulsion, freedom-from-urge
B51: Behavioral | D51: impulse-delay, saying-no, boundary-setting, habit-discipline, moderation
B52: Motivational | D52: long-term-flourishing-over-immediate-gratification, value-hierarchy
B53: Cognitive | D53: metacognitive-awareness, "I see the urge and choose," executive-function
A55: SECTION 3: VICE MAPPING (Aristotelian Excess / Deficiency)
A56: Fruit | D56: Vice-of-Excess | F56: Vice-of-Deficiency
A57: Love | D57: enabling, co-dependency, possessiveness, smothering, people-pleasing | F57: indifference, apathy, neglect, withdrawal, coldness, objectification
A58: Joy | D58: mania, toxic-positivity, escapism, denial, hedonism | F58: despair, melancholy, cynicism, resignation, joylessness, heaviness
A59: Peace | D59: conflict-avoidance, false-peace, appeasement, suppression, denial | F59: chaos, fragmentation, anxiety, restlessness, agitation, discord
A60: Patience | D60: passivity, fatalism, resignation, enabling-delay, procrastination | F60: impetuosity, irritability, restlessness, short-temperedness, demand-instantity
A61: Kindness | D61: over-accommodation, self-erasure, doormat-syndrome, compulsive-helping | F61: harshness, coldness, disregard, meanness, stinginess, contempt
A62: Goodness | D62: moralism, self-righteousness, priggishness, judgmentalism, legalism | F62: corruption, depravity, dishonesty, immorality, rot, decay, wickedness
A63: Faithfulness | D63: blind-loyalty, stubbornness, refusal-to-reassess, toxic-fidelity | F63: fickleness, unreliability, betrayal, treachery, perfidy, disloyalty, infidelity
A64: Gentleness | D64: weakness, passivity, spinelessness, avoidance-of-confrontation | F64: harshness, severity, abrasiveness, roughness, brutality, domination
A65: Self-Control | D65: asceticism, self-denial-to-harm, repression, emotional-deadness, rigidity | F65: compulsion, addiction, enslavement, impulsivity, excess, gluttony, lust, rage
A67: SECTION 4: ANTI-FRUIT — WORKS OF THE FLESH (Galatians 5:19-21)
A68: Flesh-Work | B68: Greek Term | D68: Semantic Field | F68: Primary Fruit(s) Opposed
A69: Sexual Immorality | B69: porneia | D69: lust, promiscuity, objectification, exploitation | F69: Love, Self-Control
A70: Impurity | B70: akatharsia | D70: defilement, contamination, moral-taint, profanation | F70: Goodness, Peace
A71: Debauchery | B71: aselgeia | D71: excess, abandon, unrestraint, sensuality-run-wild | F71: Self-Control, Gentleness
A72: Idolatry | B72: eidololatria | D72: false-worship, ultimate-concern-misplacement, addiction-to-created | F72: Faithfulness, Joy
A73: Sorcery | B73: pharmakeia | D73: manipulation, control-through-hidden-means, deception | F73: Goodness, Kindness
A74: Hatred | B74: echthra | D74: enmity, hostility, malice, animosity, loathing | F74: Love, Peace
A75: Discord | B75: eris | D75: strife, contention, argumentativeness, factionalism | F75: Peace, Patience
A76: Jealousy | B76: zelos | D76: envy, covetousness, rivalrousness, status-anxiety | F76: Love, Joy
A77: Fits of Rage | B77: thymos | D77: outbursts, wrath, fury, indignation, temper | F77: Patience, Gentleness
A78: Selfish Ambition | B78: eritheia | D78: self-promotion, rivalry, status-climbing, narcissism | F78: Kindness, Goodness
A79: Dissensions | B79: dichostasia | D79: divisions, splits, sectarianism, us-vs-them | F79: Peace, Faithfulness
... A83: Orgies | B83: komoi | D83: revelry, excess-celebration, boundaryless-festivity | F83: Self-Control, Goodness
A85: SECTION 5: SURFACE VARIANTS BY IDEOLOGICAL FRAME
A86: Fruit | D86: Progressive / "Woke" Surface Variants | E86: Progressive Vice-of-Excess | F86: Conservative / Traditionalist Variants | G86: Traditionalist Vice-of-Excess
A87: Love | D87: allyship, solidarity, inclusion, equity-love, radical-love, unconditional-acceptance | E87: performative-love, love-without-truth, inclusivity-as-avoidance-of-judgment | F87: tough-love, truth-in-love, ordered-love, familial-love | G87: conditional-love, love-without-kindness, exclusionary-love
A88: Joy | D88: liberatory-joy, Black-joy, queer-joy, resistance-joy, celebration-of-difference | E88: forced-joy, joy-as-political-weapon, toxic-positivity-in-activism | F88: traditional-values-joy, faith-based-happiness, prosperity, American-dream-joy | G88: complacent-joy, joy-as-denial, prosperity-gospel
A89: Peace | D89: safe-spaces, harm-reduction, non-violent-resistance, restorative-justice, de-escalation | E89: peace-as-silencing, conflict-avoidance, false-consensus, appeasement | F89: law-and-order, stability, strong-borders, peace-through-strength | G89: authoritarian-peace, peace-as-control, Pax Romana critique
A90: Patience | D90: "educate-yourself," gradual-reform, long-march, institutional-change-slow | E90: patience-as-passivity, patience-as-enabling-injustice, infinite-patience | F90: waiting-on-God, slow-to-change, institutional-respect, gradualism | G90: patience-as-inertia, patience-as-oppression-maintenance
A91: Kindness | D91: compassion, empathy, care, holding-space, validation, trauma-informed | E91: kindness-as-enabling, empathy-without-boundaries, compassion-fatigue, niceness-over-truth | F91: charity, personal-responsibility-help, bootstrap-compassion | G91: kindness-without-justice, paternalism, condescension
A92: Goodness | D92: justice, equity, anti-racism, decolonization, systemic-analysis, accountability | E92: moralism, self-righteousness, purity-testing, cancel-culture, performative-justice | F92: moral-absolutes, biblical-values, truth, objective-morality | G92: legalism, self-righteousness, moral-superiority, judgmentalism
A93: Faithfulness | D93: ally-commitment, staying-in-your-lane, loyalty-to-community, ride-or-die | E93: blind-loyalty, tribal-fidelity, no-deviation-allowed, epistemic-closure | F93: tradition, covenant, loyalty-to-institution, doctrinal-purity | G93: traditionalism-as-idolatry, blind-obedience, epistemic-closure
A94: Gentleness | D94: tone-policing-awareness, call-in-not-call-out, gentle-correction, non-violent-communication | E94: gentleness-as-avoidance-of-confrontation, never-holding-accountable, weakness | F94: masculinity-reframed (gentle-strength), fatherly-correction | G94: harshness-framed-as-love, severity, dominance
A95: Self-Control | D95: emotional-labor, boundary-setting, self-care-as-resistance, rest-as-revolution | E95: self-care-as-avoidance, narcissism-under-boundary-language, repression-framed-as-control | F95: discipline, personal-responsibility, stoicism, bootstraps | G95: repression, emotional-deadness, blame-the-victim
A97: SECTION 6: DIAGNOSTIC ASYMMETRY PATTERNS
A98: Pattern Name | D98: High-Index Fruits | E98: Low-Index Fruits | F98: Anti-Fruit Signal Present | G98: Diagnosis
A99: Pattern A: Justice without Gentleness | D99: Goodness (truth/justice), Kindness (compassion) | E99: Gentleness (measured response), Patience (composure) | F99: fits of rage, discord, selfish ambition | G99: Right concern, wrong method. Moralism vice-of-excess.
A100: Pattern B: Peace without Goodness | D100: Peace (safe spaces, non-violence), Patience (gradual reform) | E100: Goodness (truth-telling, moral courage), Faithfulness (steadfast principle) | F100: corruption, idolatry (of process), false peace | G100: Conflict avoidance masquerading as virtue.
A101: Pattern C: Love without Self-Control | D101: Love (allyship, solidarity), Kindness (empathy, validation) | E101: Self-Control (boundaries, discipline), Goodness (accountability) | F101: debauchery, impurity, excess | G101: Affect without structure. Enabling vice-of-excess.
A102: Pattern D: Gentleness without Goodness | D102: Gentleness (non-coercion), Peace (harm reduction) | E102: Goodness (moral courage), Faithfulness (truth-speaking) | F102: false peace, idolatry of niceness | G102: Niceness as moral evasion.
A104: SECTION 7: FSI SCORING METHODOLOGY | BD104: but we probably need to make one for sin
A105: Dimension | D105: How to Measure in Text | F105: Formula Component
A106: Lexical Density | D106: Frequency of canonical + deep-semantic terms per 1000 words | F106: Raw signal input
A107: Affective Range | D107: Spread across emotional vs. behavioral vs. motivational vs. cognitive facets | F107: Integration Index component
A108: Vice-Awareness | D108: Does the paper acknowledge and resist the corresponding flesh-works? | F108: Anti-Fruit Presence (negative)
A109: Integration Score | D109: Are the fruits presented as singular "fruit" (integrated) or fragmented? | F109: Integration Index = evenness across all 9
A110: Anti-Fruit Resistance | D110: Explicit rejection or transformation of flesh-works in the argument | F110: Weighted count modifier
...

Sheet README
A1: sheet | B1: source_file | C1: notes
A2: README | C2: Edit the term sheets, then use them for synonym expansion or lexicon patching.
A3: WISDOM_TERMS | B3: X:\apps\paper-intelligence-suite-python\03_THEOPHYSICS_METRICS\theophysics_scorer.py | C3: WISDOM_TERMS
A4: KNOWLEDGE_TERMS | B4: X:\apps\paper-intelligence-suite-python\03_THEOPHYSICS_METRICS\theophysics_scorer.py | C4: KNOWLEDGE_TERMS
A5: COHERENCE_TERMS | B5: X:\apps\paper-intelligence-suite-python\03_THEOPHYSICS_METRICS\theophysics_scorer.py | C5: COHERENCE_TERMS
A6: FRUITS | B6: X:\apps\paper-intelligence-suite-python\03_THEOPHYSICS_METRICS\theophysics_scorer.py | C6: FRUITS
A7: ME_VARS | B7: X:\apps\paper-intelligence-suite-python\03_THEOPHYSICS_METRICS\theophysics_scorer.py | C7: ME_VARS
A8: CLAIM_TERMS | B8: X:\apps\paper-intelligence-suite-python\06_TRUTH_ENGINE\truth_coherence_scanner.py | C8: CLAIM_TERMS
A9: EVIDENCE_TERMS | B9: X:\apps\paper-intelligence-suite-python\06_TRUTH_ENGINE\truth_coherence_scanner.py | C9: EVIDENCE_TERMS
A10: FALSIFY_TERMS | B10: X:\apps\paper-intelligence-suite-python\06_TRUTH_ENGINE\truth_coherence_scanner.py | C10: FALSIFY_TERMS
A11: DEPENDENCY_TERMS | B11: X:\apps\paper-intelligence-suite-python\06_TRUTH_ENGINE\truth_coherence_scanner.py | C11: DEPENDENCY_TERMS
A12: HEDGE_TERMS | B12: X:\apps\paper-intelligence-suite-python\06_TRUTH_ENGINE\truth_coherence_scanner.py | C12: HEDGE_TERMS
A13: ABSOLUTE_TERMS | B13: X:\apps\paper-intelligence-suite-python\06_TRUTH_ENGINE\truth_coherence_scanner.py | C13: ABSOLUTE_TERMS
A14: BRIDGE_TERMS | B14: X:\apps\paper-intelligence-suite-python\06_TRUTH_ENGINE\truth_coherence_scanner.py | C14: BRIDGE_TERMS
... A22: DOC_TYPE_PATTERNS | B22: \\dlowenas\brain\David\pipelines\engines\pipeline\stations\classifier.py | C22: DOC_TYPE_PATTERNS

Sheet WISDOM_TERMS
A1: source_file | B1: collection | C1: item_index | D1: term
A2: X:\apps\paper-intelligence-suite-python\03_THEOPHYSICS_METRICS\theophysics_scorer.py | B2: WISDOM_TERMS | C2: 1 | D2: wisdom
A3: X:\apps\paper-intelligence-suite-python\03_THEOPHYSICS_METRICS\theophysics_scorer.py | B3: WISDOM_TERMS | C3: 2 | D3: discernment
A4: X:\apps\paper-intelligence-suite-python\03_THEOPHYSICS_METRICS\theophysics_scorer.py | B4: WISDOM_TERMS | C4: 3 | D4: eternal
A5: X:\apps\paper-intelligence-suite-python\03_THEOPHYSICS_METRICS\theophysics_scorer.py | B5: WISDOM_TERMS | C5: 4 | D5: transcend
A6: X:\apps\paper-intelligence-suite-python\03_THEOPHYSICS_METRICS\theophysics_scorer.py | B6: WISDOM_TERMS | C6: 5 | D6: revelation
A7: X:\apps\paper-intelligence-suite-python\03_THEOPHYSICS_METRICS\theophysics_scorer.py | B7: WISDOM_TERMS | C7: 6 | D7: mystery
A8: X:\apps\paper-intelligence-suite-python\03_THEOPHYSICS_METRICS\theophysics_scorer.py | B8: WISDOM_TERMS | C8: 7 | D8: grace
A9: X:\apps\paper-intelligence-suite-python\03_THEOPHYSICS_METRICS\theophysics_scorer.py | B9: WISDOM_TERMS | C9: 8 | D9: covenant
A10: X:\apps\paper-intelligence-suite-python\03_THEOPHYSICS_METRICS\theophysics_scorer.py | B10: WISDOM_TERMS | C10: 9 | D10: truth
A11: X:\apps\paper-intelligence-suite-python\03_THEOPHYSICS_METRICS\theophysics_scorer.py | B11: WISDOM_TERMS | C11: 10 | D11: logos
A12: X:\apps\paper-intelligence-suite-python\03_THEOPHYSICS_METRICS\theophysics_scorer.py | B12: WISDOM_TERMS | C12: 11 | D12: spirit
A13: X:\apps\paper-intelligence-suite-python\03_THEOPHYSICS_METRICS\theophysics_scorer.py | B13: WISDOM_TERMS | C13: 12 | D13: divine
... A27: X:\apps\paper-intelligence-suite-python\03_THEOPHYSICS_METRICS\theophysics_scorer.py | B27: WISDOM_TERMS | C27: 26 | D27: covenant

Sheet KNOWLEDGE_TERMS
A1: source_file | B1: collection | C1: item_index | D1: term
A2: X:\apps\paper-intelligence-suite-python\03_THEOPHYSICS_METRICS\theophysics_scorer.py | B2: KNOWLEDGE_TERMS | C2: 1 | D2: data
A3: X:\apps\paper-intelligence-suite-python\03_THEOPHYSICS_METRICS\theophysics_scorer.py | B3: KNOWLEDGE_TERMS | C3: 2 | D3: evidence
A4: X:\apps\paper-intelligence-suite-python\03_THEOPHYSICS_METRICS\theophysics_scorer.py | B4: KNOWLEDGE_TERMS | C4: 3 | D4: experiment
A5: X:\apps\paper-intelligence-suite-python\03_THEOPHYSICS_METRICS\theophysics_scorer.py | B5: KNOWLEDGE_TERMS | C5: 4 | D5: measure
A6: X:\apps\paper-intelligence-suite-python\03_THEOPHYSICS_METRICS\theophysics_scorer.py | B6: KNOWLEDGE_TERMS | C6: 5 | D6: calculate
A7: X:\apps\paper-intelligence-suite-python\03_THEOPHYSICS_METRICS\theophysics_scorer.py | B7: KNOWLEDGE_TERMS | C7: 6 | D7: equation
A8: X:\apps\paper-intelligence-suite-python\03_THEOPHYSICS_METRICS\theophysics_scorer.py | B8: KNOWLEDGE_TERMS | C8: 7 | D8: formula
A9: X:\apps\paper-intelligence-suite-python\03_THEOPHYSICS_METRICS\theophysics_scorer.py | B9: KNOWLEDGE_TERMS | C9: 8 | D9: theorem
A10: X:\apps\paper-intelligence-suite-python\03_THEOPHYSICS_METRICS\theophysics_scorer.py | B10: KNOWLEDGE_TERMS | C10: 9 | D10: proof
A11: X:\apps\paper-intelligence-suite-python\03_THEOPHYSICS_METRICS\theophysics_scorer.py | B11: KNOWLEDGE_TERMS | C11: 10 | D11: derive
A12: X:\apps\paper-intelligence-suite-python\03_THEOPHYSICS_METRICS\theophysics_scorer.py | B12: KNOWLEDGE_TERMS | C12: 11 | D12: quantum
A13: X:\apps\paper-intelligence-suite-python\03_THEOPHYSICS_METRICS\theophysics_scorer.py | B13: KNOWLEDGE_TERMS | C13: 12 | D13: physics
... A27: X:\apps\paper-intelligence-suite-python\03_THEOPHYSICS_METRICS\theophysics_scorer.py | B27: KNOWLEDGE_TERMS | C27: 26 | D27: information

Sheet COHERENCE_TERMS
A1: source_file | B1: collection | C1: key | D1: subkey | E1: item_index | F1: value
A2: X:\apps\paper-intelligence-suite-python\03_THEOPHYSICS_METRICS\theophysics_scorer.py | B2: COHERENCE_TERMS | C2: coherence | F2: 3
A3: X:\apps\paper-intelligence-suite-python\03_THEOPHYSICS_METRICS\theophysics_scorer.py | B3: COHERENCE_TERMS | C3: coherent | F3: 3
A4: X:\apps\paper-intelligence-suite-python\03_THEOPHYSICS_METRICS\theophysics_scorer.py | B4: COHERENCE_TERMS | C4: logos | F4: 3
A5: X:\apps\paper-intelligence-suite-python\03_THEOPHYSICS_METRICS\theophysics_scorer.py | B5: COHERENCE_TERMS | C5: quantum | F5: 3
A6: X:\apps\paper-intelligence-suite-python\03_THEOPHYSICS_METRICS\theophysics_scorer.py | B6: COHERENCE_TERMS | C6: decoherence | F6: 3
A7: X:\apps\paper-intelligence-suite-python\03_THEOPHYSICS_METRICS\theophysics_scorer.py | B7: COHERENCE_TERMS | C7: wavefunction | F7: 3
A8: X:\apps\paper-intelligence-suite-python\03_THEOPHYSICS_METRICS\theophysics_scorer.py | B8: COHERENCE_TERMS | C8: entropy | F8: 2
A9: X:\apps\paper-intelligence-suite-python\03_THEOPHYSICS_METRICS\theophysics_scorer.py | B9: COHERENCE_TERMS | C9: conservation | F9: 2
A10: X:\apps\paper-intelligence-suite-python\03_THEOPHYSICS_METRICS\theophysics_scorer.py | B10: COHERENCE_TERMS | C10: order | F10: 2
A11: X:\apps\paper-intelligence-suite-python\03_THEOPHYSICS_METRICS\theophysics_scorer.py | B11: COHERENCE_TERMS | C11: structure | F11: 2
A12: X:\apps\paper-intelligence-suite-python\03_THEOPHYSICS_METRICS\theophysics_scorer.py | B12: COHERENCE_TERMS | C12: framework | F12: 2
A13: X:\apps\paper-intelligence-suite-python\03_THEOPHYSICS_METRICS\theophysics_scorer.py | B13: COHERENCE_TERMS | C13: principle | F13: 2
... A31: X:\apps\paper-intelligence-suite-python\03_THEOPHYSICS_METRICS\theophysics_scorer.py | B31: COHERENCE_TERMS | C31: fundamental | F31: 2

Sheet FRUITS
A1: source_file | B1: collection | C1: key | D1: subkey | E1: item_index | F1: value
A2: X:\apps\paper-intelligence-suite-python\03_THEOPHYSICS_METRICS\theophysics_scorer.py | B2: FRUITS | C2: love | E2: 1 | F2: love
A3: X:\apps\paper-intelligence-suite-python\03_THEOPHYSICS_METRICS\theophysics_scorer.py | B3: FRUITS | C3: love | E3: 2 | F3: care
A4: X:\apps\paper-intelligence-suite-python\03_THEOPHYSICS_METRICS\theophysics_scorer.py | B4: FRUITS | C4: love | E4: 3 | F4: sacrifice
A5: X:\apps\paper-intelligence-suite-python\03_THEOPHYSICS_METRICS\theophysics_scorer.py | B5: FRUITS | C5: love | E5: 4 | F5: agape
A6: X:\apps\paper-intelligence-suite-python\03_THEOPHYSICS_METRICS\theophysics_scorer.py | B6: FRUITS | C6: love | E6: 5 | F6: relational
A7: X:\apps\paper-intelligence-suite-python\03_THEOPHYSICS_METRICS\theophysics_scorer.py | B7: FRUITS | C7: joy | E7: 1 | F7: joy
A8: X:\apps\paper-intelligence-suite-python\03_THEOPHYSICS_METRICS\theophysics_scorer.py | B8: FRUITS | C8: joy | E8: 2 | F8: delight
A9: X:\apps\paper-intelligence-suite-python\03_THEOPHYSICS_METRICS\theophysics_scorer.py | B9: FRUITS | C9: joy | E9: 3 | F9: flourish
A10: X:\apps\paper-intelligence-suite-python\03_THEOPHYSICS_METRICS\theophysics_scorer.py | B10: FRUITS | C10: joy | E10: 4 | F10: rejoice
A11: X:\apps\paper-intelligence-suite-python\03_THEOPHYSICS_METRICS\theophysics_scorer.py | B11: FRUITS | C11: joy | E11: 5 | F11: abundance
A12: X:\apps\paper-intelligence-suite-python\03_THEOPHYSICS_METRICS\theophysics_scorer.py | B12: FRUITS | C12: peace | E12: 1 | F12: peace
A13: X:\apps\paper-intelligence-suite-python\03_THEOPHYSICS_METRICS\theophysics_scorer.py | B13: FRUITS | C13: peace | E13: 2 | F13: harmony
... A58: X:\apps\paper-intelligence-suite-python\03_THEOPHYSICS_METRICS\theophysics_scorer.py | B58: FRUITS | C58: humility | E58: 4 | F58: lowly

Sheet ME_VARS
A1: source_file | B1: collection | C1: key | D1: subkey | E1: item_index | F1: value
A2: X:\apps\paper-intelligence-suite-python\03_THEOPHYSICS_METRICS\theophysics_scorer.py | B2: ME_VARS | C2: G_gravity_belonging | E2: 1 | F2: gravity
A3: X:\apps\paper-intelligence-suite-python\03_THEOPHYSICS_METRICS\theophysics_scorer.py | B3: ME_VARS | C3: G_gravity_belonging | E3: 2 | F3: belonging
A4: X:\apps\paper-intelligence-suite-python\03_THEOPHYSICS_METRICS\theophysics_scorer.py | B4: ME_VARS | C4: G_gravity_belonging | E4: 3 | F4: community
A5: X:\apps\paper-intelligence-suite-python\03_THEOPHYSICS_METRICS\theophysics_scorer.py | B5: ME_VARS | C5: G_gravity_belonging | E5: 4 | F5: gather
A6: X:\apps\paper-intelligence-suite-python\03_THEOPHYSICS_METRICS\theophysics_scorer.py | B6: ME_VARS | C6: G_gravity_belonging | E6: 5 | F6: love
A7: X:\apps\paper-intelligence-suite-python\03_THEOPHYSICS_METRICS\theophysics_scorer.py | B7: ME_VARS | C7: G_gravity_belonging | E7: 6 | F7: binding
A8: X:\apps\paper-intelligence-suite-python\03_THEOPHYSICS_METRICS\theophysics_scorer.py | B8: ME_VARS | C8: G_gravity_belonging | E8: 7 | F8: together
A9: X:\apps\paper-intelligence-suite-python\03_THEOPHYSICS_METRICS\theophysics_scorer.py | B9: ME_VARS | C9: M_mass_meaning | E9: 1 | F9: meaning
A10: X:\apps\paper-intelligence-suite-python\03_THEOPHYSICS_METRICS\theophysics_scorer.py | B10: ME_VARS | C10: M_mass_meaning | E10: 2 | F10: purpose
A11: X:\apps\paper-intelligence-suite-python\03_THEOPHYSICS_METRICS\theophysics_scorer.py | B11: ME_VARS | C11: M_mass_meaning | E11: 3 | F11: mass
A12: X:\apps\paper-intelligence-suite-python\03_THEOPHYSICS_METRICS\theophysics_scorer.py | B12: ME_VARS | C12: M_mass_meaning | E12: 4 | F12: nuclear
A13: X:\apps\paper-intelligence-suite-python\03_THEOPHYSICS_METRICS\theophysics_scorer.py | B13: ME_VARS | C13: M_mass_meaning | E13: 5 | F13: commit
... A68: X:\apps\paper-intelligence-suite-python\03_THEOPHYSICS_METRICS\theophysics_scorer.py | B68: ME_VARS | C68: C_christ_coherence | E68: 7 | F68: complete

Sheet CLAIM_TERMS
A1: source_file | B1: collection | C1: item_index | D1: term
A2: X:\apps\paper-intelligence-suite-python\06_TRUTH_ENGINE\truth_coherence_scanner.py | B2: CLAIM_TERMS | C2: 1 | D2: shows
A3: X:\apps\paper-intelligence-suite-python\06_TRUTH_ENGINE\truth_coherence_scanner.py | B3: CLAIM_TERMS | C3: 2 | D3: demands
A4: X:\apps\paper-intelligence-suite-python\06_TRUTH_ENGINE\truth_coherence_scanner.py | B4: CLAIM_TERMS | C4: 3 | D4: proves
A5: X:\apps\paper-intelligence-suite-python\06_TRUTH_ENGINE\truth_coherence_scanner.py | B5: CLAIM_TERMS | C5: 4 | D5: is
A6: X:\apps\paper-intelligence-suite-python\06_TRUTH_ENGINE\truth_coherence_scanner.py | B6: CLAIM_TERMS | C6: 5 | D6: must
A7: X:\apps\paper-intelligence-suite-python\06_TRUTH_ENGINE\truth_coherence_scanner.py | B7: CLAIM_TERMS | C7: 6 | D7: requires
A8: X:\apps\paper-intelligence-suite-python\06_TRUTH_ENGINE\truth_coherence_scanner.py | B8: CLAIM_TERMS | C8: 7 | D8: indicates
A9: X:\apps\paper-intelligence-suite-python\06_TRUTH_ENGINE\truth_coherence_scanner.py | B9: CLAIM_TERMS | C9: 8 | D9: are
A10: X:\apps\paper-intelligence-suite-python\06_TRUTH_ENGINE\truth_coherence_scanner.py | B10: CLAIM_TERMS | C10: 9 | D10: forces
A11: X:\apps\paper-intelligence-suite-python\06_TRUTH_ENGINE\truth_coherence_scanner.py | B11: CLAIM_TERMS | C11: 10 | D11: grounds
A12: X:\apps\paper-intelligence-suite-python\06_TRUTH_ENGINE\truth_coherence_scanner.py | B12: CLAIM_TERMS | C12: 11 | D12: means
A13: X:\apps\paper-intelligence-suite-python\06_TRUTH_ENGINE\truth_coherence_scanner.py | B13: CLAIM_TERMS | C13: 12 | D13: predicts
A14: X:\apps\paper-intelligence-suite-python\06_TRUTH_ENGINE\truth_coherence_scanner.py | B14: CLAIM_TERMS | C14: 13 | D14: explains

Sheet EVIDENCE_TERMS
A1: source_file | B1: collection | C1: item_index | D1: term
A2: X:\apps\paper-intelligence-suite-python\06_TRUTH_ENGINE\truth_coherence_scanner.py | B2: EVIDENCE_TERMS | C2: 1 | D2: replicated
A3: X:\apps\paper-intelligence-suite-python\06_TRUTH_ENGINE\truth_coherence_scanner.py | B3: EVIDENCE_TERMS | C3: 2 | D3: evidence
A4: X:\apps\paper-intelligence-suite-python\06_TRUTH_ENGINE\truth_coherence_scanner.py | B4: EVIDENCE_TERMS | C4: 3 | D4: proof
A5: X:\apps\paper-intelligence-suite-python\06_TRUTH_ENGINE\truth_coherence_scanner.py | B5: EVIDENCE_TERMS | C5: 4 | D5: source
A6: X:\apps\paper-intelligence-suite-python\06_TRUTH_ENGINE\truth_coherence_scanner.py | B6: EVIDENCE_TERMS | C6: 5 | D6: experiment
A7: X:\apps\paper-intelligence-suite-python\06_TRUTH_ENGINE\truth_coherence_scanner.py | B7: EVIDENCE_TERMS | C7: 6 | D7: study
A8: X:\apps\paper-intelligence-suite-python\06_TRUTH_ENGINE\truth_coherence_scanner.py | B8: EVIDENCE_TERMS | C8: 7 | D8: data
A9: X:\apps\paper-intelligence-suite-python\06_TRUTH_ENGINE\truth_coherence_scanner.py | B9: EVIDENCE_TERMS | C9: 8 | D9: confirmed
A10: X:\apps\paper-intelligence-suite-python\06_TRUTH_ENGINE\truth_coherence_scanner.py | B10: EVIDENCE_TERMS | C10: 9 | D10: measured
A11: X:\apps\paper-intelligence-suite-python\06_TRUTH_ENGINE\truth_coherence_scanner.py | B11: EVIDENCE_TERMS | C11: 10 | D11: dataset
A12: X:\apps\paper-intelligence-suite-python\06_TRUTH_ENGINE\truth_coherence_scanner.py | B12: EVIDENCE_TERMS | C12: 11 | D12: trial
A13: X:\apps\paper-intelligence-suite-python\06_TRUTH_ENGINE\truth_coherence_scanner.py | B13: EVIDENCE_TERMS | C13: 12 | D13: equation
A14: X:\apps\paper-intelligence-suite-python\06_TRUTH_ENGINE\truth_coherence_scanner.py | B14: EVIDENCE_TERMS | C14: 13 | D14: observed

Sheet FALSIFY_TERMS
A1: source_file | B1: collection | C1: item_index | D1: term
A2: X:\apps\paper-intelligence-suite-python\06_TRUTH_ENGINE\truth_coherence_scanner.py | B2: FALSIFY_TERMS | C2: 1 | D2: breaks if
A3: X:\apps\paper-intelligence-suite-python\06_TRUTH_ENGINE\truth_coherence_scanner.py | B3: FALSIFY_TERMS | C3: 2 | D3: if false
A4: X:\apps\paper-intelligence-suite-python\06_TRUTH_ENGINE\truth_coherence_scanner.py | B4: FALSIFY_TERMS | C4: 3 | D4: disconfirm
A5: X:\apps\paper-intelligence-suite-python\06_TRUTH_ENGINE\truth_coherence_scanner.py | B5: FALSIFY_TERMS | C5: 4 | D5: invalidates
A6: X:\apps\paper-intelligence-suite-python\06_TRUTH_ENGINE\truth_coherence_scanner.py | B6: FALSIFY_TERMS | C6: 5 | D6: collapse if
A7: X:\apps\paper-intelligence-suite-python\06_TRUTH_ENGINE\truth_coherence_scanner.py | B7: FALSIFY_TERMS | C7: 6 | D7: death condition
A8: X:\apps\paper-intelligence-suite-python\06_TRUTH_ENGINE\truth_coherence_scanner.py | B8: FALSIFY_TERMS | C8: 7 | D8: falsification
A9: X:\apps\paper-intelligence-suite-python\06_TRUTH_ENGINE\truth_coherence_scanner.py | B9: FALSIFY_TERMS | C9: 8 | D9: kill
A10: X:\apps\paper-intelligence-suite-python\06_TRUTH_ENGINE\truth_coherence_scanner.py | B10: FALSIFY_TERMS | C10: 9 | D10: would fail
A11: X:\apps\paper-intelligence-suite-python\06_TRUTH_ENGINE\truth_coherence_scanner.py | B11: FALSIFY_TERMS | C11: 10 | D11: falsify

Sheet DEPENDENCY_TERMS
A1: source_file | B1: collection | C1: item_index | D1: term
A2: X:\apps\paper-intelligence-suite-python\06_TRUTH_ENGINE\truth_coherence_scanner.py | B2: DEPENDENCY_TERMS | C2: 1 | D2: boundary condition
A3: X:\apps\paper-intelligence-suite-python\06_TRUTH_ENGINE\truth_coherence_scanner.py | B3: DEPENDENCY_TERMS | C3: 2 | D3: if
A4: X:\apps\paper-intelligence-suite-python\06_TRUTH_ENGINE\truth_coherence_scanner.py | B4: DEPENDENCY_TERMS | C4: 3 | D4: depends on
A5: X:\apps\paper-intelligence-suite-python\06_TRUTH_ENGINE\truth_coherence_scanner.py | B5: DEPENDENCY_TERMS | C5: 4 | D5: because
A6: X:\apps\paper-intelligence-suite-python\06_TRUTH_ENGINE\truth_coherence_scanner.py | B6: DEPENDENCY_TERMS | C6: 5 | D6: given
A7: X:\apps\paper-intelligence-suite-python\06_TRUTH_ENGINE\truth_coherence_scanner.py | B7: DEPENDENCY_TERMS | C7: 6 | D7: premise
A8: X:\apps\paper-intelligence-suite-python\06_TRUTH_ENGINE\truth_coherence_scanner.py | B8: DEPENDENCY_TERMS | C8: 7 | D8: requires
A9: X:\apps\paper-intelligence-suite-python\06_TRUTH_ENGINE\truth_coherence_scanner.py | B9: DEPENDENCY_TERMS | C9: 8 | D9: under
A10: X:\apps\paper-intelligence-suite-python\06_TRUTH_ENGINE\truth_coherence_scanner.py | B10: DEPENDENCY_TERMS | C10: 9 | D10: assumes

Sheet HEDGE_TERMS
A1: source_file | B1: collection | C1: item_index | D1: term
A2: X:\apps\paper-intelligence-suite-python\06_TRUTH_ENGINE\truth_coherence_scanner.py | B2: HEDGE_TERMS | C2: 1 | D2: probably
A3: X:\apps\paper-intelligence-suite-python\06_TRUTH_ENGINE\truth_coherence_scanner.py | B3: HEDGE_TERMS | C3: 2 | D3: seems
A4: X:\apps\paper-intelligence-suite-python\06_TRUTH_ENGINE\truth_coherence_scanner.py | B4: HEDGE_TERMS | C4: 3 | D4: maybe
A5: X:\apps\paper-intelligence-suite-python\06_TRUTH_ENGINE\truth_coherence_scanner.py | B5: HEDGE_TERMS | C5: 4 | D5: might
A6: X:\apps\paper-intelligence-suite-python\06_TRUTH_ENGINE\truth_coherence_scanner.py | B6: HEDGE_TERMS | C6: 5 | D6: likely
A7: X:\apps\paper-intelligence-suite-python\06_TRUTH_ENGINE\truth_coherence_scanner.py | B7: HEDGE_TERMS | C7: 6 | D7: roughly
A8: X:\apps\paper-intelligence-suite-python\06_TRUTH_ENGINE\truth_coherence_scanner.py | B8: HEDGE_TERMS | C8: 7 | D8: perhaps
A9: X:\apps\paper-intelligence-suite-python\06_TRUTH_ENGINE\truth_coherence_scanner.py | B9: HEDGE_TERMS | C9: 8 | D9: could
A10: X:\apps\paper-intelligence-suite-python\06_TRUTH_ENGINE\truth_coherence_scanner.py | B10: HEDGE_TERMS | C10: 9 | D10: appears
A11: X:\apps\paper-intelligence-suite-python\06_TRUTH_ENGINE\truth_coherence_scanner.py | B11: HEDGE_TERMS | C11: 10 | D11: sort of
A12: X:\apps\paper-intelligence-suite-python\06_TRUTH_ENGINE\truth_coherence_scanner.py | B12: HEDGE_TERMS | C12: 11 | D12: kind of
A13: X:\apps\paper-intelligence-suite-python\06_TRUTH_ENGINE\truth_coherence_scanner.py | B13: HEDGE_TERMS | C13: 12 | D13: possibly

Sheet ABSOLUTE_TERMS
A1: source_file | B1: collection | C1: item_index | D1: term
A2: X:\apps\paper-intelligence-suite-python\06_TRUTH_ENGINE\truth_coherence_scanner.py | B2: ABSOLUTE_TERMS | C2: 1 | D2: proves
A3: X:\apps\paper-intelligence-suite-python\06_TRUTH_ENGINE\truth_coherence_scanner.py | B3: ABSOLUTE_TERMS | C3: 2 | D3: always
A4: X:\apps\paper-intelligence-suite-python\06_TRUTH_ENGINE\truth_coherence_scanner.py | B4: ABSOLUTE_TERMS | C4: 3 | D4: never
A5: X:\apps\paper-intelligence-suite-python\06_TRUTH_ENGINE\truth_coherence_scanner.py | B5: ABSOLUTE_TERMS | C5: 4 | D5: certainly
A6: X:\apps\paper-intelligence-suite-python\06_TRUTH_ENGINE\truth_coherence_scanner.py | B6: ABSOLUTE_TERMS | C6: 5 | D6: obviously
A7: X:\apps\paper-intelligence-suite-python\06_TRUTH_ENGINE\truth_coherence_scanner.py | B7: ABSOLUTE_TERMS | C7: 6 | D7: undeniable
A8: X:\apps\paper-intelligence-suite-python\06_TRUTH_ENGINE\truth_coherence_scanner.py | B8: ABSOLUTE_TERMS | C8: 7 | D8: impossible

Sheet BRIDGE_TERMS
A1: source_file | B1: collection | C1: item_index | D1: term
A2: X:\apps\paper-intelligence-suite-python\06_TRUTH_ENGINE\truth_coherence_scanner.py | B2: BRIDGE_TERMS | C2: 1 | D2: this means
A3: X:\apps\paper-intelligence-suite-python\06_TRUTH_ENGINE\truth_coherence_scanner.py | B3: BRIDGE_TERMS | C3: 2 | D3: thus
A4: X:\apps\paper-intelligence-suite-python\06_TRUTH_ENGINE\truth_coherence_scanner.py | B4: BRIDGE_TERMS | C4: 3 | D4: so
A5: X:\apps\paper-intelligence-suite-python\06_TRUTH_ENGINE\truth_coherence_scanner.py | B5: BRIDGE_TERMS | C5: 4 | D5: then
A6: X:\apps\paper-intelligence-suite-python\06_TRUTH_ENGINE\truth_coherence_scanner.py | B6: BRIDGE_TERMS | C6: 5 | D6: because
A7: X:\apps\paper-intelligence-suite-python\06_TRUTH_ENGINE\truth_coherence_scanner.py | B7: BRIDGE_TERMS | C7: 6 | D7: consequently
A8: X:\apps\paper-intelligence-suite-python\06_TRUTH_ENGINE\truth_coherence_scanner.py | B8: BRIDGE_TERMS | C8: 7 | D8: as a result
A9: X:\apps\paper-intelligence-suite-python\06_TRUTH_ENGINE\truth_coherence_scanner.py | B9: BRIDGE_TERMS | C9: 8 | D9: but
A10: X:\apps\paper-intelligence-suite-python\06_TRUTH_ENGINE\truth_coherence_scanner.py | B10: BRIDGE_TERMS | C10: 9 | D10: therefore
A11: X:\apps\paper-intelligence-suite-python\06_TRUTH_ENGINE\truth_coherence_scanner.py | B11: BRIDGE_TERMS | C11: 10 | D11: next
A12: X:\apps\paper-intelligence-suite-python\06_TRUTH_ENGINE\truth_coherence_scanner.py | B12: BRIDGE_TERMS | C12: 11 | D12: however

Sheet NEGATION_TERMS
A1: source_file | B1: collection | C1: item_index | D1: term
A2: X:\apps\paper-intelligence-suite-python\06_TRUTH_ENGINE\truth_coherence_scanner.py | B2: NEGATION_TERMS | C2: 1 | D2: false
A3: X:\apps\paper-intelligence-suite-python\06_TRUTH_ENGINE\truth_coherence_scanner.py | B3: NEGATION_TERMS | C3: 2 | D3: can't
A4: X:\apps\paper-intelligence-suite-python\06_TRUTH_ENGINE\truth_coherence_scanner.py | B4: NEGATION_TERMS | C4: 3 | D4: never
A5: X:\apps\paper-intelligence-suite-python\06_TRUTH_ENGINE\truth_coherence_scanner.py | B5: NEGATION_TERMS | C5: 4 | D5: fails
A6: X:\apps\paper-intelligence-suite-python\06_TRUTH_ENGINE\truth_coherence_scanner.py | B6: NEGATION_TERMS | C6: 5 | D6: cannot
A7: X:\apps\paper-intelligence-suite-python\06_TRUTH_ENGINE\truth_coherence_scanner.py | B7: NEGATION_TERMS | C7: 6 | D7: no
A8: X:\apps\paper-intelligence-suite-python\06_TRUTH_ENGINE\truth_coherence_scanner.py | B8: NEGATION_TERMS | C8: 7 | D8: not

Sheet FRUITS_LEX
A1: source_file | B1: collection | C1: key | D1: subkey | E1: item_index | F1: value
A2: X:\apps\paper-intelligence-suite-python\06_TRUTH_ENGINE\truth_coherence_scanner.py | B2: FRUITS_LEXICON | C2: love | E2: 1 | F2: compassion
A3: X:\apps\paper-intelligence-suite-python\06_TRUTH_ENGINE\truth_coherence_scanner.py | B3: FRUITS_LEXICON | C3: love | E3: 2 | F3: care
A4: X:\apps\paper-intelligence-suite-python\06_TRUTH_ENGINE\truth_coherence_scanner.py | B4: FRUITS_LEXICON | C4: love | E4: 3 | F4: love
A5: X:\apps\paper-intelligence-suite-python\06_TRUTH_ENGINE\truth_coherence_scanner.py | B5: FRUITS_LEXICON | C5: love | E5: 4 | F5: charity
A6: X:\apps\paper-intelligence-suite-python\06_TRUTH_ENGINE\truth_coherence_scanner.py | B6: FRUITS_LEXICON | C6: joy | E6: 1 | F6: glad
A7: X:\apps\paper-intelligence-suite-python\06_TRUTH_ENGINE\truth_coherence_scanner.py | B7: FRUITS_LEXICON | C7: joy | E7: 2 | F7: joy
A8: X:\apps\paper-intelligence-suite-python\06_TRUTH_ENGINE\truth_coherence_scanner.py | B8: FRUITS_LEXICON | C8: joy | E8: 3 | F8: rejoice
A9: X:\apps\paper-intelligence-suite-python\06_TRUTH_ENGINE\truth_coherence_scanner.py | B9: FRUITS_LEXICON | C9: joy | E9: 4 | F9: delight
A10: X:\apps\paper-intelligence-suite-python\06_TRUTH_ENGINE\truth_coherence_scanner.py | B10: FRUITS_LEXICON | C10: peace | E10: 1 | F10: peace
A11: X:\apps\paper-intelligence-suite-python\06_TRUTH_ENGINE\truth_coherence_scanner.py | B11: FRUITS_LEXICON | C11: peace | E11: 2 | F11: calm
A12: X:\apps\paper-intelligence-suite-python\06_TRUTH_ENGINE\truth_coherence_scanner.py | B12: FRUITS_LEXICON | C12: peace | E12: 3 | F12: rest
A13: X:\apps\paper-intelligence-suite-python\06_TRUTH_ENGINE\truth_coherence_scanner.py | B13: FRUITS_LEXICON | C13: peace | E13: 4 | F13: reconcile
... A38: X:\apps\paper-intelligence-suite-python\06_TRUTH_ENGINE\truth_coherence_scanner.py | B38: FRUITS_LEXICON | C38: self_control | E38: 5 | F38: discipline

Sheet ANTI_FRUITS
A1: source_file | B1: collection | C1: key | D1: subkey | E1: item_index | F1: value
A2: X:\apps\paper-intelligence-suite-python\06_TRUTH_ENGINE\truth_coherence_scanner.py | B2: ANTI_FRUITS_LEXICON | C2: love | E2: 1 | F2: malice
A3: X:\apps\paper-intelligence-suite-python\06_TRUTH_ENGINE\truth_coherence_scanner.py | B3: ANTI_FRUITS_LEXICON | C3: love | E3: 2 | F3: cruelty
A4: X:\apps\paper-intelligence-suite-python\06_TRUTH_ENGINE\truth_coherence_scanner.py | B4: ANTI_FRUITS_LEXICON | C4: love | E4: 3 | F4: contempt
A5: X:\apps\paper-intelligence-suite-python\06_TRUTH_ENGINE\truth_coherence_scanner.py | B5: ANTI_FRUITS_LEXICON | C5: love | E5: 4 | F5: hatred
A6: X:\apps\paper-intelligence-suite-python\06_TRUTH_ENGINE\truth_coherence_scanner.py | B6: ANTI_FRUITS_LEXICON | C6: joy | E6: 1 | F6: hopeless
A7: X:\apps\paper-intelligence-suite-python\06_TRUTH_ENGINE\truth_coherence_scanner.py | B7: ANTI_FRUITS_LEXICON | C7: joy | E7: 2 | F7: misery
A8: X:\apps\paper-intelligence-suite-python\06_TRUTH_ENGINE\truth_coherence_scanner.py | B8: ANTI_FRUITS_LEXICON | C8: joy | E8: 3 | F8: nihilism
A9: X:\apps\paper-intelligence-suite-python\06_TRUTH_ENGINE\truth_coherence_scanner.py | B9: ANTI_FRUITS_LEXICON | C9: joy | E9: 4 | F9: despair
A10: X:\apps\paper-intelligence-suite-python\06_TRUTH_ENGINE\truth_coherence_scanner.py | B10: ANTI_FRUITS_LEXICON | C10: peace | E10: 1 | F10: hostility
A11: X:\apps\paper-intelligence-suite-python\06_TRUTH_ENGINE\truth_coherence_scanner.py | B11: ANTI_FRUITS_LEXICON | C11: peace | E11: 2 | F11: violence
A12: X:\apps\paper-intelligence-suite-python\06_TRUTH_ENGINE\truth_coherence_scanner.py | B12: ANTI_FRUITS_LEXICON | C12: peace | E12: 3 | F12: panic
A13: X:\apps\paper-intelligence-suite-python\06_TRUTH_ENGINE\truth_coherence_scanner.py | B13: ANTI_FRUITS_LEXICON | C13: peace | E13: 4 | F13: chaos
... A37: X:\apps\paper-intelligence-suite-python\06_TRUTH_ENGINE\truth_coherence_scanner.py | B37: ANTI_FRUITS_LEXICON | C37: self_control | E37: 4 | F37: unrestrained

Sheet CHAR_ATTR_PATTERNS
A1: source_file | B1: collection | C1: key | D1: subkey | E1: item_index | F1: value
A2: X:\apps\paper-intelligence-suite-python\06_TRUTH_ENGINE\truth_coherence_scanner.py | B2: CHARACTER_ATTRIBUTE_PATTERNS | C2: spiritual_coherence | D2: kind | F2: protective
A3: X:\apps\paper-intelligence-suite-python\06_TRUTH_ENGINE\truth_coherence_scanner.py | B3: CHARACTER_ATTRIBUTE_PATTERNS | C3: spiritual_coherence | D3: positive | E3: 1 | F3: transparent faith
A4: X:\apps\paper-intelligence-suite-python\06_TRUTH_ENGINE\truth_coherence_scanner.py | B4: CHARACTER_ATTRIBUTE_PATTERNS | C4: spiritual_coherence | D4: positive | E4: 2 | F4: sacrificial love
A5: X:\apps\paper-intelligence-suite-python\06_TRUTH_ENGINE\truth_coherence_scanner.py | B5: CHARACTER_ATTRIBUTE_PATTERNS | C5: spiritual_coherence | D5: positive | E5: 3 | F5: walks the talk
A6: X:\apps\paper-intelligence-suite-python\06_TRUTH_ENGINE\truth_coherence_scanner.py | B6: CHARACTER_ATTRIBUTE_PATTERNS | C6: spiritual_coherence | D6: positive | E6: 4 | F6: servant heart
A7: X:\apps\paper-intelligence-suite-python\06_TRUTH_ENGINE\truth_coherence_scanner.py | B7: CHARACTER_ATTRIBUTE_PATTERNS | C7: spiritual_coherence | D7: positive | E7: 5 | F7: glorifies god
A8: X:\apps\paper-intelligence-suite-python\06_TRUTH_ENGINE\truth_coherence_scanner.py | B8: CHARACTER_ATTRIBUTE_PATTERNS | C8: spiritual_coherence | D8: positive | E8: 6 | F8: genuine worship
A9: X:\apps\paper-intelligence-suite-python\06_TRUTH_ENGINE\truth_coherence_scanner.py | B9: CHARACTER_ATTRIBUTE_PATTERNS | C9: spiritual_coherence | D9: positive | E9: 7 | F9: coherent theology
A10: X:\apps\paper-intelligence-suite-python\06_TRUTH_ENGINE\truth_coherence_scanner.py | B10: CHARACTER_ATTRIBUTE_PATTERNS | C10: spiritual_coherence | D10: positive | E10: 8 | F10: consistent worldview
A11: X:\apps\paper-intelligence-suite-python\06_TRUTH_ENGINE\truth_coherence_scanner.py | B11: CHARACTER_ATTRIBUTE_PATTERNS | C11: spiritual_coherence | D11: negative | E11: 1 | F11: contradictory statements
A12: X:\apps\paper-intelligence-suite-python\06_TRUTH_ENGINE\truth_coherence_scanner.py | B12: CHARACTER_ATTRIBUTE_PATTERNS | C12: spiritual_coherence | D12: negative | E12: 2 | F12: self-serving theology
A13: X:\apps\paper-intelligence-suite-python\06_TRUTH_ENGINE\truth_coherence_scanner.py | B13: CHARACTER_ATTRIBUTE_PATTERNS | C13: spiritual_coherence | D13: negative | E13: 3 | F13: manipulates faith
A14: X:\apps\paper-intelligence-suite-python\06_TRUTH_ENGINE\truth_coherence_scanner.py | B14: CHARACTER_ATTRIBUTE_PATTERNS | C14: spiritual_coherence | D14: negative | E14: 4 | F14: selective scripture
A15: X:\apps\paper-intelligence-suite-python\06_TRUTH_ENGINE\truth_coherence_scanner.py | B15: CHARACTER_ATTRIBUTE_PATTERNS | C15: spiritual_coherence | D15: negative | E15: 5 | F15: twists scripture
A16: X:\apps\paper-intelligence-suite-python\06_TRUTH_ENGINE\truth_coherence_scanner.py | B16: CHARACTER_ATTRIBUTE_PATTERNS | C16: humility_index | D16: kind | F16: protective
A17: X:\apps\paper-intelligence-suite-python\06_TRUTH_ENGINE\truth_coherence_scanner.py | B17: CHARACTER_ATTRIBUTE_PATTERNS | C17: humility_index | D17: positive | E17: 1 | F17: admits uncertainty
A18: X:\apps\paper-intelligence-suite-python\06_TRUTH_ENGINE\truth_coherence_scanner.py | B18: CHARACTER_ATTRIBUTE_PATTERNS | C18: humility_index | D18: positive | E18: 2 | F18: servant leadership
A19: X:\apps\paper-intelligence-suite-python\06_TRUTH_ENGINE\truth_coherence_scanner.py | B19: CHARACTER_ATTRIBUTE_PATTERNS | C19: humility_index | D19: positive | E19: 3 | F19: acknowledges mistakes
A20: X:\apps\paper-intelligence-suite-python\06_TRUTH_ENGINE\truth_coherence_scanner.py | B20: CHARACTER_ATTRIBUTE_PATTERNS | C20: humility_index | D20: positive | E20: 4 | F20: gives credit to others
A21: X:\apps\paper-intelligence-suite-python\06_TRUTH_ENGINE\truth_coherence_scanner.py | B21: CHARACTER_ATTRIBUTE_PATTERNS | C21: humility_index | D21: positive | E21: 5 | F21: puts others first
A22: X:\apps\paper-intelligence-suite-python\06_TRUTH_ENGINE\truth_coherence_scanner.py | B22: CHARACTER_ATTRIBUTE_PATTERNS | C22: humility_index | D22: positive | E22: 6 | F22: seeks guidance
A23: X:\apps\paper-intelligence-suite-python\06_TRUTH_ENGINE\truth_coherence_scanner.py | B23: CHARACTER_ATTRIBUTE_PATTERNS | C23: humility_index | D23: positive | E23: 7 | F23: teachable spirit
A24: X:\apps\paper-intelligence-suite-python\06_TRUTH_ENGINE\truth_coherence_scanner.py | B24: CHARACTER_ATTRIBUTE_PATTERNS | C24: humility_index | D24: negative | E24: 1 | F24: never admits error
A25: X:\apps\paper-intelligence-suite-python\06_TRUTH_ENGINE\truth_coherence_scanner.py | B25: CHARACTER_ATTRIBUTE_PATTERNS | C25: humility_index | D25: negative | E25: 2 | F25: demands worship
A26: X:\apps\paper-intelligence-suite-python\06_TRUTH_ENGINE\truth_coherence_scanner.py | B26: CHARACTER_ATTRIBUTE_PATTERNS | C26: humility_index | D26: negative | E26: 3 | F26: places self above all
A27: X:\apps\paper-intelligence-suite-python\06_TRUTH_ENGINE\truth_coherence_scanner.py | B27: CHARACTER_ATTRIBUTE_PATTERNS | C27: humility_index | D27: negative | E27: 4 | F27: claims infallibility
A28: X:\apps\paper-intelligence-suite-python\06_TRUTH_ENGINE\truth_coherence_scanner.py | B28: CHARACTER_ATTRIBUTE_PATTERNS | C28: humility_index | D28: negative | E28: 5 | F28: takes all credit
... A30: X:\apps\paper-intelligence-suite-python\06_TRUTH_ENGINE\truth_coherence_scanner.py | B30: CHARACTER_ATTRIBUTE_PATTERNS | C30: humility_index | D30: negative | E30: 7 | F30: shows arrogance
A31: X:\apps\paper-intelligence-suite-python\06_TRUTH_ENGINE\truth_coherence_scanner.py | B31: CHARACTER_ATTRIBUTE_PATTERNS | C31: spiritual_discernment | D31: kind | F31: protective
A32: X:\apps\paper-intelligence-suite-python\06_TRUTH_ENGINE\truth_coherence_scanner.py | B32: CHARACTER_ATTRIBUTE_PATTERNS | C32: spiritual_discernment | D32: positive | E32: 1 | F32: recognizes false teaching
A33: X:\apps\paper-intelligence-suite-python\06_TRUTH_ENGINE\truth_coherence_scanner.py | B33: CHARACTER_ATTRIBUTE_PATTERNS | C33: spiritual_discernment | D33: positive | E33: 2 | F33: tests the spirits
A34: X:\apps\paper-intelligence-suite-python\06_TRUTH_ENGINE\truth_coherence_scanner.py | B34: CHARACTER_ATTRIBUTE_PATTERNS | C34: spiritual_discernment | D34: positive | E34: 3 | F34: sees through deception
A35: X:\apps\paper-intelligence-suite-python\06_TRUTH_ENGINE\truth_coherence_scanner.py | B35: CHARACTER_ATTRIBUTE_PATTERNS | C35: spiritual_discernment | D35: positive | E35: 4 | F35: identifies wolves
A36: X:\apps\paper-intelligence-suite-python\06_TRUTH_ENGINE\truth_coherence_scanner.py | B36: CHARACTER_ATTRIBUTE_PATTERNS | C36: spiritual_discernment | D36: positive | E36: 5 | F36: discerns motives
A37: X:\apps\paper-intelligence-suite-python\06_TRUTH_ENGINE\truth_coherence_scanner.py | B37: CHARACTER_ATTRIBUTE_PATTERNS | C37: spiritual_discernment | D37: positive | E37: 6 | F37: spiritual maturity
A38: X:\apps\paper-intelligence-suite-python\06_TRUTH_ENGINE\truth_coherence_scanner.py | B38: CHARACTER_ATTRIBUTE_PATTERNS | C38: spiritual_discernment | D38: negative | E38: 1 | F38: follows blindly
A39: X:\apps\paper-intelligence-suite-python\06_TRUTH_ENGINE\truth_coherence_scanner.py | B39: CHARACTER_ATTRIBUTE_PATTERNS | C39: spiritual_discernment | D39: negative | E39: 2 | F39: easily deceived
A40: X:\apps\paper-intelligence-suite-python\06_TRUTH_ENGINE\truth_coherence_scanner.py | B40: CHARACTER_ATTRIBUTE_PATTERNS | C40: spiritual_discernment | D40: negative | E40: 3 | F40: lacks discernment
A41: X:\apps\paper-intelligence-suite-python\06_TRUTH_ENGINE\truth_coherence_scanner.py | B41: CHARACTER_ATTRIBUTE_PATTERNS | C41: spiritual_discernment | D41: negative | E41: 4 | F41: naive trust
A42: X:\apps\paper-intelligence-suite-python\06_TRUTH_ENGINE\truth_coherence_scanner.py | B42: CHARACTER_ATTRIBUTE_PATTERNS | C42: moral_courage | D42: kind | F42: protective
A43: X:\apps\paper-intelligence-suite-python\06_TRUTH_ENGINE\truth_coherence_scanner.py | B43: CHARACTER_ATTRIBUTE_PATTERNS | C43: moral_courage | D43: positive | E43: 1 | F43: maintains integrity
A44: X:\apps\paper-intelligence-suite-python\06_TRUTH_ENGINE\truth_coherence_scanner.py | B44: CHARACTER_ATTRIBUTE_PATTERNS | C44: moral_courage | D44: positive | E44: 2 | F44: stands for truth
A45: X:\apps\paper-intelligence-suite-python\06_TRUTH_ENGINE\truth_coherence_scanner.py | B45: CHARACTER_ATTRIBUTE_PATTERNS | C45: moral_courage | D45: positive | E45: 3 | F45: refuses compromise
A46: X:\apps\paper-intelligence-suite-python\06_TRUTH_ENGINE\truth_coherence_scanner.py | B46: CHARACTER_ATTRIBUTE_PATTERNS | C46: moral_courage | D46: positive | E46: 4 | F46: defends the innocent
A47: X:\apps\paper-intelligence-suite-python\06_TRUTH_ENGINE\truth_coherence_scanner.py | B47: CHARACTER_ATTRIBUTE_PATTERNS | C47: moral_courage | D47: positive | E47: 5 | F47: sacrifices for others
A48: X:\apps\paper-intelligence-suite-python\06_TRUTH_ENGINE\truth_coherence_scanner.py | B48: CHARACTER_ATTRIBUTE_PATTERNS | C48: moral_courage | D48: positive | E48: 6 | F48: resists pressure
A49: X:\apps\paper-intelligence-suite-python\06_TRUTH_ENGINE\truth_coherence_scanner.py | B49: CHARACTER_ATTRIBUTE_PATTERNS | C49: moral_courage | D49: positive | E49: 7 | F49: speaks against injustice
A50: X:\apps\paper-intelligence-suite-python\06_TRUTH_ENGINE\truth_coherence_scanner.py | B50: CHARACTER_ATTRIBUTE_PATTERNS | C50: moral_courage | D50: negative | E50: 1 | F50: follows crowd
A51: X:\apps\paper-intelligence-suite-python\06_TRUTH_ENGINE\truth_coherence_scanner.py | B51: CHARACTER_ATTRIBUTE_PATTERNS | C51: moral_courage | D51: negative | E51: 2 | F51: abandons principles for gain
A52: X:\apps\paper-intelligence-suite-python\06_TRUTH_ENGINE\truth_coherence_scanner.py | B52: CHARACTER_ATTRIBUTE_PATTERNS | C52: moral_courage | D52: negative | E52: 3 | F52: compromises principles
A53: X:\apps\paper-intelligence-suite-python\06_TRUTH_ENGINE\truth_coherence_scanner.py | B53: CHARACTER_ATTRIBUTE_PATTERNS | C53: moral_courage | D53: negative | E53: 4 | F53: stays silent about evil
A54: X:\apps\paper-intelligence-suite-python\06_TRUTH_ENGINE\truth_coherence_scanner.py | B54: CHARACTER_ATTRIBUTE_PATTERNS | C54: deception_mastery | D54: kind | F54: threat
A55: X:\apps\paper-intelligence-suite-python\06_TRUTH_ENGINE\truth_coherence_scanner.py | B55: CHARACTER_ATTRIBUTE_PATTERNS | C55: deception_mastery | D55: positive | E55: 1 | F55: selective truth telling
A56: X:\apps\paper-intelligence-suite-python\06_TRUTH_ENGINE\truth_coherence_scanner.py | B56: CHARACTER_ATTRIBUTE_PATTERNS | C56: deception_mastery | D56: positive | E56: 2 | F56: manages information
A57: X:\apps\paper-intelligence-suite-python\06_TRUTH_ENGINE\truth_coherence_scanner.py | B57: CHARACTER_ATTRIBUTE_PATTERNS | C57: deception_mastery | D57: positive | E57: 3 | F57: spin doctor
A58: X:\apps\paper-intelligence-suite-python\06_TRUTH_ENGINE\truth_coherence_scanner.py | B58: CHARACTER_ATTRIBUTE_PATTERNS | C58: deception_mastery | D58: positive | E58: 4 | F58: curates reality
A59: X:\apps\paper-intelligence-suite-python\06_TRUTH_ENGINE\truth_coherence_scanner.py | B59: CHARACTER_ATTRIBUTE_PATTERNS | C59: deception_mastery | D59: positive | E59: 5 | F59: gaslighting
A60: X:\apps\paper-intelligence-suite-python\06_TRUTH_ENGINE\truth_coherence_scanner.py | B60: CHARACTER_ATTRIBUTE_PATTERNS | C60: deception_mastery | D60: positive | E60: 6 | F60: shapes perception
A61: X:\apps\paper-intelligence-suite-python\06_TRUTH_ENGINE\truth_coherence_scanner.py | B61: CHARACTER_ATTRIBUTE_PATTERNS | C61: deception_mastery | D61: positive | E61: 7 | F61: manipulates media
A62: X:\apps\paper-intelligence-suite-python\06_TRUTH_ENGINE\truth_coherence_scanner.py | B62: CHARACTER_ATTRIBUTE_PATTERNS | C62: deception_mastery | D62: positive | E62: 8 | F62: creates false consensus
A63: X:\apps\paper-intelligence-suite-python\06_TRUTH_ENGINE\truth_coherence_scanner.py | B63: CHARACTER_ATTRIBUTE_PATTERNS | C63: deception_mastery | D63: positive | E63: 9 | F63: narrative architect
A64: X:\apps\paper-intelligence-suite-python\06_TRUTH_ENGINE\truth_coherence_scanner.py | B64: CHARACTER_ATTRIBUTE_PATTERNS | C64: deception_mastery | D64: positive | E64: 10 | F64: controls narrative
A65: X:\apps\paper-intelligence-suite-python\06_TRUTH_ENGINE\truth_coherence_scanner.py | B65: CHARACTER_ATTRIBUTE_PATTERNS | C65: deception_mastery | D65: negative | E65: 1 | F65: transparent communication
A66: X:\apps\paper-intelligence-suite-python\06_TRUTH_ENGINE\truth_coherence_scanner.py | B66: CHARACTER_ATTRIBUTE_PATTERNS | C66: deception_mastery | D66: negative | E66: 2 | F66: provides full context
... A69: X:\apps\paper-intelligence-suite-python\06_TRUTH_ENGINE\truth_coherence_scanner.py | B69: CHARACTER_ATTRIBUTE_PATTERNS | C69: deception_mastery | D69: negative | E69: 5 | F69: open information
A70: X:\apps\paper-intelligence-suite-python\06_TRUTH_ENGINE\truth_coherence_scanner.py | B70: CHARACTER_ATTRIBUTE_PATTERNS | C70: charismatic_manipulation | D70: kind | F70: threat
A71: X:\apps\paper-intelligence-suite-python\06_TRUTH_ENGINE\truth_coherence_scanner.py | B71: CHARACTER_ATTRIBUTE_PATTERNS | C71: charismatic_manipulation | D71: positive | E71: 1 | F71: false intimacy
A72: X:\apps\paper-intelligence-suite-python\06_TRUTH_ENGINE\truth_coherence_scanner.py | B72: CHARACTER_ATTRIBUTE_PATTERNS | C72: charismatic_manipulation | D72: positive | E72: 2 | F72: uses charm to deceive
A73: X:\apps\paper-intelligence-suite-python\06_TRUTH_ENGINE\truth_coherence_scanner.py | B73: CHARACTER_ATTRIBUTE_PATTERNS | C73: charismatic_manipulation | D73: positive | E73: 3 | F73: mesmerizing presence
A74: X:\apps\paper-intelligence-suite-python\06_TRUTH_ENGINE\truth_coherence_scanner.py | B74: CHARACTER_ATTRIBUTE_PATTERNS | C74: charismatic_manipulation | D74: positive | E74: 4 | F74: inspires cult-like devotion
A75: X:\apps\paper-intelligence-suite-python\06_TRUTH_ENGINE\truth_coherence_scanner.py | B75: CHARACTER_ATTRIBUTE_PATTERNS | C75: charismatic_manipulation | D75: positive | E75: 5 | F75: exploits trust
A76: X:\apps\paper-intelligence-suite-python\06_TRUTH_ENGINE\truth_coherence_scanner.py | B76: CHARACTER_ATTRIBUTE_PATTERNS | C76: charismatic_manipulation | D76: positive | E76: 6 | F76: uses emotional manipulation
A77: X:\apps\paper-intelligence-suite-python\06_TRUTH_ENGINE\truth_coherence_scanner.py | B77: CHARACTER_ATTRIBUTE_PATTERNS | C77: charismatic_manipulation | D77: positive | E77: 7 | F77: magnetic personality
A78: X:\apps\paper-intelligence-suite-python\06_TRUTH_ENGINE\truth_coherence_scanner.py | B78: CHARACTER_ATTRIBUTE_PATTERNS | C78: charismatic_manipulation | D78: positive | E78: 8 | F78: creates dependency
A79: X:\apps\paper-intelligence-suite-python\06_TRUTH_ENGINE\truth_coherence_scanner.py | B79: CHARACTER_ATTRIBUTE_PATTERNS | C79: charismatic_manipulation | D79: positive | E79: 9 | F79: demands loyalty
A80: X:\apps\paper-intelligence-suite-python\06_TRUTH_ENGINE\truth_coherence_scanner.py | B80: CHARACTER_ATTRIBUTE_PATTERNS | C80: charismatic_manipulation | D80: positive | E80: 10 | F80: creates parasocial bonds
A81: X:\apps\paper-intelligence-suite-python\06_TRUTH_ENGINE\truth_coherence_scanner.py | B81: CHARACTER_ATTRIBUTE_PATTERNS | C81: charismatic_manipulation | D81: negative | E81: 1 | F81: builds genuine community
A82: X:\apps\paper-intelligence-suite-python\06_TRUTH_ENGINE\truth_coherence_scanner.py | B82: CHARACTER_ATTRIBUTE_PATTERNS | C82: charismatic_manipulation | D82: negative | E82: 2 | F82: transparent motives
... A85: X:\apps\paper-intelligence-suite-python\06_TRUTH_ENGINE\truth_coherence_scanner.py | B85: CHARACTER_ATTRIBUTE_PATTERNS | C85: charismatic_manipulation | D85: negative | E85: 5 | F85: encourages independence
A86: X:\apps\paper-intelligence-suite-python\06_TRUTH_ENGINE\truth_coherence_scanner.py | B86: CHARACTER_ATTRIBUTE_PATTERNS | C86: authority_usurpation | D86: kind | F86: threat
A87: X:\apps\paper-intelligence-suite-python\06_TRUTH_ENGINE\truth_coherence_scanner.py | B87: CHARACTER_ATTRIBUTE_PATTERNS | C87: authority_usurpation | D87: positive | E87: 1 | F87: undermines institutions
A88: X:\apps\paper-intelligence-suite-python\06_TRUTH_ENGINE\truth_coherence_scanner.py | B88: CHARACTER_ATTRIBUTE_PATTERNS | C88: authority_usurpation | D88: positive | E88: 2 | F88: creates parallel power structures
A89: X:\apps\paper-intelligence-suite-python\06_TRUTH_ENGINE\truth_coherence_scanner.py | B89: CHARACTER_ATTRIBUTE_PATTERNS | C89: authority_usurpation | D89: positive | E89: 3 | F89: executive overreach
A90: X:\apps\paper-intelligence-suite-python\06_TRUTH_ENGINE\truth_coherence_scanner.py | B90: CHARACTER_ATTRIBUTE_PATTERNS | C90: authority_usurpation | D90: positive | E90: 4 | F90: consolidates control
A91: X:\apps\paper-intelligence-suite-python\06_TRUTH_ENGINE\truth_coherence_scanner.py | B91: CHARACTER_ATTRIBUTE_PATTERNS | C91: authority_usurpation | D91: positive | E91: 5 | F91: demands supreme loyalty
A92: X:\apps\paper-intelligence-suite-python\06_TRUTH_ENGINE\truth_coherence_scanner.py | B92: CHARACTER_ATTRIBUTE_PATTERNS | C92: authority_usurpation | D92: positive | E92: 6 | F92: concentrates authority
A93: X:\apps\paper-intelligence-suite-python\06_TRUTH_ENGINE\truth_coherence_scanner.py | B93: CHARACTER_ATTRIBUTE_PATTERNS | C93: authority_usurpation | D93: positive | E93: 7 | F93: eliminates opposition
A94: X:\apps\paper-intelligence-suite-python\06_TRUTH_ENGINE\truth_coherence_scanner.py | B94: CHARACTER_ATTRIBUTE_PATTERNS | C94: authority_usurpation | D94: positive | E94: 8 | F94: bypasses democratic processes
A95: X:\apps\paper-intelligence-suite-python\06_TRUTH_ENGINE\truth_coherence_scanner.py | B95: CHARACTER_ATTRIBUTE_PATTERNS | C95: authority_usurpation | D95: positive | E95: 9 | F95: replaces established authority
A96: X:\apps\paper-intelligence-suite-python\06_TRUTH_ENGINE\truth_coherence_scanner.py | B96: CHARACTER_ATTRIBUTE_PATTERNS | C96: authority_usurpation | D96: negative | E96: 1 | F96: accountable to others
A97: X:\apps\paper-intelligence-suite-python\06_TRUTH_ENGINE\truth_coherence_scanner.py | B97: CHARACTER_ATTRIBUTE_PATTERNS | C97: authority_usurpation | D97: negative | E97: 2 | F97: respects institutions
A98: X:\apps\paper-intelligence-suite-python\06_TRUTH_ENGINE\truth_coherence_scanner.py | B98: CHARACTER_ATTRIBUTE_PATTERNS | C98: authority_usurpation | D98: negative | E98: 3 | F98: distributes authority
... A100: X:\apps\paper-intelligence-suite-python\06_TRUTH_ENGINE\truth_coherence_scanner.py | B100: CHARACTER_ATTRIBUTE_PATTERNS | C100: authority_usurpation | D100: negative | E100: 5 | F100: respects checks and balances
A101: X:\apps\paper-intelligence-suite-python\06_TRUTH_ENGINE\truth_coherence_scanner.py | B101: CHARACTER_ATTRIBUTE_PATTERNS | C101: global_solution_complex | D101: kind | F101: threat
A102: X:\apps\paper-intelligence-suite-python\06_TRUTH_ENGINE\truth_coherence_scanner.py | B102: CHARACTER_ATTRIBUTE_PATTERNS | C102: global_solution_complex | D102: positive | E102: 1 | F102: era of universal peace
A103: X:\apps\paper-intelligence-suite-python\06_TRUTH_ENGINE\truth_coherence_scanner.py | B103: CHARACTER_ATTRIBUTE_PATTERNS | C103: global_solution_complex | D103: positive | E103: 2 | F103: global governance
A104: X:\apps\paper-intelligence-suite-python\06_TRUTH_ENGINE\truth_coherence_scanner.py | B104: CHARACTER_ATTRIBUTE_PATTERNS | C104: global_solution_complex | D104: positive | E104: 3 | F104: ushering in a new age
A105: X:\apps\paper-intelligence-suite-python\06_TRUTH_ENGINE\truth_coherence_scanner.py | B105: CHARACTER_ATTRIBUTE_PATTERNS | C105: global_solution_complex | D105: positive | E105: 4 | F105: final answer to
A106: X:\apps\paper-intelligence-suite-python\06_TRUTH_ENGINE\truth_coherence_scanner.py | B106: CHARACTER_ATTRIBUTE_PATTERNS | C106: global_solution_complex | D106: positive | E106: 5 | F106: one solution for humanity
...

Sheet FRUIT_BLEND
A1: source_file | B1: collection | C1: key | D1: subkey | E1: item_index | F1: value
A2: X:\apps\paper-intelligence-suite-python\08_EMOTION_PROFILE\emotion_analyzer.py | B2: FRUIT_BLEND | C2: love | D2: positive | E2: 1 | F2: love
A3: X:\apps\paper-intelligence-suite-python\08_EMOTION_PROFILE\emotion_analyzer.py | B3: FRUIT_BLEND | C3: love | D3: positive | E3: 2 | F3: caring
A4: X:\apps\paper-intelligence-suite-python\08_EMOTION_PROFILE\emotion_analyzer.py | B4: FRUIT_BLEND | C4: love | D4: positive | E4: 3 | F4: admiration
A5: X:\apps\paper-intelligence-suite-python\08_EMOTION_PROFILE\emotion_analyzer.py | B5: FRUIT_BLEND | C5: love | D5: positive | E5: 4 | F5: gratitude
A6: X:\apps\paper-intelligence-suite-python\08_EMOTION_PROFILE\emotion_analyzer.py | B6: FRUIT_BLEND | C6: love | D6: negative | E6: 1 | F6: anger
A7: X:\apps\paper-intelligence-suite-python\08_EMOTION_PROFILE\emotion_analyzer.py | B7: FRUIT_BLEND | C7: love | D7: negative | E7: 2 | F7: disgust
A8: X:\apps\paper-intelligence-suite-python\08_EMOTION_PROFILE\emotion_analyzer.py | B8: FRUIT_BLEND | C8: love | D8: negative | E8: 3 | F8: disapproval
A9: X:\apps\paper-intelligence-suite-python\08_EMOTION_PROFILE\emotion_analyzer.py | B9: FRUIT_BLEND | C9: joy | D9: positive | E9: 1 | F9: joy
A10: X:\apps\paper-intelligence-suite-python\08_EMOTION_PROFILE\emotion_analyzer.py | B10: FRUIT_BLEND | C10: joy | D10: positive | E10: 2 | F10: optimism
A11: X:\apps\paper-intelligence-suite-python\08_EMOTION_PROFILE\emotion_analyzer.py | B11: FRUIT_BLEND | C11: joy | D11: positive | E11: 3 | F11: excitement
A12: X:\apps\paper-intelligence-suite-python\08_EMOTION_PROFILE\emotion_analyzer.py | B12: FRUIT_BLEND | C12: joy | D12: positive | E12: 4 | F12: pride
A13: X:\apps\paper-intelligence-suite-python\08_EMOTION_PROFILE\emotion_analyzer.py | B13: FRUIT_BLEND | C13: joy | D13: positive | E13: 5 | F13: gratitude
... A71: X:\apps\paper-intelligence-suite-python\08_EMOTION_PROFILE\emotion_analyzer.py | B71: FRUIT_BLEND | C71: self_control | D71: negative | E71: 5 | F71: excitement

Sheet ANTI_FRUIT_MAP
A1: source_file | B1: collection | C1: key | D1: subkey | E1: item_index | F1: value
A2: X:\apps\paper-intelligence-suite-python\08_EMOTION_PROFILE\emotion_analyzer.py | B2: ANTI_FRUIT_MAP | C2: hatred | E2: 1 | F2: anger
A3: X:\apps\paper-intelligence-suite-python\08_EMOTION_PROFILE\emotion_analyzer.py | B3: ANTI_FRUIT_MAP | C3: hatred | E3: 2 | F3: disgust
A4: X:\apps\paper-intelligence-suite-python\08_EMOTION_PROFILE\emotion_analyzer.py | B4: ANTI_FRUIT_MAP | C4: hatred | E4: 3 | F4: disapproval
A5: X:\apps\paper-intelligence-suite-python\08_EMOTION_PROFILE\emotion_analyzer.py | B5: ANTI_FRUIT_MAP | C5: despair | E5: 1 | F5: sadness
A6: X:\apps\paper-intelligence-suite-python\08_EMOTION_PROFILE\emotion_analyzer.py | B6: ANTI_FRUIT_MAP | C6: despair | E6: 2 | F6: grief
A7: X:\apps\paper-intelligence-suite-python\08_EMOTION_PROFILE\emotion_analyzer.py | B7: ANTI_FRUIT_MAP | C7: despair | E7: 3 | F7: disappointment
A8: X:\apps\paper-intelligence-suite-python\08_EMOTION_PROFILE\emotion_analyzer.py | B8: ANTI_FRUIT_MAP | C8: conflict | E8: 1 | F8: anger
A9: X:\apps\paper-intelligence-suite-python\08_EMOTION_PROFILE\emotion_analyzer.py | B9: ANTI_FRUIT_MAP | C9: conflict | E9: 2 | F9: annoyance
A10: X:\apps\paper-intelligence-suite-python\08_EMOTION_PROFILE\emotion_analyzer.py | B10: ANTI_FRUIT_MAP | C10: conflict | E10: 3 | F10: fear
A11: X:\apps\paper-intelligence-suite-python\08_EMOTION_PROFILE\emotion_analyzer.py | B11: ANTI_FRUIT_MAP | C11: conflict | E11: 4 | F11: nervousness
A12: X:\apps\paper-intelligence-suite-python\08_EMOTION_PROFILE\emotion_analyzer.py | B12: ANTI_FRUIT_MAP | C12: impatience | E12: 1 | F12: anger
A13: X:\apps\paper-intelligence-suite-python\08_EMOTION_PROFILE\emotion_analyzer.py | B13: ANTI_FRUIT_MAP | C13: impatience | E13: 2 | F13: annoyance
... A32: X:\apps\paper-intelligence-suite-python\08_EMOTION_PROFILE\emotion_analyzer.py | B32: ANTI_FRUIT_MAP | C32: indulgence | E32: 4 | F32: annoyance

Sheet LAW_KEYWORDS
A1: source_file | B1: collection | C1: key | D1: subkey | E1: item_index | F1: value
A2: \\dlowenas\brain\David\pipelines\engines\pipeline\stations\classifier.py | B2: LAW_KEYWORDS | C2: L1_Gravitation | E2: 1 | F2: gravity
A3: \\dlowenas\brain\David\pipelines\engines\pipeline\stations\classifier.py | B3: LAW_KEYWORDS | C3: L1_Gravitation | E3: 2 | F3: curvature
A4: \\dlowenas\brain\David\pipelines\engines\pipeline\stations\classifier.py | B4: LAW_KEYWORDS | C4: L1_Gravitation | E4: 3 | F4: spacetime
A5: \\dlowenas\brain\David\pipelines\engines\pipeline\stations\classifier.py | B5: LAW_KEYWORDS | C5: L1_Gravitation | E5: 4 | F5: mass
A6: \\dlowenas\brain\David\pipelines\engines\pipeline\stations\classifier.py | B6: LAW_KEYWORDS | C6: L1_Gravitation | E6: 5 | F6: sin
A7: \\dlowenas\brain\David\pipelines\engines\pipeline\stations\classifier.py | B7: LAW_KEYWORDS | C7: L1_Gravitation | E7: 6 | F7: grace
A8: \\dlowenas\brain\David\pipelines\engines\pipeline\stations\classifier.py | B8: LAW_KEYWORDS | C8: L1_Gravitation | E8: 7 | F8: gravitational
A9: \\dlowenas\brain\David\pipelines\engines\pipeline\stations\classifier.py | B9: LAW_KEYWORDS | C9: L1_Gravitation | E9: 8 | F9: geodesic
A10: \\dlowenas\brain\David\pipelines\engines\pipeline\stations\classifier.py | B10: LAW_KEYWORDS | C10: L1_Gravitation | E10: 9 | F10: attraction
A11: \\dlowenas\brain\David\pipelines\engines\pipeline\stations\classifier.py | B11: LAW_KEYWORDS | C11: L1_Gravitation | E11: 10 | F11: weight
A12: \\dlowenas\brain\David\pipelines\engines\pipeline\stations\classifier.py | B12: LAW_KEYWORDS | C12: L2_Motion | E12: 1 | F12: force
A13: \\dlowenas\brain\David\pipelines\engines\pipeline\stations\classifier.py | B13: LAW_KEYWORDS | C13: L2_Motion | E13: 2 | F13: acceleration
... A98: \\dlowenas\brain\David\pipelines\engines\pipeline\stations\classifier.py | B98: LAW_KEYWORDS | C98: L10_Coherence | E98: 10 | F98: master equation

Sheet DOC_TYPE_PATTERNS
A1: source_file | B1: collection | C1: key | D1: subkey | E1: item_index | F1: value
A2: \\dlowenas\brain\David\pipelines\engines\pipeline\stations\classifier.py | B2: DOC_TYPE_PATTERNS | C2: paper | E2: 1 | F2: abstract
A3: \\dlowenas\brain\David\pipelines\engines\pipeline\stations\classifier.py | B3: DOC_TYPE_PATTERNS | C3: paper | E3: 2 | F3: introduction
A4: \\dlowenas\brain\David\pipelines\engines\pipeline\stations\classifier.py | B4: DOC_TYPE_PATTERNS | C4: paper | E4: 3 | F4: methodology
A5: \\dlowenas\brain\David\pipelines\engines\pipeline\stations\classifier.py | B5: DOC_TYPE_PATTERNS | C5: paper | E5: 4 | F5: conclusion
A6: \\dlowenas\brain\David\pipelines\engines\pipeline\stations\classifier.py | B6: DOC_TYPE_PATTERNS | C6: paper | E6: 5 | F6: references
A7: \\dlowenas\brain\David\pipelines\engines\pipeline\stations\classifier.py | B7: DOC_TYPE_PATTERNS | C7: paper | E7: 6 | F7: theorem
A8: \\dlowenas\brain\David\pipelines\engines\pipeline\stations\classifier.py | B8: DOC_TYPE_PATTERNS | C8: paper | E8: 7 | F8: proof
A9: \\dlowenas\brain\David\pipelines\engines\pipeline\stations\classifier.py | B9: DOC_TYPE_PATTERNS | C9: paper | E9: 8 | F9: lemma
A10: \\dlowenas\brain\David\pipelines\engines\pipeline\stations\classifier.py | B10: DOC_TYPE_PATTERNS | C10: article | E10: 1 | F10: subscribe
A11: \\dlowenas\brain\David\pipelines\engines\pipeline\stations\classifier.py | B11: DOC_TYPE_PATTERNS | C11: article | E11: 2 | F11: read more
A12: \\dlowenas\brain\David\pipelines\engines\pipeline\stations\classifier.py | B12: DOC_TYPE_PATTERNS | C12: article | E12: 3 | F12: published
A13: \\dlowenas\brain\David\pipelines\engines\pipeline\stations\classifier.py | B13: DOC_TYPE_PATTERNS | C13: article | E13: 4 | F13: blog
... A30: \\dlowenas\brain\David\pipelines\engines\pipeline\stations\classifier.py | B30: DOC_TYPE_PATTERNS | C30: code | E30: 5 | F30: const

Sheet SEMANTIC_BUCKETS
A1: term | B1: bucket | C1: subbucket | D1: polarity | E1: weight | F1: danger_level | G1: allowed_context | H1: forbidden_context | I1: recommended_action | J1: source_note | K1: example_safe_rewrite
A2: suggests | B2: CLAIM_STRENGTH | C2: weak_inference | D2: neutral | E2: 1 | F2: low | G2: exploratory interpretation; preliminary evidence | H2: final proof language | I2: usually safe; may be too weak if formal proof exists | J2: added from requested synonym expansion | K2: This suggests a possible constraint rather than proving the full claim.
A3: may indicate | B3: CLAIM_STRENGTH | C3: weak_inference | D3: neutral | E3: 1 | F3: low | G3: exploratory interpretation; preliminary evidence | H3: final proof language | I3: usually safe; may be too weak if formal proof exists | J3: added from requested synonym expansion | K3: This suggests a possible constraint rather than proving the full claim.
A4: is consistent with | B4: CLAIM_STRENGTH | C4: weak_inference | D4: neutral | E4: 1 | F4: low | G4: exploratory interpretation; preliminary evidence | H4: final proof language | I4: usually safe; may be too weak if formal proof exists | J4: added from requested synonym expansion | K4: This suggests a possible constraint rather than proving the full claim.
A5: points toward | B5: CLAIM_STRENGTH | C5: weak_inference | D5: neutral | E5: 1 | F5: low | G5: exploratory interpretation; preliminary evidence | H5: final proof language | I5: usually safe; may be too weak if formal proof exists | J5: added from requested synonym expansion | K5: This suggests a possible constraint rather than proving the full claim.
A6: raises the possibility | B6: CLAIM_STRENGTH | C6: weak_inference | D6: neutral | E6: 1 | F6: low | G6: exploratory interpretation; preliminary evidence | H6: final proof language | I6: usually safe; may be too weak if formal proof exists | J6: added from requested synonym expansion | K6: This suggests a possible constraint rather than proving the full claim.
A7: appears to support | B7: CLAIM_STRENGTH | C7: weak_inference | D7: neutral | E7: 1 | F7: low | G7: exploratory interpretation; preliminary evidence | H7: final proof language | I7: usually safe; may be too weak if formal proof exists | J7: added from requested synonym expansion | K7: This suggests a possible constraint rather than proving the full claim.
A8: is compatible with | B8: CLAIM_STRENGTH | C8: weak_inference | D8: neutral | E8: 1 | F8: low | G8: exploratory interpretation; preliminary evidence | H8: final proof language | I8: usually safe; may be too weak if formal proof exists | J8: added from requested synonym expansion | K8: This suggests a possible constraint rather than proving the full claim.
A9: could imply | B9: CLAIM_STRENGTH | C9: weak_inference | D9: neutral | E9: 1 | F9: low | G9: exploratory interpretation; preliminary evidence | H9: final proof language | I9: usually safe; may be too weak if formal proof exists | J9: added from requested synonym expansion | K9: This suggests a possible constraint rather than proving the full claim.
A10: supports | B10: CLAIM_STRENGTH | C10: moderate_claim | D10: neutral | E10: 3 | F10: medium | G10: model results; source-backed argument; structural mapping | H10: claiming formal proof without theorem/evidence | I10: require evidence marker or model/proof reference | J10: added from requested synonym expansion | K10: The model constrains the class of systems rather than deriving every domain equation.
A11: explains | B11: CLAIM_STRENGTH | C11: moderate_claim | D11: neutral | E11: 3 | F11: medium | G11: model results; source-backed argument; structural mapping | H11: claiming formal proof without theorem/evidence | I11: require evidence marker or model/proof reference | J11: added from requested synonym expansion | K11: The model constrains the class of systems rather than deriving every domain equation.
A12: accounts for | B12: CLAIM_STRENGTH | C12: moderate_claim | D12: neutral | E12: 3 | F12: medium | G12: model results; source-backed argument; structural mapping | H12: claiming formal proof without theorem/evidence | I12: require evidence marker or model/proof reference | J12: added from requested synonym expansion | K12: The model constrains the class of systems rather than deriving every domain equation.
A13: constrains | B13: CLAIM_STRENGTH | C13: moderate_claim | D13: neutral | E13: 3 | F13: medium | G13: model results; source-backed argument; structural mapping | H13: claiming formal proof without theorem/evidence | I13: require evidence marker or model/proof reference | J13: added from requested synonym expansion | K13: The model constrains the class of systems rather than deriving every domain equation.
... A348: destructive certainty | B348: ANTI_FRUIT_BEHAVIOR_EXPANSION | C348: anti_fruit | D348: negative | E348: 4 | F348: medium | G348: anti-fruit detection; adversarial critique | H348: none | I348: flag as anti-fruit signal; inspect context | J348: anti-fruit semantic expansion | K348: The language signals compulsion rather than self-control.

Sheet LEXICON_ADDITIONS_README
A1: Section | B1: What changed | C1: How to use it | D1: Notes
A2: SEMANTIC_BUCKETS | B2: Added claim-strength, reduction-quality, relation-type, evidence-maturity, formal-proof, falsification, drift, theology-status, reviewer-risk, methods/provenance, fruit and anti-fruit expansions. | C2: Use this as the canonical weighted term table for the next auditor script. | D2: This does not overwrite the existing sheets.
A3: CLAIM_STRENGTH | B3: Weak/moderate/strong/forbidden language levels. | C3: Flag strong terms unless proof/evidence markers are nearby. | D3: Especially catches proof-language drift.
A4: REDUCTION_QUALITY | B4: Exact/approximate/analogical/broken reduction terms. | C4: Use to enforce the Jim pivot. | D4: Prevents Prism derivation drift.
A5: RELATION_TYPE | B5: Identity, causation, constraint, correlation, analogy, dependency, entailment terms. | C5: Detect relation drift inside arguments. | D5: Most papers overreach by sliding relation type.
A6: FORMAL_PROOF | B6: Lean-safe terms and forbidden phrases. | C6: Require theorem scope for Lean claims. | D6: Lean verifies encoded structures, not historical/metaphysical reality by itself.
A7: FRUIT/ANTI-FRUIT | B7: Behavior-level synonyms for fruit and anti-fruit detection. | C7: Use for moral/character semantic scoring. | D7: These are behavioral signals, not automatic judgments.

Sheet SEMANTIC_BUCKETS_SUMMARY
A1: Metric | B1: Value | C1: Notes
A2: Total added semantic rows | B2: 347 | C2: Rows added to SEMANTIC_BUCKETS
A4: Bucket | B4: Count | C4: Notes
A5: ANTI_FRUIT_BEHAVIOR_EXPANSION | B5: 21
A6: CLAIM_STRENGTH | B6: 36
A7: DANGER_LANGUAGE | B7: 7
A8: DRIFT_WARNING | B8: 18
A9: EVIDENCE_MATURITY | B9: 18
A10: FALSIFICATION | B10: 20
A11: FORMAL_PROOF | B11: 31
A12: FRUIT_BEHAVIOR_EXPANSION | B12: 58
A13: METHODS_PROVENANCE | B13: 27
A14: PREFERRED_REPLACEMENT | B14: 16
A15: REDUCTION_QUALITY | B15: 30
A16: RELATION_TYPE | B16: 35
... A18: THEOLOGICAL_STATUS | B18: 17
A20: Danger Level | B20: Count | C20: Notes
A21: critical | B21: 26
A22: high | B22: 50
A23: low | B23: 195
A24: medium | B24: 76
